Workbook

Sheet PRUEBA
C1: IDENTIFICACION | F1: IR.1.1.10 Al finalizar el Programa, 540 familias de los municipios de LC, SSY y SRN tienen acceso a agua potable de calidad de forma continuo y sostenible. | N1: IR.1.1.13 Al finalizar el programa 24 CAPS de la zona de intervención han entregado al INAA todos los requisitos para su legalización, según el procedimiento de la ley 722 de CAPS. IR.1.1.21 12 CAPS con participación de al menos un 50% de mujeres en la toma de decisiones | W1: IR.1.1.16 24 CAPS logran mantener como mínimo un 10% extra sobre sus costos de funcionamiento mensual. | Z1: IR.1.1.17 24 CAPS cuentan e implementan un plan de operación y mantenimiento… | AJ1: IR.1.1.14 24 CAPS realizan asambleas comunitarias de rendición de cuentas conforme a su Reglamento Interno. | AU1: IR.1.1.20 24 CAPS recogen en sus planes de acción y reglamento interno medidas y acciones positivas dirigidas a promover la participación activa de las mujeres | AX1: IR.1.1.10 Al finalizar el Programa, 540 familias de los municipios de LC, SSY y SRN tienen acceso a agua potable de calidad de forma continuo y sostenible.
A2: HOJAS RELACIONADAS PARA REGRESAR HAGA CLICK è | F2: Utilizar Hoja Org_CAPS | N2: Hoja "Entrevista_CAPS" | U2: Hoja Gestión_ CAPS | W2: Hoja " Entrevista_CAPS" | AN2: Hoja " Est_Conservación" | AU2: IR.1.1.20Género!A1 | AX2: Ind.Sostenib.!A1 | BD2: INSTRUCCIONES PARA EL CALCULO DEL INDICE DE SOSTENIBILIDAD
A3: Municipio | B3: Microregión /Distrito | C3: Comunidad/CAPS | D3: Tipo de Sistema | E3: Tiempo de Conformación | F3: A.Organización | N3: B.Capital Social | U3: C.Autogestión | W3: D.Recuperación de costes | Z3: E.Operación & Mantenimiento | AC3: F.Salud Comunitaria y Ambiental | AJ3: G.Rendición de cuentas | AN3: H.Estado y conservación sistema | AU3: I.Incorporacion del enfoque de Gènero | AX3: Indice de Sostenibilidad MABE | BA3: Indice de Sostenbilidad MAG
F4: nº miembros totales | G4: Val | H4: Legalización | I4: 50% particip. Mujeres | J4: Val | K4: Capacidad Convocatoria | L4: Val | M4: A | N4: Red CAPs | O4: CMC | P4: COMACO | Q4: CMR | R4: CPC | S4: CAS | T4: B | U4: C1 | V4: Val | W4: D1 | X4: D2 | Y4: D | Z4: E1 | AA4: E2 | AB4: E | AC4: F1 | AD4: F2 | AE4: F3 | AF4: F4 | AG4: F5 | AH4: F6 | AI4: F | AJ4: G1 | AK4: G2 | AL4: G3 | AM4: G | AN4: H1 | AO4: Val | AP4: H2 | AQ4: Val | AR4: H3 | AS4: H4 | AT4: H | AU4: A | AV4: B | AW4: I | AX4: 0-5 años | AY4: 5-10 años | AZ4: màs de 10 años | BA4: 0-5 años | BB4: 5-10 años | BC4: màs de 10 años
A5: SRN | B5: 1 | C5: 1- El Diamante/ San Martin | D5: MABE | E5: mas de 10 años | F5: 9 | G5: =IF(F5>=4,1,IF(F5<4,0)) -> 1 | H5: 1 | I5: 0.44 | J5: =IF(I5>=0.5,1,0) -> 0 | K5: 3 | L5: =IF(K5>=2,1,IF(K5<2,0)) -> 1 | M5: =SUM(G5*0.2+H5*0.3+J5*0.2+L5*0.3) -> 0.8 | N5: 1 | O5: 1 | P5: 0 | Q5: 0 | R5: 1 | S5: 1 | T5: =IF((N5+O5+P5+Q5+S5)>=2,1,IF((N5+O5+P5+Q5+S5)<2,0)) -> 1 | U5: 3 | V5: =IF(U5>=2,1,IF(U5<2,0)) -> 1 | W5: 1 | X5: 1 | Y5: =IF((W5+X5)=2,1,IF((W5+X5)<2,0)) -> 1 | Z5: 0 | AA5: 0 | AB5: =Z5*AA5 -> 0 | AC5: 0 | AD5: 1 | AE5: 1 | AF5: 1 | AG5: 0 | AH5: 1 | AI5: =IF(SUM(AC5:AH5)>=3,1,IF(SUM(AC5:AH5)<3,0)) -> 1 | AJ5: 1 | AK5: 1 | AL5: 1 | AM5: =IF(SUM(AJ5:AL5)>=3,1,IF(SUM(AJ5:AL5)<3,0)) -> 1 | AN5: 5 | AO5: =IF(AN5>=3,1,0) -> 1 | AP5: 5 | AQ5: =IF(AP5>=4,1,0) -> 1 | AR5: 0 | AS5: 1 | AT5: =(AO5*0.3)+(AQ5*0.3)+(AR5*0.2)+(AS5*0.2) -> 0.8 | AU5: 0 | AV5: 0 | AW5: =+(AU5*0.6)+(AV5*0.4) -> 0 | AZ5: =((M5*0.1)+(T5*0.05)+(V5*0.2)+(Y5*0.2)+(AB5*0.15)+(AI5*0.05)+(AM5*0.1)+(AT5*0.05)+(AW5*0.1)*100) -> 0.72 | BD5: Para el càlculo del Indice de la sostenibilidad de los sistemas se utilizará la tabla de la hoja Indic_sostenibilidad ( porcentajes según el sistema y conservación construcción),la fórmula a colocar será la suma de la ùltima columna, ejemplo la A,B,C.... H de cada medición pòr el porcentaje correspondiente segùn tabla de indicadores. Para ejemplificar: ((M6*0,15)+(T6*0,05)+(V6+0,15)+(Y6*0,15)+(AB6*0,15)+(AI6*0,15)+(AM6*0,05)+(AT6*0,10)+(AW6*0,10)+100)
A6: SRN | C6: 2- La Breiera | D6: MAG | E6: 5 - 10 años | F6: 6 | G6: =IF(F6>=4,1,IF(F6<4,0)) -> 1 | H6: 0 | I6: 0.55 | J6: =IF(I6>=0.5,1,0) -> 1 | K6: 5 | L6: =IF(K6>=2,1,IF(K6<2,0)) -> 1 | M6: =SUM(G6*0.2+H6*0.3+J6*0.2+L6*0.3) -> 0.7 | N6: 1 | O6: 0 | P6: 0 | Q6: 0 | R6: 1 | S6: 1 | T6: =IF((N6+O6+P6+Q6+S6)>=2,1,IF((N6+O6+P6+Q6+S6)<2,0)) -> 1 | U6: 3 | V6: =IF(U6>=2,1,IF(U6<2,0)) -> 1 | W6: 0 | X6: 1 | Y6: =IF((W6+X6)=2,1,IF((W6+X6)<2,0)) -> 0 | Z6: 0 | AA6: 1 | AB6: =Z6*AA6 -> 0 | AC6: 0 | AD6: 1 | AE6: 0 | AF6: 1 | AG6: 1 | AH6: 0 | AI6: =IF(SUM(AC6:AH6)>=3,1,IF(SUM(AC6:AH6)<3,0)) -> 1 | AJ6: 0 | AK6: 1 | AL6: 1 | AM6: =IF(SUM(AJ6:AL6)>=3,1,IF(SUM(AJ6:AL6)<3,0)) -> 0 | AN6: 2 | AO6: =IF(AN6>=3,1,0) -> 0 | AP6: 6 | AQ6: =IF(AP6>=4,1,0) -> 1 | AR6: 0 | AS6: 1 | AT6: =(AO6*0.3)+(AQ6*0.3)+(AR6*0.2)+(AS6*0.2) -> 0.5 | AU6: 0 | AV6: 0 | AW6: =+(AU6*0.6)+(AV6*0.4) -> 0 | BB6: =((M6*0.15)+(T6*0.05)+(V6*0.15)+(Y6*0.15)+(AB6*0.15)+(AI6*0.1)+(AM6*0.1)+(AT6*0.05)+(AW6*0.1)*100) -> 0.43
A7: SRN | C7: 3- Valle de Suni | D7: MABE | E7: 0 - 5 años | F7: 6 | G7: =IF(F7>=4,1,IF(F7<4,0)) -> 1 | I7: 0.5 | J7: =IF(I7>=0.5,1,0) -> 1 | L7: =IF(K7>=2,1,IF(K7<2,0)) -> 0 | M7: =SUM(G7*0.2+H7*0.3+J7*0.2+L7*0.3) -> 0.4 | T7: =IF((N7+O7+P7+Q7+S7)>=2,1,IF((N7+O7+P7+Q7+S7)<2,0)) -> 0 | V7: =IF(U7>=2,1,IF(U7<2,0)) -> 0 | Y7: =IF((W7+X7)=2,1,IF((W7+X7)<2,0)) -> 0 | AB7: =Z7*AA7 -> 0 | AI7: =IF(SUM(AC7:AH7)>=3,1,IF(SUM(AC7:AH7)<3,0)) -> 0 | AM7: =IF(SUM(AJ7:AL7)>=3,1,IF(SUM(AJ7:AL7)<3,0)) -> 0 | AO7: =IF(AN7>=3,1,0) -> 0 | AQ7: =IF(AP7>=4,1,0) -> 0 | AT7: =(AO7*0.3)+(AQ7*0.3)+(AR7*0.2)+(AS7*0.2) -> 0 | AV7: 0 | AW7: =+(AU7*0.6)+(AV7*0.4) -> 0 | AX7: =((M7*0.15)+(T7*0.05)+(V7*0.15)+(Y7*0.15)+(AB7*0.15)+(AI7*0.05)+(AM7*0.1)+(AT7*0.1)+(AW7*0.1)*100) -> 0.06
A8: SRN | C8: 4- El Espino | D8: MAG | E8: mas de 10 años | G8: =IF(F8>=4,1,IF(F8<4,0)) -> 0 | J8: =IF(I8>=0.5,1,0) -> 0 | L8: =IF(K8>=2,1,IF(K8<2,0)) -> 0 | M8: =SUM(G8*0.2+H8*0.3+J8*0.2+L8*0.3) -> 0 | T8: =IF((N8+O8+P8+Q8+S8)>=2,1,IF((N8+O8+P8+Q8+S8)<2,0)) -> 0 | V8: =IF(U8>=2,1,IF(U8<2,0)) -> 0 | Y8: =IF((W8+X8)=2,1,IF((W8+X8)<2,0)) -> 0 | AB8: =Z8*AA8 -> 0 | AI8: =IF(SUM(AC8:AH8)>=3,1,IF(SUM(AC8:AH8)<3,0)) -> 0 | AM8: =IF(SUM(AJ8:AL8)>=3,1,IF(SUM(AJ8:AL8)<3,0)) -> 0 | AO8: =IF(AN8>=3,1,0) -> 0 | AQ8: =IF(AP8>=4,1,0) -> 0 | AT8: =(AO8*0.3)+(AQ8*0.3)+(AR8*0.2)+(AS8*0.2) -> 0 | AV8: 0 | AW8: =+(AU8*0.6)+(AV8*0.4) -> 0 | BC8: =((M8*0.1)+(T8*0.05)+(V8*0.2)+(Y7*0.2)+(AB8*0.1)+(AI8*0.05)+(AM8*0.15)+(AT8*0.05)+(AW8*0.1)*100) -> 0
A9: SRN | C9: 5- San Marcos | D9: MAG | E9: mas de 10 años | G9: =IF(F9>=4,1,IF(F9<4,0)) -> 0 | J9: =IF(I9>=0.5,1,0) -> 0 | L9: =IF(K9>=2,1,IF(K9<2,0)) -> 0 | M9: =SUM(G9*0.2+H9*0.3+J9*0.2+L9*0.3) -> 0 | T9: =IF((N9+O9+P9+Q9+S9)>=2,1,IF((N9+O9+P9+Q9+S9)<2,0)) -> 0 | V9: =IF(U9>=2,1,IF(U9<2,0)) -> 0 | Y9: =IF((W9+X9)=2,1,IF((W9+X9)<2,0)) -> 0 | AB9: =Z9*AA9 -> 0 | AI9: =IF(SUM(AC9:AH9)>=3,1,IF(SUM(AC9:AH9)<3,0)) -> 0 | AM9: =IF(SUM(AJ9:AL9)>=3,1,IF(SUM(AJ9:AL9)<3,0)) -> 0 | AO9: =IF(AN9>=3,1,0) -> 0 | AQ9: =IF(AP9>=4,1,0) -> 0 | AT9: =(AO9*0.3)+(AQ9*0.3)+(AR9*0.2)+(AS9*0.2) -> 0 | AU9: 0 | AV9: 0 | AW9: =+(AU9*0.6)+(AV9*0.4) -> 0 | BC9: =((M9*0.1)+(T9*0.05)+(V9*0.2)+(Y8*0.2)+(AB9*0.1)+(AI9*0.05)+(AM9*0.15)+(AT9*0.05)+(AW9*0.1)*100) -> 0
A10: SRN | C10: 6- Los Arados | D10: MABE | E10: 0 - 5 años | G10: =IF(F10>=4,1,IF(F10<4,0)) -> 0 | J10: =IF(I10>=0.5,1,0) -> 0 | L10: =IF(K10>=2,1,IF(K10<2,0)) -> 0 | M10: =SUM(G10*0.2+H10*0.3+J10*0.2+L10*0.3) -> 0 | T10: =IF((N10+O10+P10+Q10+S10)>=2,1,IF((N10+O10+P10+Q10+S10)<2,0)) -> 0 | V10: =IF(U10>=2,1,IF(U10<2,0)) -> 0 | Y10: =IF((W10+X10)=2,1,IF((W10+X10)<2,0)) -> 0 | AB10: =Z10*AA10 -> 0 | AI10: =IF(SUM(AC10:AH10)>=3,1,IF(SUM(AC10:AH10)<3,0)) -> 0 | AM10: =IF(SUM(AJ10:AL10)>=3,1,IF(SUM(AJ10:AL10)<3,0)) -> 0 | AO10: =IF(AN10>=3,1,0) -> 0 | AQ10: =IF(AP10>=4,1,0) -> 0 | AT10: =(AO10*0.3)+(AQ10*0.3)+(AR10*0.2)+(AS10*0.2) -> 0 | AU10: 0 | AV10: 0 | AW10: =+(AU10*0.6)+(AV10*0.4) -> 0 | AX10: =((M10*0.15)+(T10*0.05)+(V10*0.15)+(Y10*0.15)+(AB10*0.15)+(AI10*0.05)+(AM10*0.1)+(AT10*0.1)+(AW10*0.1)*100) -> 0
A11: SRN | C11: 7- Lomas de Sacacli | D11: MABE | E11: 0 - 5 años | G11: =IF(F11>=4,1,IF(F11<4,0)) -> 0 | J11: =IF(I11>=0.5,1,0) -> 0 | L11: =IF(K11>=2,1,IF(K11<2,0)) -> 0 | M11: =SUM(G11*0.2+H11*0.3+J11*0.2+L11*0.3) -> 0 | T11: =IF((N11+O11+P11+Q11+S11)>=2,1,IF((N11+O11+P11+Q11+S11)<2,0)) -> 0 | V11: =IF(U11>=2,1,IF(U11<2,0)) -> 0 | Y11: =IF((W11+X11)=2,1,IF((W11+X11)<2,0)) -> 0 | AB11: =Z11*AA11 -> 0 | AI11: =IF(SUM(AC11:AH11)>=3,1,IF(SUM(AC11:AH11)<3,0)) -> 0 | AM11: =IF(SUM(AJ11:AL11)>=3,1,IF(SUM(AJ11:AL11)<3,0)) -> 0 | AO11: =IF(AN11>=3,1,0) -> 0 | AQ11: =IF(AP11>=4,1,0) -> 0 | AT11: =(AO11*0.3)+(AQ11*0.3)+(AR11*0.2)+(AS11*0.2) -> 0 | AU11: 0 | AV11: 0 | AW11: =+(AU11*0.6)+(AV11*0.4) -> 0 | AX11: =((M11*0.15)+(T11*0.05)+(V11*0.15)+(Y11*0.15)+(AB11*0.15)+(AI11*0.05)+(AM11*0.1)+(AT11*0.1)+(AW11*0.1)*100) -> 0
A12: SRN | C12: 8- Sacacli | D12: MABE | E12: 5 - 10 años | G12: =IF(F12>=4,1,IF(F12<4,0)) -> 0 | J12: =IF(I12>=0.5,1,0) -> 0 | L12: =IF(K12>=2,1,IF(K12<2,0)) -> 0 | M12: =SUM(G12*0.2+H12*0.3+J12*0.2+L12*0.3) -> 0 | T12: =IF((N12+O12+P12+Q12+S12)>=2,1,IF((N12+O12+P12+Q12+S12)<2,0)) -> 0 | V12: =IF(U12>=2,1,IF(U12<2,0)) -> 0 | Y12: =IF((W12+X12)=2,1,IF((W12+X12)<2,0)) -> 0 | AB12: =Z12*AA12 -> 0 | AI12: =IF(SUM(AC12:AH12)>=3,1,IF(SUM(AC12:AH12)<3,0)) -> 0 | AM12: =IF(SUM(AJ12:AL12)>=3,1,IF(SUM(AJ12:AL12)<3,0)) -> 0 | AO12: =IF(AN12>=3,1,0) -> 0 | AQ12: =IF(AP12>=4,1,0) -> 0 | AT12: =(AO12*0.3)+(AQ12*0.3)+(AR12*0.2)+(AS12*0.2) -> 0 | AU12: 0 | AV12: 0 | AW12: =+(AU12*0.6)+(AV12*0.4) -> 0 | AY12: =((M12*0.1)+(T12*0.05)+(V12*0.15)+(Y12*0.2)+(AB12*0.2)+(AI12*0.05)+(AM12*0.1)+(AT12*0.05)+(AW12*0.1)*100) -> 0
A13: SRN | C13: 9- Estación Cerro Grande | E13: No existe SAP | G13: =IF(F13>=4,1,IF(F13<4,0)) -> 0 | J13: =IF(I13>=0.5,1,0) -> 0 | L13: =IF(K13>=2,1,IF(K13<2,0)) -> 0 | M13: =SUM(G13*0.2+H13*0.3+J13*0.2+L13*0.3) -> 0 | T13: =IF((N13+O13+P13+Q13+S13)>=2,1,IF((N13+O13+P13+Q13+S13)<2,0)) -> 0 | V13: =IF(U13>=2,1,IF(U13<2,0)) -> 0 | Y13: =IF((W13+X13)=2,1,IF((W13+X13)<2,0)) -> 0 | AB13: =Z13*AA13 -> 0 | AI13: =IF(SUM(AC13:AH13)>=3,1,IF(SUM(AC13:AH13)<3,0)) -> 0 | AM13: =IF(SUM(AJ13:AL13)>=3,1,IF(SUM(AJ13:AL13)<3,0)) -> 0 | AO13: =IF(AN13>=3,1,0) -> 0 | AQ13: =IF(AP13>=4,1,0) -> 0 | AT13: =(AO13*0.3)+(AQ13*0.3)+(AR13*0.2)+(AS13*0.2) -> 0 | AU13: 0 | AV13: 0 | AW13: =+(AU13*0.6)+(AV13*0.4) -> 0
A14: LC | C14: 10- Valerio | D14: MABE | E14: 5- 10 años | G14: =IF(F14>=4,1,IF(F14<4,0)) -> 0 | J14: =IF(I14>=0.5,1,0) -> 0 | L14: =IF(K14>=2,1,IF(K14<2,0)) -> 0 | M14: =SUM(G14*0.2+H14*0.3+J14*0.2+L14*0.3) -> 0 | T14: =IF((N14+O14+P14+Q14+S14)>=2,1,IF((N14+O14+P14+Q14+S14)<2,0)) -> 0 | V14: =IF(U14>=2,1,IF(U14<2,0)) -> 0 | Y14: =IF((W14+X14)=2,1,IF((W14+X14)<2,0)) -> 0 | AB14: =Z14*AA14 -> 0 | AI14: =IF(SUM(AC14:AH14)>=3,1,IF(SUM(AC14:AH14)<3,0)) -> 0 | AM14: =IF(SUM(AJ14:AL14)>=3,1,IF(SUM(AJ14:AL14)<3,0)) -> 0 | AO14: =IF(AN14>=3,1,0) -> 0 | AQ14: =IF(AP14>=4,1,0) -> 0 | AT14: =(AO14*0.3)+(AQ14*0.3)+(AR14*0.2)+(AS14*0.2) -> 0 | AU14: 0 | AV14: 0 | AW14: =+(AU14*0.6)+(AV14*0.4) -> 0 | AY14: =((M14*0.1)+(T14*0.05)+(V14*0.15)+(Y14*0.2)+(AB14*0.2)+(AI14*0.05)+(AM14*0.1)+(AT14*0.05)+(AW14*0.1)*100) -> 0
A15: LC | C15: 11- Yupali | D15: MABE | E15: 5- 10 años | G15: =IF(F15>=4,1,IF(F15<4,0)) -> 0 | J15: =IF(I15>=0.5,1,0) -> 0 | L15: =IF(K15>=2,1,IF(K15<2,0)) -> 0 | M15: =SUM(G15*0.2+H15*0.3+J15*0.2+L15*0.3) -> 0 | T15: =IF((N15+O15+P15+Q15+S15)>=2,1,IF((N15+O15+P15+Q15+S15)<2,0)) -> 0 | V15: =IF(U15>=2,1,IF(U15<2,0)) -> 0 | Y15: =IF((W15+X15)=2,1,IF((W15+X15)<2,0)) -> 0 | AB15: =Z15*AA15 -> 0 | AI15: =IF(SUM(AC15:AH15)>=3,1,IF(SUM(AC15:AH15)<3,0)) -> 0 | AM15: =IF(SUM(AJ15:AL15)>=3,1,IF(SUM(AJ15:AL15)<3,0)) -> 0 | AO15: =IF(AN15>=3,1,0) -> 0 | AQ15: =IF(AP15>=4,1,0) -> 0 | AT15: =(AO15*0.3)+(AQ15*0.3)+(AR15*0.2)+(AS15*0.2) -> 0 | AU15: 0 | AV15: 0 | AW15: =+(AU15*0.6)+(AV15*0.4) -> 0 | AY15: =((M15*0.1)+(T15*0.05)+(V15*0.15)+(Y15*0.2)+(AB15*0.2)+(AI15*0.05)+(AM15*0.1)+(AT15*0.05)+(AW15*0.1)*100) -> 0
A16: LC | C16: 12- Gracalcan | D16: MAG | E16: 5- 10 años | G16: =IF(F16>=4,1,IF(F16<4,0)) -> 0 | J16: =IF(I16>=0.5,1,0) -> 0 | L16: =IF(K16>=2,1,IF(K16<2,0)) -> 0 | M16: =SUM(G16*0.2+H16*0.3+J16*0.2+L16*0.3) -> 0 | T16: =IF((N16+O16+P16+Q16+S16)>=2,1,IF((N16+O16+P16+Q16+S16)<2,0)) -> 0 | V16: =IF(U16>=2,1,IF(U16<2,0)) -> 0 | Y16: =IF((W16+X16)=2,1,IF((W16+X16)<2,0)) -> 0 | AB16: =Z16*AA16 -> 0 | AI16: =IF(SUM(AC16:AH16)>=3,1,IF(SUM(AC16:AH16)<3,0)) -> 0 | AM16: =IF(SUM(AJ16:AL16)>=3,1,IF(SUM(AJ16:AL16)<3,0)) -> 0 | AO16: =IF(AN16>=3,1,0) -> 0 | AQ16: =IF(AP16>=4,1,0) -> 0 | AT16: =(AO16*0.3)+(AQ16*0.3)+(AR16*0.2)+(AS16*0.2) -> 0 | AU16: 0 | AV16: 0 | AW16: =+(AU16*0.6)+(AV16*0.4) -> 0 | BB16: =((M16*0.15)+(T16*0.05)+(V16*0.15)+(Y16*0.15)+(AB16*0.15)+(AI16*0.1)+(AM16*0.1)+(AT16*0.05)+(AW16*0.1)*100) -> 0
A17: LC | C17: 13- Agua Fria | D17: MAG | E17: 5- 10 años | G17: =IF(F17>=4,1,IF(F17<4,0)) -> 0 | J17: =IF(I17>=0.5,1,0) -> 0 | L17: =IF(K17>=2,1,IF(K17<2,0)) -> 0 | M17: =SUM(G17*0.2+H17*0.3+J17*0.2+L17*0.3) -> 0 | T17: =IF((N17+O17+P17+Q17+S17)>=2,1,IF((N17+O17+P17+Q17+S17)<2,0)) -> 0 | V17: =IF(U17>=2,1,IF(U17<2,0)) -> 0 | Y17: =IF((W17+X17)=2,1,IF((W17+X17)<2,0)) -> 0 | AB17: =Z17*AA17 -> 0 | AI17: =IF(SUM(AC17:AH17)>=3,1,IF(SUM(AC17:AH17)<3,0)) -> 0 | AM17: =IF(SUM(AJ17:AL17)>=3,1,IF(SUM(AJ17:AL17)<3,0)) -> 0 | AO17: =IF(AN17>=3,1,0) -> 0 | AQ17: =IF(AP17>=4,1,0) -> 0 | AT17: =(AO17*0.3)+(AQ17*0.3)+(AR17*0.2)+(AS17*0.2) -> 0 | AU17: 0 | AV17: 0 | AW17: =+(AU17*0.6)+(AV17*0.4) -> 0 | BB17: =((M17*0.15)+(T17*0.05)+(V17*0.15)+(Y17*0.15)+(AB17*0.15)+(AI17*0.1)+(AM17*0.1)+(AT17*0.05)+(AW17*0.1)*100) -> 0
A18: LC | C18: 14- Zapote Oriental | D18: MABE | E18: 0 - 5 años | G18: =IF(F18>=4,1,IF(F18<4,0)) -> 0 | J18: =IF(I18>=0.5,1,0) -> 0 | L18: =IF(K18>=2,1,IF(K18<2,0)) -> 0 | M18: =SUM(G18*0.2+H18*0.3+J18*0.2+L18*0.3) -> 0 | T18: =IF((N18+O18+P18+Q18+S18)>=2,1,IF((N18+O18+P18+Q18+S18)<2,0)) -> 0 | V18: =IF(U18>=2,1,IF(U18<2,0)) -> 0 | Y18: =IF((W18+X18)=2,1,IF((W18+X18)<2,0)) -> 0 | AB18: =Z18*AA18 -> 0 | AI18: =IF(SUM(AC18:AH18)>=3,1,IF(SUM(AC18:AH18)<3,0)) -> 0 | AM18: =IF(SUM(AJ18:AL18)>=3,1,IF(SUM(AJ18:AL18)<3,0)) -> 0 | AO18: =IF(AN18>=3,1,0) -> 0 | AQ18: =IF(AP18>=4,1,0) -> 0 | AT18: =(AO18*0.3)+(AQ18*0.3)+(AR18*0.2)+(AS18*0.2) -> 0 | AU18: 0 | AV18: 0 | AW18: =+(AU18*0.6)+(AV18*0.4) -> 0 | AX18: =((M18*0.15)+(T18*0.05)+(V18*0.15)+(Y18*0.15)+(AB18*0.15)+(AI18*0.05)+(AM18*0.1)+(AT18*0.1)+(AW18*0.1)*100) -> 0
A19: LC | C19: 15- Santiago del Coyolito | D19: MABE | E19: 5 - 10 años | G19: =IF(F19>=4,1,IF(F19<4,0)) -> 0 | J19: =IF(I19>=0.5,1,0) -> 0 | L19: =IF(K19>=2,1,IF(K19<2,0)) -> 0 | M19: =SUM(G19*0.2+H19*0.3+J19*0.2+L19*0.3) -> 0 | T19: =IF((N19+O19+P19+Q19+S19)>=2,1,IF((N19+O19+P19+Q19+S19)<2,0)) -> 0 | V19: =IF(U19>=2,1,IF(U19<2,0)) -> 0 | Y19: =IF((W19+X19)=2,1,IF((W19+X19)<2,0)) -> 0 | AB19: =Z19*AA19 -> 0 | AI19: =IF(SUM(AC19:AH19)>=3,1,IF(SUM(AC19:AH19)<3,0)) -> 0 | AM19: =IF(SUM(AJ19:AL19)>=3,1,IF(SUM(AJ19:AL19)<3,0)) -> 0 | AO19: =IF(AN19>=3,1,0) -> 0 | AQ19: =IF(AP19>=4,1,0) -> 0 | AT19: =(AO19*0.3)+(AQ19*0.3)+(AR19*0.2)+(AS19*0.2) -> 0 | AU19: 0 | AV19: 0 | AW19: =+(AU19*0.6)+(AV19*0.4) -> 0 | AY19: =((M19*0.1)+(T19*0.05)+(V19*0.15)+(Y19*0.2)+(AB19*0.2)+(AI19*0.05)+(AM19*0.1)+(AT19*0.05)+(AW19*0.1)*100) -> 0
A20: LC | C20: 16- Las Quebradas | E20: No existe SAP | G20: =IF(F20>=4,1,IF(F20<4,0)) -> 0 | J20: =IF(I20>=0.5,1,0) -> 0 | L20: =IF(K20>=2,1,IF(K20<2,0)) -> 0 | M20: =SUM(G20*0.2+H20*0.3+J20*0.2+L20*0.3) -> 0 | T20: =IF((N20+O20+P20+Q20+S20)>=2,1,IF((N20+O20+P20+Q20+S20)<2,0)) -> 0 | V20: =IF(U20>=2,1,IF(U20<2,0)) -> 0 | Y20: =IF((W20+X20)=2,1,IF((W20+X20)<2,0)) -> 0 | AB20: =Z20*AA20 -> 0 | AI20: =IF(SUM(AC20:AH20)>=3,1,IF(SUM(AC20:AH20)<3,0)) -> 0 | AM20: =IF(SUM(AJ20:AL20)>=3,1,IF(SUM(AJ20:AL20)<3,0)) -> 0 | AO20: =IF(AN20>=3,1,0) -> 0 | AQ20: =IF(AP20>=4,1,0) -> 0 | AT20: =(AO20*0.3)+(AQ20*0.3)+(AR20*0.2)+(AS20*0.2) -> 0 | AU20: 0 | AV20: 0 | AW20: =+(AU20*0.6)+(AV20*0.4) -> 0
A21: SSY | C21: 17- La Naranjita | D21: MAG | E21: 0 - 5 años | G21: =IF(F21>=4,1,IF(F21<4,0)) -> 0 | J21: =IF(I21>=0.5,1,0) -> 0 | L21: =IF(K21>=2,1,IF(K21<2,0)) -> 0 | M21: =SUM(G21*0.2+H21*0.3+J21*0.2+L21*0.3) -> 0 | T21: =IF((N21+O21+P21+Q21+S21)>=2,1,IF((N21+O21+P21+Q21+S21)<2,0)) -> 0 | V21: =IF(U21>=2,1,IF(U21<2,0)) -> 0 | Y21: =IF((W21+X21)=2,1,IF((W21+X21)<2,0)) -> 0 | AB21: =Z21*AA21 -> 0 | AI21: =IF(SUM(AC21:AH21)>=3,1,IF(SUM(AC21:AH21)<3,0)) -> 0 | AM21: =IF(SUM(AJ21:AL21)>=3,1,IF(SUM(AJ21:AL21)<3,0)) -> 0 | AO21: =IF(AN21>=3,1,0) -> 0 | AQ21: =IF(AP21>=4,1,0) -> 0 | AT21: =(AO21*0.3)+(AQ21*0.3)+(AR21*0.2)+(AS21*0.2) -> 0 | AU21: 0 | AV21: 0 | AW21: =+(AU21*0.6)+(AV21*0.4) -> 0 | BA21: =((M21*0.15)+(T21*0.05)+(V21*0.15)+(Y21*0.15)+(AB21*0.15)+(AI21*0.05)+(AM21*0.1)+(AT21*0.1)+(AW21*0.1)*100) -> 0
A22: SSY | C22: 18- Los Prendedizos | D22: MAG | E22: 5 -10 años | G22: =IF(F22>=4,1,IF(F22<4,0)) -> 0 | J22: =IF(I22>=0.5,1,0) -> 0 | L22: =IF(K22>=2,1,IF(K22<2,0)) -> 0 | M22: =SUM(G22*0.2+H22*0.3+J22*0.2+L22*0.3) -> 0 | T22: =IF((N22+O22+P22+Q22+S22)>=2,1,IF((N22+O22+P22+Q22+S22)<2,0)) -> 0 | V22: =IF(U22>=2,1,IF(U22<2,0)) -> 0 | Y22: =IF((W22+X22)=2,1,IF((W22+X22)<2,0)) -> 0 | AB22: =Z22*AA22 -> 0 | AI22: =IF(SUM(AC22:AH22)>=3,1,IF(SUM(AC22:AH22)<3,0)) -> 0 | AM22: =IF(SUM(AJ22:AL22)>=3,1,IF(SUM(AJ22:AL22)<3,0)) -> 0 | AO22: =IF(AN22>=3,1,0) -> 0 | AQ22: =IF(AP22>=4,1,0) -> 0 | AT22: =(AO22*0.3)+(AQ22*0.3)+(AR22*0.2)+(AS22*0.2) -> 0 | AU22: 0 | AV22: 0 | AW22: =+(AU22*0.6)+(AV22*0.4) -> 0 | BB22: =((M22*0.15)+(T22*0.05)+(V22*0.15)+(Y22*0.15)+(AB22*0.15)+(AI22*0.1)+(AM22*0.1)+(AT22*0.05)+(AW22*0.1)*100) -> 0
A23: SSY | C23: 19- Las Trozas | D23: MAG | E23: 5 - 10 años | G23: =IF(F23>=4,1,IF(F23<4,0)) -> 0 | J23: =IF(I23>=0.5,1,0) -> 0 | L23: =IF(K23>=2,1,IF(K23<2,0)) -> 0 | M23: =SUM(G23*0.2+H23*0.3+J23*0.2+L23*0.3) -> 0 | T23: =IF((N23+O23+P23+Q23+S23)>=2,1,IF((N23+O23+P23+Q23+S23)<2,0)) -> 0 | V23: =IF(U23>=2,1,IF(U23<2,0)) -> 0 | Y23: =IF((W23+X23)=2,1,IF((W23+X23)<2,0)) -> 0 | AB23: =Z23*AA23 -> 0 | AI23: =IF(SUM(AC23:AH23)>=3,1,IF(SUM(AC23:AH23)<3,0)) -> 0 | AM23: =IF(SUM(AJ23:AL23)>=3,1,IF(SUM(AJ23:AL23)<3,0)) -> 0 | AO23: =IF(AN23>=3,1,0) -> 0 | AQ23: =IF(AP23>=4,1,0) -> 0 | AT23: =(AO23*0.3)+(AQ23*0.3)+(AR23*0.2)+(AS23*0.2) -> 0 | AU23: 0 | AV23: 0 | AW23: =+(AU23*0.6)+(AV23*0.4) -> 0 | BB23: =((M23*0.15)+(T23*0.05)+(V23*0.15)+(Y23*0.15)+(AB23*0.15)+(AI23*0.1)+(AM23*0.1)+(AT23*0.05)+(AW23*0.1)*100) -> 0
A24: SSY | C24: 20- Las Delicias | D24: MAG | E24: 0 - 5 años | G24: =IF(F24>=4,1,IF(F24<4,0)) -> 0 | J24: =IF(I24>=0.5,1,0) -> 0 | L24: =IF(K24>=2,1,IF(K24<2,0)) -> 0 | M24: =SUM(G24*0.2+H24*0.3+J24*0.2+L24*0.3) -> 0 | T24: =IF((N24+O24+P24+Q24+S24)>=2,1,IF((N24+O24+P24+Q24+S24)<2,0)) -> 0 | V24: =IF(U24>=2,1,IF(U24<2,0)) -> 0 | Y24: =IF((W24+X24)=2,1,IF((W24+X24)<2,0)) -> 0 | AB24: =Z24*AA24 -> 0 | AI24: =IF(SUM(AC24:AH24)>=3,1,IF(SUM(AC24:AH24)<3,0)) -> 0 | AM24: =IF(SUM(AJ24:AL24)>=3,1,IF(SUM(AJ24:AL24)<3,0)) -> 0 | AO24: =IF(AN24>=3,1,0) -> 0 | AQ24: =IF(AP24>=4,1,0) -> 0 | AT24: =(AO24*0.3)+(AQ24*0.3)+(AR24*0.2)+(AS24*0.2) -> 0 | AU24: 0 | AV24: 0 | AW24: =+(AU24*0.6)+(AV24*0.4) -> 0 | BA24: =((M24*0.15)+(T24*0.05)+(V24*0.15)+(Y24*0.15)+(AB24*0.15)+(AI24*0.05)+(AM24*0.1)+(AT24*0.1)+(AW24*0.1)*100) -> 0
A25: SSY | C25: 21- El Volcán | D25: MAG | E25: 5 - 10 años | G25: =IF(F25>=4,1,IF(F25<4,0)) -> 0 | J25: =IF(I25>=0.5,1,0) -> 0 | L25: =IF(K25>=2,1,IF(K25<2,0)) -> 0 | M25: =SUM(G25*0.2+H25*0.3+J25*0.2+L25*0.3) -> 0 | T25: =IF((N25+O25+P25+Q25+S25)>=2,1,IF((N25+O25+P25+Q25+S25)<2,0)) -> 0 | V25: =IF(U25>=2,1,IF(U25<2,0)) -> 0 | Y25: =IF((W25+X25)=2,1,IF((W25+X25)<2,0)) -> 0 | AB25: =Z25*AA25 -> 0 | AI25: =IF(SUM(AC25:AH25)>=3,1,IF(SUM(AC25:AH25)<3,0)) -> 0 | AM25: =IF(SUM(AJ25:AL25)>=3,1,IF(SUM(AJ25:AL25)<3,0)) -> 0 | AO25: =IF(AN25>=3,1,0) -> 0 | AQ25: =IF(AP25>=4,1,0) -> 0 | AT25: =(AO25*0.3)+(AQ25*0.3)+(AR25*0.2)+(AS25*0.2) -> 0 | AU25: 0 | AV25: 0 | AW25: =+(AU25*0.6)+(AV25*0.4) -> 0 | BB25: =((M25*0.15)+(T25*0.05)+(V25*0.15)+(Y25*0.15)+(AB25*0.15)+(AI25*0.1)+(AM25*0.1)+(AT25*0.05)+(AW25*0.1)*100) -> 0
A26: SSY | C26: 22- El Regadio | D26: MAG | E26: 0- 5 años | G26: =IF(F26>=4,1,IF(F26<4,0)) -> 0 | J26: =IF(I26>=0.5,1,0) -> 0 | L26: =IF(K26>=2,1,IF(K26<2,0)) -> 0 | M26: =SUM(G26*0.2+H26*0.3+J26*0.2+L26*0.3) -> 0 | T26: =IF((N26+O26+P26+Q26+S26)>=2,1,IF((N26+O26+P26+Q26+S26)<2,0)) -> 0 | V26: =IF(U26>=2,1,IF(U26<2,0)) -> 0 | Y26: =IF((W26+X26)=2,1,IF((W26+X26)<2,0)) -> 0 | AB26: =Z26*AA26 -> 0 | AI26: =IF(SUM(AC26:AH26)>=3,1,IF(SUM(AC26:AH26)<3,0)) -> 0 | AM26: =IF(SUM(AJ26:AL26)>=3,1,IF(SUM(AJ26:AL26)<3,0)) -> 0 | AO26: =IF(AN26>=3,1,0) -> 0 | AQ26: =IF(AP26>=4,1,0) -> 0 | AT26: =(AO26*0.3)+(AQ26*0.3)+(AR26*0.2)+(AS26*0.2) -> 0 | AU26: 0 | AV26: 0 | AW26: =+(AU26*0.6)+(AV26*0.4) -> 0 | BA26: =((M26*0.15)+(T26*0.05)+(V26*0.15)+(Y26*0.15)+(AB26*0.15)+(AI26*0.05)+(AM26*0.1)+(AT26*0.1)+(AW26*0.1)*100) -> 0
A27: SSY | C27: 23- Quebrada Arriba | D27: MAG | E27: 5 - 10 años | G27: =IF(F27>=4,1,IF(F27<4,0)) -> 0 | J27: =IF(I27>=0.5,1,0) -> 0 | L27: =IF(K27>=2,1,IF(K27<2,0)) -> 0 | M27: =SUM(G27*0.2+H27*0.3+J27*0.2+L27*0.3) -> 0 | T27: =IF((N27+O27+P27+Q27+S27)>=2,1,IF((N27+O27+P27+Q27+S27)<2,0)) -> 0 | V27: =IF(U27>=2,1,IF(U27<2,0)) -> 0 | Y27: =IF((W27+X27)=2,1,IF((W27+X27)<2,0)) -> 0 | AB27: =Z27*AA27 -> 0 | AI27: =IF(SUM(AC27:AH27)>=3,1,IF(SUM(AC27:AH27)<3,0)) -> 0 | AM27: =IF(SUM(AJ27:AL27)>=3,1,IF(SUM(AJ27:AL27)<3,0)) -> 0 | AO27: =IF(AN27>=3,1,0) -> 0 | AQ27: =IF(AP27>=4,1,0) -> 0 | AT27: =(AO27*0.3)+(AQ27*0.3)+(AR27*0.2)+(AS27*0.2) -> 0 | AU27: 0 | AV27: 0 | AW27: =+(AU27*0.6)+(AV27*0.4) -> 0 | BB27: =((M27*0.15)+(T27*0.05)+(V27*0.15)+(Y27*0.15)+(AB27*0.15)+(AI27*0.1)+(AM27*0.1)+(AT27*0.05)+(AW27*0.1)*100) -> 0
A28: SSY | C28: 24- La Garita | D28: MAG | E28: 5 - 10 años | G28: =IF(F28>=4,1,IF(F28<4,0)) -> 0 | J28: =IF(I28>=0.5,1,0) -> 0 | L28: =IF(K28>=2,1,IF(K28<2,0)) -> 0 | M28: =SUM(G28*0.2+H28*0.3+J28*0.2+L28*0.3) -> 0 | T28: =IF((N28+O28+P28+Q28+S28)>=2,1,IF((N28+O28+P28+Q28+S28)<2,0)) -> 0 | V28: =IF(U28>=2,1,IF(U28<2,0)) -> 0 | Y28: =IF((W28+X28)=2,1,IF((W28+X28)<2,0)) -> 0 | AB28: =Z28*AA28 -> 0 | AI28: =IF(SUM(AC28:AH28)>=3,1,IF(SUM(AC28:AH28)<3,0)) -> 0 | AM28: =IF(SUM(AJ28:AL28)>=3,1,IF(SUM(AJ28:AL28)<3,0)) -> 0 | AO28: =IF(AN28>=3,1,0) -> 0 | AQ28: =IF(AP28>=4,1,0) -> 0 | AT28: =(AO28*0.3)+(AQ28*0.3)+(AR28*0.2)+(AS28*0.2) -> 0 | AU28: 0 | AV28: 0 | AW28: =+(AU28*0.6)+(AV28*0.4) -> 0 | BB28: =((M28*0.15)+(T28*0.05)+(V28*0.15)+(Y28*0.15)+(AB28*0.15)+(AI28*0.1)+(AM28*0.1)+(AT28*0.05)+(AW28*0.1)*100) -> 0
A29: SSY | C29: 25- Cayancimil | D29: MAG | E29: 5 - 10 años | G29: =IF(F29>=4,1,IF(F29<4,0)) -> 0 | J29: =IF(I29>=0.5,1,0) -> 0 | L29: =IF(K29>=2,1,IF(K29<2,0)) -> 0 | M29: =SUM(G29*0.2+H29*0.3+J29*0.2+L29*0.3) -> 0 | T29: =IF((N29+O29+P29+Q29+S29)>=2,1,IF((N29+O29+P29+Q29+S29)<2,0)) -> 0 | V29: =IF(U29>=2,1,IF(U29<2,0)) -> 0 | Y29: =IF((W29+X29)=2,1,IF((W29+X29)<2,0)) -> 0 | AB29: =Z29*AA29 -> 0 | AI29: =IF(SUM(AC29:AH29)>=3,1,IF(SUM(AC29:AH29)<3,0)) -> 0 | AM29: =IF(SUM(AJ29:AL29)>=3,1,IF(SUM(AJ29:AL29)<3,0)) -> 0 | AO29: =IF(AN29>=3,1,0) -> 0 | AQ29: =IF(AP29>=4,1,0) -> 0 | AT29: =(AO29*0.3)+(AQ29*0.3)+(AR29*0.2)+(AS29*0.2) -> 0 | AU29: 0 | AV29: 0 | AW29: =+(AU29*0.6)+(AV29*0.4) -> 0 | BB29: =((M29*0.15)+(T29*0.05)+(V29*0.15)+(Y29*0.15)+(AB29*0.15)+(AI29*0.1)+(AM29*0.1)+(AT29*0.05)+(AW29*0.1)*100) -> 0
A30: SSY | C30: 26- El Barro | D30: MAG | E30: 0 - 5 años | G30: =IF(F30>=4,1,IF(F30<4,0)) -> 0 | J30: =IF(I30>=0.5,1,0) -> 0 | L30: =IF(K30>=2,1,IF(K30<2,0)) -> 0 | M30: =SUM(G30*0.2+H30*0.3+J30*0.2+L30*0.3) -> 0 | T30: =IF((N30+O30+P30+Q30+S30)>=2,1,IF((N30+O30+P30+Q30+S30)<2,0)) -> 0 | V30: =IF(U30>=2,1,IF(U30<2,0)) -> 0 | Y30: =IF((W30+X30)=2,1,IF((W30+X30)<2,0)) -> 0 | AB30: =Z30*AA30 -> 0 | AI30: =IF(SUM(AC30:AH30)>=3,1,IF(SUM(AC30:AH30)<3,0)) -> 0 | AM30: =IF(SUM(AJ30:AL30)>=3,1,IF(SUM(AJ30:AL30)<3,0)) -> 0 | AO30: =IF(AN30>=3,1,0) -> 0 | AQ30: =IF(AP30>=4,1,0) -> 0 | AT30: =(AO30*0.3)+(AQ30*0.3)+(AR30*0.2)+(AS30*0.2) -> 0 | AU30: 0 | AV30: 0 | AW30: =+(AU30*0.6)+(AV30*0.4) -> 0 | BA30: =((M30*0.15)+(T30*0.05)+(V30*0.15)+(Y30*0.15)+(AB30*0.15)+(AI30*0.05)+(AM30*0.1)+(AT30*0.1)+(AW30*0.1)*100) -> 0

Sheet ytyy
C2: TIPO DE SISTEMA: MAG
A3: Municipio | B3: COMUNIDAD | C3: 1)CAPTACION | H3: 2)TANQUE DE ALMACENAMIENTO | P3: 3) CLORINADOR | R3: 4) OTROS
C4: MAG1 | D4: MAG2 | E4: MAG3 | F4: MAG4 | G4: H1 | H4: MAG5 | I4: MAG6 | J4: MAG7 | K4: MAG8 | L4: MAG9 | M4: MAG10 | N4: MAG11 | O4: H2 | P4: MAG12 | Q4: H3 | R4: MAG13 | S4: H4 | T4: Entrevistado por: | U4: Fecha de la Entrevista
C5: ¿Está cerca la obra de captación, a la primera casa? | D5: ¿La cerca de la obra de captación está en buen estado? | E5: No se observan focos de contaminación (restos de envases de pesticidas, basura, heces…) alrededor de la fuente de agua? | F5: ¿No Tiene grietas la obra de captación? | H5: Está cercado el tanque de almacenamiento? | I5: La cerca del tanque está en buen estado? | J5: No tiene grietas el tanque de almacenamiento? | K5: No Tiene fugas el tanque de almacenamiento? | L5: No Rebosa el tanque de almacenamiento? | M5: Están las válvulas del tanque en buen estado? | N5: Está la tapa de inspección en buen estado? | P5: Está funcionando el sistema de cloración? | R5: Durante el recorrido, hay fugas visibles en el sistema?
A6: SRN | B6: 1- El Diamante. | C6: 1 | D6: 1 | E6: 0 | F6: 0 | G6: =+SUM(C6:F6) -> 2 | H6: 1 | I6: 1 | J6: 1 | K6: 1 | L6: 0 | M6: 1 | N6: 1 | O6: =+SUM(H6:N6) -> 6 | P6: 0 | Q6: =+P6 -> 0 | R6: 0 | S6: =+R6 -> 0 | T6: Nohemi Mercado | U6: 40952
A7: SRN | B7: 2- La Breiera | C7: 0 | D7: 0 | E7: 1 | F7: 0 | G7: =+SUM(C7:F7) -> 1 | H7: 0 | I7: 0 | J7: 1 | K7: 0 | L7: 1 | M7: 0 | N7: 1 | O7: =+SUM(H7:N7) -> 3 | P7: 0 | Q7: =+P7 -> 0 | R7: 0 | S7: =+R7 -> 0 | T7: Nohemi Mercado | U7: 40953
A8: SRN | B8: 3- Valle de Suni | G8: =+SUM(C8:F8) -> 0 | O8: =+SUM(H8:N8) -> 0 | Q8: =+P8 -> 0 | S8: =+R8 -> 0
A9: SRN | B9: 4- El Espino | G9: =+SUM(C9:F9) -> 0 | O9: =+SUM(H9:N9) -> 0 | Q9: =+P9 -> 0 | S9: =+R9 -> 0
A10: SRN | B10: 5- San Marcos | G10: =+SUM(C10:F10) -> 0 | O10: =+SUM(H10:N10) -> 0 | Q10: =+P10 -> 0 | S10: =+R10 -> 0
A11: SRN | B11: 6- Los Arados | G11: =+SUM(C11:F11) -> 0 | O11: =+SUM(H11:N11) -> 0 | Q11: =+P11 -> 0 | S11: =+R11 -> 0
A12: SRN | B12: 7- Lomas de Sacacli | G12: =+SUM(C12:F12) -> 0 | O12: =+SUM(H12:N12) -> 0 | Q12: =+P12 -> 0 | S12: =+R12 -> 0
A13: SRN | B13: 8- Sacacli | G13: =+SUM(C13:F13) -> 0 | O13: =+SUM(H13:N13) -> 0 | Q13: =+P13 -> 0 | S13: =+R13 -> 0
A14: SRN | B14: 9- Estación Cerro Grande | G14: =+SUM(C14:F14) -> 0 | O14: =+SUM(H14:N14) -> 0 | Q14: =+P14 -> 0 | S14: =+R14 -> 0
A15: LC | B15: 10- Valerio | G15: =+SUM(C15:F15) -> 0 | O15: =+SUM(H15:N15) -> 0 | Q15: =+P15 -> 0 | S15: =+R15 -> 0
A16: LC | B16: 11- Yupali | G16: =+SUM(C16:F16) -> 0 | O16: =+SUM(H16:N16) -> 0 | Q16: =+P16 -> 0 | S16: =+R16 -> 0
A17: LC | B17: 12- Gracalcan | C17: 0 | D17: 1 | E17: 1 | F17: 1 | G17: =+SUM(C17:F17) -> 3 | H17: 1 | I17: 0 | J17: 1 | K17: 1 | L17: 1 | M17: 0 | N17: 1 | O17: =+SUM(H17:N17) -> 5 | P17: 1 | Q17: =+P17 -> 1 | R17: 0 | S17: =+R17 -> 0 | T17: Arlen Zeledón | U17: 40955
A18: LC | B18: 13- Agua Fria | C18: 0 | D18: 1 | E18: 1 | F18: 1 | G18: =+SUM(C18:F18) -> 3 | H18: 0 | I18: 1 | J18: 1 | K18: 1 | L18: 0 | M18: 0 | N18: 1 | O18: =+SUM(H18:N18) -> 4 | P18: 1 | Q18: =+P18 -> 1 | R18: 0 | S18: =+R18 -> 0 | T18: Arlen Zeledón | U18: 40959
A19: LC | B19: 14- Zapote Oriental | G19: =+SUM(C19:F19) -> 0 | O19: =+SUM(H19:N19) -> 0 | Q19: =+P19 -> 0 | S19: =+R19 -> 0
A20: LC | B20: 15- Santiago del Coyolito | G20: =+SUM(C20:F20) -> 0 | O20: =+SUM(H20:N20) -> 0 | Q20: =+P20 -> 0 | S20: =+R20 -> 0
A21: LC | B21: 16- Las Quebradas | G21: =+SUM(C21:F21) -> 0 | O21: =+SUM(H21:N21) -> 0 | Q21: =+P21 -> 0 | S21: =+R21 -> 0
A22: SSY | B22: 17- La Naranjita | G22: =+SUM(C22:F22) -> 0 | O22: =+SUM(H22:N22) -> 0 | Q22: =+P22 -> 0 | S22: =+R22 -> 0
A23: SSY | B23: 18- Los Prendedizos | G23: =+SUM(C23:F23) -> 0 | O23: =+SUM(H23:N23) -> 0 | Q23: =+P23 -> 0 | S23: =+R23 -> 0
A24: SSY | B24: 19- Las Trozas | G24: =+SUM(C24:F24) -> 0 | O24: =+SUM(H24:N24) -> 0 | Q24: =+P24 -> 0 | S24: =+R24 -> 0
A25: SSY | B25: 20- Las Delicias | G25: =+SUM(C25:F25) -> 0 | O25: =+SUM(H25:N25) -> 0 | Q25: =+P25 -> 0 | S25: =+R25 -> 0
A26: SSY | B26: 21- El Volcán | G26: =+SUM(C26:F26) -> 0 | O26: =+SUM(H26:N26) -> 0 | Q26: =+P26 -> 0 | S26: =+R26 -> 0
A27: SSY | B27: 22- El Regadio | G27: =+SUM(C27:F27) -> 0 | O27: =+SUM(H27:N27) -> 0 | Q27: =+P27 -> 0 | S27: =+R27 -> 0
A28: SSY | B28: 23- Quebrada Arriba | G28: =+SUM(C28:F28) -> 0 | O28: =+SUM(H28:N28) -> 0 | Q28: =+P28 -> 0 | S28: =+R28 -> 0
A29: SSY | B29: 24- La Garita | G29: =+SUM(C29:F29) -> 0 | O29: =+SUM(H29:N29) -> 0 | Q29: =+P29 -> 0 | S29: =+R29 -> 0
A30: SSY | B30: 25- Cayancimil | G30: =+SUM(C30:F30) -> 0 | O30: =+SUM(H30:N30) -> 0 | Q30: =+P30 -> 0 | S30: =+R30 -> 0
A31: SSY | B31: 26- El Barro | G31: =+SUM(C31:F31) -> 0 | O31: =+SUM(H31:N31) -> 0 | Q31: =+P31 -> 0 | S31: =+R31 -> 0

Sheet Est_Conserv_MABE
C4: ESTADO DE CONSERVACION DE LOS SISTEMAS MABE
A5: Municipio | B5: COMUNIDAD | C5: 1) Estación de Bombeo | H5: H1 | I5: 2)Tanque de Almacenamiento | P5: H2 | Q5: 3) Clorinador | R5: H3 | S5: 4) Otros | T5: H4 | U5: Entrevistado por: | V5: Fecha de la Entrevista
C6: MABE1 | D6: MABE 2 | E6: MABE3 | F6: MABE4 | G6: MABE5 | I6: MABE6 | J6: MABE7 | K6: MABE8 | L6: MABE9 | M6: MABE10 | N6: MABE11 | O6: MABE12 | Q6: MABE14 | S6: MABE16
C7: Tiene cerco de protección el predio del pozo | D7: No hay letrinas ubicadas a menos de 20 mts del pozo | E7: Las paredes y el techo de la caseta de bombeo están en buen estado? | F7: La caseta tiene puerta cerrada con llave | G7: Está registrando el macromedidor | I7: Está cercado el tanque de almacenamiento? | J7: La cerca del tanque está en buen estado? | K7: No tiene grietas el tanque de almacenamiento? | L7: No Tiene fugas el tanque de almacenamiento? | M7: No Rebosa el tanque de almacenamiento? | N7: Están las válvulas del tanque en buen estado? | O7: Está la tapa de inspección en buen estado? | Q7: Está funcionando el sistema de cloración? | S7: Durante el recorrido, No hay fugas visibles en el sistema?
A8: SRN | B8: 1- El Diamante. | H8: =+SUM(C8:G8) -> 0 | P8: =+SUM(I8:O8) -> 0 | R8: =+Q8 -> 0 | S8: =+R8 -> 0 | T8: =+S8 -> 0
A9: SRN | B9: 2- La Breiera | H9: =+SUM(C9:G9) -> 0 | P9: =+SUM(I9:O9) -> 0 | R9: =+Q9 -> 0 | S9: =+R9 -> 0 | T9: =+S9 -> 0
A10: SRN | B10: 3- Valle de Suni | H10: =+SUM(C10:G10) -> 0 | P10: =+SUM(I10:O10) -> 0 | R10: =+Q10 -> 0 | S10: =+R10 -> 0 | T10: =+S10 -> 0
A11: SRN | B11: 4- El Espino | H11: =+SUM(C11:G11) -> 0 | P11: =+SUM(I11:O11) -> 0 | R11: =+Q11 -> 0 | S11: =+R11 -> 0 | T11: =+S11 -> 0
A12: SRN | B12: 5- San Marcos | H12: =+SUM(C12:G12) -> 0 | P12: =+SUM(I12:O12) -> 0 | R12: =+Q12 -> 0 | S12: =+R12 -> 0 | T12: =+S12 -> 0
A13: SRN | B13: 6- Los Arados | H13: =+SUM(C13:G13) -> 0 | P13: =+SUM(I13:O13) -> 0 | R13: =+Q13 -> 0 | S13: =+R13 -> 0 | T13: =+S13 -> 0
A14: SRN | B14: 7- Lomas de Sacacli | H14: =+SUM(C14:G14) -> 0 | P14: =+SUM(I14:O14) -> 0 | R14: =+Q14 -> 0 | S14: =+R14 -> 0 | T14: =+S14 -> 0
A15: SRN | B15: 8- Sacacli | H15: =+SUM(C15:G15) -> 0 | P15: =+SUM(I15:O15) -> 0 | R15: =+Q15 -> 0 | S15: =+R15 -> 0 | T15: =+S15 -> 0
A16: SRN | B16: 9- Estación Cerro Grande | H16: =+SUM(C16:G16) -> 0 | P16: =+SUM(I16:O16) -> 0 | R16: =+Q16 -> 0 | S16: =+R16 -> 0 | T16: =+S16 -> 0
A17: LC | B17: 10- Valerio | C17: 1 | D17: 1 | E17: 1 | F17: 1 | G17: 1 | H17: =+SUM(C17:G17) -> 5 | I17: 1 | J17: 1 | K17: 1 | L17: 1 | M17: 1 | N17: 0 | O17: 1 | P17: =+SUM(I17:O17) -> 6 | Q17: 1 | R17: =+Q17 -> 1 | S17: 1 | T17: =+S17 -> 1 | U17: Arlen Zeledón | V17: 40952
A18: LC | B18: 11- Yupali | C18: 1 | D18: 1 | E18: 1 | F18: 1 | G18: 1 | H18: =+SUM(C18:G18) -> 5 | I18: 1 | J18: 1 | K18: 1 | L18: 1 | M18: 1 | N18: 0 | O18: 1 | P18: =+SUM(I18:O18) -> 6 | Q18: 1 | R18: =+Q18 -> 1 | S18: 1 | T18: =+S18 -> 1 | U18: Arlen Zeledón | V18: 40955
A19: LC | B19: 14- Zapote Oriental | H19: =+SUM(C19:G19) -> 0 | P19: =+SUM(I19:O19) -> 0 | R19: =+Q19 -> 0 | S19: =+R19 -> 0 | T19: =+S19 -> 0
A20: LC | B20: 15- Santiago del Coyolito | C20: 1 | D20: 1 | E20: 1 | F20: 1 | G20: 1 | H20: =+SUM(C20:G20) -> 5 | I20: 1 | J20: 1 | K20: 1 | L20: 1 | M20: 0 | N20: 1 | O20: 1 | P20: =+SUM(I20:O20) -> 6 | Q20: 1 | R20: =+Q20 -> 1 | S20: =+R20 -> 1 | T20: =+S20 -> 1 | U20: Arlen Zeledón | V20: 13702/12
A21: LC | B21: 16- Las Quebradas | H21: =+SUM(C21:G21) -> 0 | I21: =+SUM(I8:I20) -> 3 | J21: =+SUM(J8:J20) -> 3 | K21: =+SUM(K8:K20) -> 3 | L21: =+SUM(L8:L20) -> 3 | M21: =+SUM(M8:M20) -> 2 | N21: =+SUM(N8:N20) -> 1 | P21: =+SUM(I21:O21) -> 15 | R21: =+Q21 -> 0 | S21: =+R21 -> 0 | T21: =+S21 -> 0
A22: SSY | B22: 17- La Naranjita | H22: =+SUM(C22:G22) -> 0 | P22: =+SUM(I22:O22) -> 0 | R22: =+Q22 -> 0 | S22: =+R22 -> 0 | T22: =+S22 -> 0
A23: SSY | B23: 18- Los Prendedizos | H23: =+SUM(C23:G23) -> 0 | P23: =+SUM(I23:O23) -> 0 | R23: =+Q23 -> 0 | S23: =+R23 -> 0 | T23: =+S23 -> 0
A24: SSY | B24: 19- Las Trozas | H24: =+SUM(C24:G24) -> 0 | P24: =+SUM(I24:O24) -> 0 | R24: =+Q24 -> 0 | S24: =+R24 -> 0 | T24: =+S24 -> 0
A25: SSY | B25: 20- Las Delicias | H25: =+SUM(C25:G25) -> 0 | P25: =+SUM(I25:O25) -> 0 | R25: =+Q25 -> 0 | S25: =+R25 -> 0 | T25: =+S25 -> 0
A26: SSY | B26: 21- El Volcán | H26: =+SUM(C26:G26) -> 0 | P26: =+SUM(I26:O26) -> 0 | R26: =+Q26 -> 0 | S26: =+R26 -> 0 | T26: =+S26 -> 0
A27: SSY | B27: 22- El Regadio | H27: =+SUM(C27:G27) -> 0 | P27: =+SUM(I27:O27) -> 0 | R27: =+Q27 -> 0 | S27: =+R27 -> 0 | T27: =+S27 -> 0
A28: SSY | B28: 23- Quebrada Arriba | H28: =+SUM(C28:G28) -> 0 | P28: =+SUM(I28:O28) -> 0 | R28: =+Q28 -> 0 | S28: =+R28 -> 0 | T28: =+S28 -> 0
A29: SSY | B29: 24- La Garita | H29: =+SUM(C29:G29) -> 0 | P29: =+SUM(I29:O29) -> 0 | R29: =+Q29 -> 0 | S29: =+R29 -> 0 | T29: =+S29 -> 0
A30: SSY | B30: 25- Cayancimil | H30: =+SUM(C30:G30) -> 0 | P30: =+SUM(I30:O30) -> 0 | R30: =+Q30 -> 0 | S30: =+R30 -> 0 | T30: =+S30 -> 0
A31: SSY | B31: 26- El Barro | H31: =+SUM(C31:G31) -> 0 | P31: =+SUM(I31:O31) -> 0 | R31: =+Q31 -> 0 | S31: =+R31 -> 0 | T31: =+S31 -> 0

Sheet Tabla de Contenidos
A1: INDICE DE HERRAMIENTAS DE LOS INDICADORES SOSTENIBILIDAD DE LOS CAPS | E1: Ir a Resultados Finales
A2: Código | B2: Nombre/Descripción | C2: Haga click en el link siguiente | D2: OBSERVACION | E2: Fuente de la información
A3: 1 | B3: BAREMOS INDICE DE SOSTENIBILIDAD | C3: Ind.Sostenib. | D3: Esta tabla debe ser modificada antes de comenzar el análisis. | E3: No procede
B4: Resultado del Índice de Sostenibilidad obtenido | C4: Resultado Final | D4: Esta tabla se nutre de todas las pestañas anteriores. POR FAVOR NO MODIFICAR NADA. :) | E4: No procede
A5: 2 | B5: Listado de CAPS a evaluar | C5: Listado CAPS | D5: Completar nombres CAPS a evaluar.
A6: 3 | B6: Conformación de la JD | C6: Conformación JD | D6: Completar con en acta Constitutiva de la JD o la actualizada si hubo reestructuración. | E6: Acta constitutiva
A7: A. | B7: ORGANIZACIÓN | D7: Si no hay libro de actas no se puede completar este criterio
B8: Nº miembros activos JD | E8: Libro de Actas
B9: Participación de mujeres | C9: A.Organización | E9: Libro de Actas
B10: Capacidad de convocatoria | D10: Se asume la informacion facilitada por el caps | E10: Cartas/ Invitaciones
B11: Legalización | C11: A.Legalización | E11: Certificados oficiales
A12: B. | B12: CAPITAL SOCIAL
B13: Espacios comunitarios en los que la JD del CAPS participa | C13: B.CapitalSocial | E13: Entrevistas realizadas al CAPS
A14: C. | B14: AUTOGESTION
B15: Capacidad de resolución de problemas (administrativo, legal, organizativo, técnico) | C15: C.AutoGestionCAPS | E15: Cartas, informes
A16: D. | B16: RECUPERACIÓN DE COSTOS | C16: D.RecuperacióndeCostes | E16: Libros contables Reportes mensuales de la cuenta de ahorro
A17: E. | B17: OPERACIÓN Y MANTENIMIENTO
B18: Existencia de Plan de Operación y Mantenimiento. Realización del 60% de las acciones recogidas en el Plan. | C18: E.Ope y Manten | E18: Actividades recogidas en los Libros de actas. Perioricidad en función del RI
A19: F. | B19: SALUD COMUNITARIA Y AMBIENTAL | C19: F.Salud Comunit | E19: Reportes de actividades recogidas en los Libros de actas
A20: G. | B20: RENDICIÓN DE CUENTAS | C20: G.Rendición de cuentas | E20: Libros contables Libro de Actas
A21: H. | B21: CONSERVACIÓN DEL SISTEMA
B22: Conservación del sistema: MABE | C22: H.1 Estado_Conserv MABE | E22: Inspección ocular
B23: Conservación del sistema: MAG | C23: H.2.Estado_Conserv.MAG | E23: Inspección ocular
B24: Conservación del sistema: POZOS | C24: H.3.Estado_Consev.Pozos | E24: Inspección ocular
A26: I. | B26: GÉNERO
B27: Acciones positivas dirigidas a promover la participación activa de las mujeres y acciones contempladas en Reglamento Interno. | C27: I.Genero

Sheet Ind.Sostenib.
A1: Volver a Tabla de contenidos | F1: INDICES DE SOSTENIBILIDAD | J1: Ir a Resultados Finales
A3: MABE
A4: Años de Construcción del SAP | B4: Organización | C4: Nivel de Servicio de agua | D4: Recuperación de Costes | E4: Operación y Mantenimiento | F4: GIRH | G4: Rendición de Cuentas | H4: Estado y Conservación del SAP | I4: Incorporación del enfoque de Género. | J4: Autogestión | K4: Indice de Sostenibilidad
A5: 0 - 5 años | B5: 0.15 | C5: 0.05 | D5: 0.15 | E5: 0.15 | F5: 0.05 | G5: 0.1 | H5: 0.1 | I5: 0.1 | J5: 0.15 | K5: =SUM(B5:J5) -> 1
A6: 5 - 10 años | B6: 0.1 | C6: 0.05 | D6: 0.2 | E6: 0.2 | F6: 0.05 | G6: 0.1 | H6: 0.05 | I6: 0.1 | J6: 0.15 | K6: =SUM(B6:J6) -> 1
A7: más de 10 años | B7: 0.1 | C7: 0.05 | D7: 0.2 | E7: 0.15 | F7: 0.05 | G7: 0.1 | H7: 0.05 | I7: 0.1 | J7: 0.2 | K7: =SUM(B7:J7) -> 1
A10: MAG /POZOS
A11: Años de Construcción del SAP | B11: Organización | C11: Nivel de Servicio de agua | D11: Recuperación de Costes | E11: Operación y Mantenimiento | F11: GIRH | G11: Rendición de Cuentas | H11: Estado y Conservación del SAP | I11: Incorporación del enfoque de Género. | J11: Autogestión | K11: Indice de Sostenibilidad
A12: 0 - 5 años | B12: 0.15 | C12: 0.05 | D12: 0.15 | E12: 0.15 | F12: 0.05 | G12: 0.1 | H12: 0.1 | I12: 0.1 | J12: 0.15 | K12: =SUM(B12:J12) -> 1
A13: 5 - 10 años | B13: 0.15 | C13: 0.05 | D13: 0.15 | E13: 0.15 | F13: 0.1 | G13: 0.1 | H13: 0.05 | I13: 0.1 | J13: 0.15 | K13: =SUM(B13:J13) -> 1
A14: mas de 10 años | B14: 0.1 | C14: 0.05 | D14: 0.2 | E14: 0.1 | F14: 0.05 | G14: 0.15 | H14: 0.05 | I14: 0.1 | J14: 0.2 | K14: =SUM(B14:J14) -> 1
A17: Índices de Sostenibilidad
A18: De 0 - 59 | B18: Hay muchas debilidades en la gestión del CAPS y funcionamiento del SAP, y se esta en riesgo la sostenibilidad en el futuro
A19: De 60 - 79 | B19: El CAPS esta realizando acciones de gestión y administración del SAP que apuntan a la sostenibilidad
A20: De 80 - 100 | B20: El CAPS esta realizando acciones internas que garantizan la sostenibilidad y en cordinación con otros.

Sheet Listado CAPS
B1: Volver a Tabla de contenidos | C1: Actualizada a fecha de: dd/mm/aaaa | F1: Ir a Resultados Finales
A2: DEPARTAMENTO | B2: MUNICIPIO | C2: COMUNIDAD/ES | D2: CAPS | E2: TIPO DE SISTEMA | F2: TIEMPO DEL SISTEMA | G2: VVIENDAS ATENDIDAS | H2: POBLACIÓN ATENDIDA | I2: VIVIENDAS SIN SERVICIO | J2: POBLACIÓN SIN SERVICIO | K2: Tipo de sistema | L2: Tiempo del sistema
A3: Madriz | B3: Yalaguina | C3: Los Encuentros | D3: Los Encuentros | E3: MAG | F3: 1 | K3: MAG | L3: 1 | M3: entre 0-5 años
D4: B | K4: MABE | L4: 2 | M4: 5-10 años
D5: C | K5: POZO | L5: 3 | M5: más de 10 años
D6: D | K6: MIXTO (MABE-MAG)
D7: E | K7: POZO EXCAVADO
D8: F | K8: POZO PERFORADO
D9: G | K9: MANANTIAL
D10: H | K10: LLUVIA
D11: I | K11: SUPERFICIE
D12: J
D13: K
D14: L
D15: M
D16: N
D17: Ñ
D18: O
D19: P
D20: Q
D21: R
D22: S
D23: T
... D28: Y

Sheet Conformación JD
B1: Volver a Tabla de contenidos | C1: 0. ESTRUCTURA DE LA JD | T1: Ir a Resultados Finales
C2: Instrucciones: 1) Para el llenado de este formato se debe utilizar el Acta de conformación del CAPS No toque las celdas sombreadas
Z3: Ir a Hoja de I.Género
A4: Departamento | B4: Municipio | C4: Comunidad | D4: CAPS | E4: A fecha de | F4: Cargos JD
F5: Presidente | H5: Tesorero | J5: Secretario | L5: Fiscal | N5: Vocal_1 | P5: Vocal_2 | R5: Vocal_3 | T5: Vocal_4 | V5: Vocal_5 | X5: Miembros totales | Y5: Total de mujeres | Z5: Total de Mujeres en cargos de poder (Presi y Tesorera) | AA5: % de mujeres en la JD
F6: H | G6: M | H6: H | I6: M | J6: H | K6: M | L6: H | M6: M | N6: H | O6: M | P6: H | Q6: M | R6: H | S6: M | T6: H | U6: M | V6: H | W6: M
A7: ='Listado CAPS'!A3 -> Madriz | B7: ='Listado CAPS'!B3 -> Yalaguina | C7: ='Listado CAPS'!C3 -> Los Encuentros | D7: ='Listado CAPS'!D3 -> Los Encuentros | E7: 45083 | F7: 1 | I7: 1 | K7: 1 | L7: 1 | O7: 1 | X7: =SUM(F7:W7) -> 5 | Y7: =+SUM(G7+I7+K7+M7+O7+Q7+S7+U7+W7) -> 3 | Z7: =SUM(G7+I7) -> 1 | AA7: =IF(Y7=0,0,(Y7/X7)) -> 0.6
A8: ='Listado CAPS'!A4 -> 0 | B8: ='Listado CAPS'!B4 -> 0 | C8: ='Listado CAPS'!C4 -> 0 | D8: ='Listado CAPS'!D4 -> B | X8: =SUM(F8:W8) -> 0 | Y8: =+SUM(G8+I8+K8+M8+O8+Q8+S8+U8+W8) -> 0 | Z8: =SUM(G8+I8) -> 0 | AA8: =IF(Y8=0,0,(Y8/X8)) -> 0
A9: ='Listado CAPS'!A5 -> 0 | B9: ='Listado CAPS'!B5 -> 0 | C9: ='Listado CAPS'!C5 -> 0 | D9: ='Listado CAPS'!D5 -> C | X9: =SUM(F9:W9) -> 0 | Y9: =+SUM(G9+I9+K9+M9+O9+Q9+S9+U9+W9) -> 0 | Z9: =SUM(G9+I9) -> 0 | AA9: =IF(Y9=0,0,(Y9/X9)) -> 0
A10: ='Listado CAPS'!A6 -> 0 | B10: ='Listado CAPS'!B6 -> 0 | C10: ='Listado CAPS'!C6 -> 0 | D10: ='Listado CAPS'!D6 -> D | X10: =SUM(F10:W10) -> 0 | Y10: =+SUM(G10+I10+K10+M10+O10+Q10+S10+U10+W10) -> 0 | Z10: =SUM(G10+I10) -> 0 | AA10: =IF(Y10=0,0,(Y10/X10)) -> 0
A11: ='Listado CAPS'!A7 -> 0 | B11: ='Listado CAPS'!B7 -> 0 | C11: ='Listado CAPS'!C7 -> 0 | D11: ='Listado CAPS'!D7 -> E | X11: =SUM(F11:W11) -> 0 | Y11: =+SUM(G11+I11+K11+M11+O11+Q11+S11+U11+W11) -> 0 | Z11: =SUM(G11+I11) -> 0 | AA11: =IF(Y11=0,0,(Y11/X11)) -> 0
A12: ='Listado CAPS'!A8 -> 0 | B12: ='Listado CAPS'!B8 -> 0 | C12: ='Listado CAPS'!C8 -> 0 | D12: ='Listado CAPS'!D8 -> F | X12: =SUM(F12:W12) -> 0 | Y12: =+SUM(G12+I12+K12+M12+O12+Q12+S12+U12+W12) -> 0 | Z12: =SUM(G12+I12) -> 0 | AA12: =IF(Y12=0,0,(Y12/X12)) -> 0
A13: ='Listado CAPS'!A9 -> 0 | B13: ='Listado CAPS'!B9 -> 0 | C13: ='Listado CAPS'!C9 -> 0 | D13: ='Listado CAPS'!D9 -> G | X13: =SUM(F13:W13) -> 0 | Y13: =+SUM(G13+I13+K13+M13+O13+Q13+S13+U13+W13) -> 0 | Z13: =SUM(G13+I13) -> 0 | AA13: =IF(Y13=0,0,(Y13/X13)) -> 0
A14: ='Listado CAPS'!A10 -> 0 | B14: ='Listado CAPS'!B10 -> 0 | C14: ='Listado CAPS'!C10 -> 0 | D14: ='Listado CAPS'!D10 -> H | X14: =SUM(F14:W14) -> 0 | Y14: =+SUM(G14+I14+K14+M14+O14+Q14+S14+U14+W14) -> 0 | Z14: =SUM(G14+I14) -> 0 | AA14: =IF(Y14=0,0,(Y14/X14)) -> 0
A15: ='Listado CAPS'!A11 -> 0 | B15: ='Listado CAPS'!B11 -> 0 | C15: ='Listado CAPS'!C11 -> 0 | D15: ='Listado CAPS'!D11 -> I | X15: =SUM(F15:W15) -> 0 | Y15: =+SUM(G15+I15+K15+M15+O15+Q15+S15+U15+W15) -> 0 | Z15: =SUM(G15+I15) -> 0 | AA15: =IF(Y15=0,0,(Y15/X15)) -> 0
A16: ='Listado CAPS'!A12 -> 0 | B16: ='Listado CAPS'!B12 -> 0 | C16: ='Listado CAPS'!C12 -> 0 | D16: ='Listado CAPS'!D12 -> J | X16: =SUM(F16:W16) -> 0 | Y16: =+SUM(G16+I16+K16+M16+O16+Q16+S16+U16+W16) -> 0 | Z16: =SUM(G16+I16) -> 0 | AA16: =IF(Y16=0,0,(Y16/X16)) -> 0
A17: ='Listado CAPS'!A13 -> 0 | B17: ='Listado CAPS'!B13 -> 0 | C17: ='Listado CAPS'!C13 -> 0 | D17: ='Listado CAPS'!D13 -> K | X17: =SUM(F17:W17) -> 0 | Y17: =+SUM(G17+I17+K17+M17+O17+Q17+S17+U17+W17) -> 0 | Z17: =SUM(G17+I17) -> 0 | AA17: =IF(Y17=0,0,(Y17/X17)) -> 0
A18: ='Listado CAPS'!A14 -> 0 | B18: ='Listado CAPS'!B14 -> 0 | C18: ='Listado CAPS'!C14 -> 0 | D18: ='Listado CAPS'!D14 -> L | X18: =SUM(F18:W18) -> 0 | Y18: =+SUM(G18+I18+K18+M18+O18+Q18+S18+U18+W18) -> 0 | Z18: =SUM(G18+I18) -> 0 | AA18: =IF(Y18=0,0,(Y18/X18)) -> 0
A19: ='Listado CAPS'!A15 -> 0 | B19: ='Listado CAPS'!B15 -> 0 | C19: ='Listado CAPS'!C15 -> 0 | D19: ='Listado CAPS'!D15 -> M | X19: =SUM(F19:W19) -> 0 | Y19: =+SUM(G19+I19+K19+M19+O19+Q19+S19+U19+W19) -> 0 | Z19: =SUM(G19+I19) -> 0 | AA19: =IF(Y19=0,0,(Y19/X19)) -> 0
... A32: ='Listado CAPS'!A28 -> 0 | B32: ='Listado CAPS'!B28 -> 0 | C32: ='Listado CAPS'!C28 -> 0 | D32: ='Listado CAPS'!D28 -> Y | X32: =SUM(F32:W32) -> 0 | Y32: =+SUM(G32+I32+K32+M32+O32+Q32+S32+U32+W32) -> 0 | Z32: =SUM(G32+I32) -> 0 | AA32: =IF(Y32=0,0,(Y32/X32)) -> 0
E33: TOTAL: | F33: =SUM(F7:F32) -> 1 | G33: =SUM(G7:G32) -> 0 | H33: =SUM(H7:H32) -> 0 | I33: =SUM(I7:I32) -> 1 | J33: =SUM(J7:J32) -> 0 | K33: =SUM(K7:K32) -> 1 | L33: =SUM(L7:L32) -> 1 | M33: =SUM(M7:M32) -> 0 | ... W33: =SUM(W7:W32) -> 0 | X33: =SUM(F33:W33) -> 5 | Y33: =+SUM(G33+I33+K33+M33+O33+Q33+S33+U33+W33) -> 3 | Z33: =IF(SUM(Z7:Z32)=0,0,SUM(Z7:Z32)/COUNTIF(X7:X32,"<>0")) -> 1 | AA33: =IF(SUM(AA7:AA32)=0,0,SUM(AA7:AA32)/COUNTIF(Y7:Y32,"<>0")) -> 0.6

Sheet  A.Legalización 
C2: Volver a Tabla de contenidos | D2: A. LEGALIZACIÓN | M2: Ir a Resultados Finales
F3: Instrucciones: Rellene las columnas en blanco según cada caso (1 si es SI). No modifique la columna "Valor total" por que es la que esta relacionada con la hoja de Resultado final. | K3: Criterios: Si no esta legalizado valor cero, si sí lo esta entonces: al menos 2 de los permisos si es MAG o Pozo u otras, 3 si es MABE por la tarifa diferenciada.
A5: Departamento | B5: Municipio | C5: Comunidad | D5: CAPS | E5: Tipo de sistema | F5: Certificado Registro municipal | G5: Certificado INAA | H5: Certificado RUC | I5: Tarifa Diferenciada INE 03/09/2012 | J5: Legalización SAP (infraestructura/terrenos) | K5: Valor Total | L5: Medios de Verificación Existe? | M5: Nombre del Medio de Verificación
A6: ='Listado CAPS'!A3 -> Madriz | B6: ='Listado CAPS'!B3 -> Yalaguina | C6: ='Listado CAPS'!C3 -> Los Encuentros | D6: ='Listado CAPS'!D3 -> Los Encuentros | E6: ='Listado CAPS'!E3 -> MAG | F6: 1 | G6: 1 | J6: 1 | K6: =IF(J6<>1,0,IF(E6="MABE",IF(SUM(F6:J6)>=3,1,0),IF(E6="MAG",IF(SUM(F6:J6)>=2,1,0),IF(E6<>"MAG, MABE",IF(SUM(F6:J6)>=2,1,0))))) -> 1
A7: ='Listado CAPS'!A4 -> 0 | B7: ='Listado CAPS'!B4 -> 0 | C7: ='Listado CAPS'!C4 -> 0 | D7: ='Listado CAPS'!D4 -> B | K7: =IF(J7<>1,0,IF(E7="MABE",IF(SUM(F7:J7)>=3,1,0),IF(E7="MAG",IF(SUM(F7:J7)>=2,1,0),IF(E7<>"MAG, MABE",IF(SUM(F7:J7)>=2,1,0))))) -> 0
A8: ='Listado CAPS'!A5 -> 0 | B8: ='Listado CAPS'!B5 -> 0 | C8: ='Listado CAPS'!C5 -> 0 | D8: ='Listado CAPS'!D5 -> C | K8: =IF(J8<>1,0,IF(E8="MABE",IF(SUM(F8:J8)>=3,1,0),IF(E8="MAG",IF(SUM(F8:J8)>=2,1,0),IF(E8<>"MAG, MABE",IF(SUM(F8:J8)>=2,1,0))))) -> 0
A9: ='Listado CAPS'!A6 -> 0 | B9: ='Listado CAPS'!B6 -> 0 | C9: ='Listado CAPS'!C6 -> 0 | D9: ='Listado CAPS'!D6 -> D | K9: =IF(J9<>1,0,IF(E9="MABE",IF(SUM(F9:J9)>=3,1,0),IF(E9="MAG",IF(SUM(F9:J9)>=2,1,0),IF(E9<>"MAG, MABE",IF(SUM(F9:J9)>=2,1,0))))) -> 0
A10: ='Listado CAPS'!A7 -> 0 | B10: ='Listado CAPS'!B7 -> 0 | C10: ='Listado CAPS'!C7 -> 0 | D10: ='Listado CAPS'!D7 -> E | K10: =IF(J10<>1,0,IF(E10="MABE",IF(SUM(F10:J10)>=3,1,0),IF(E10="MAG",IF(SUM(F10:J10)>=2,1,0),IF(E10<>"MAG, MABE",IF(SUM(F10:J10)>=2,1,0))))) -> 0
A11: ='Listado CAPS'!A8 -> 0 | B11: ='Listado CAPS'!B8 -> 0 | C11: ='Listado CAPS'!C8 -> 0 | D11: ='Listado CAPS'!D8 -> F | K11: =IF(J11<>1,0,IF(E11="MABE",IF(SUM(F11:J11)>=3,1,0),IF(E11="MAG",IF(SUM(F11:J11)>=2,1,0),IF(E11<>"MAG, MABE",IF(SUM(F11:J11)>=2,1,0))))) -> 0
A12: ='Listado CAPS'!A9 -> 0 | B12: ='Listado CAPS'!B9 -> 0 | C12: ='Listado CAPS'!C9 -> 0 | D12: ='Listado CAPS'!D9 -> G | K12: =IF(J12<>1,0,IF(E12="MABE",IF(SUM(F12:J12)>=3,1,0),IF(E12="MAG",IF(SUM(F12:J12)>=2,1,0),IF(E12<>"MAG, MABE",IF(SUM(F12:J12)>=2,1,0))))) -> 0
A13: ='Listado CAPS'!A10 -> 0 | B13: ='Listado CAPS'!B10 -> 0 | C13: ='Listado CAPS'!C10 -> 0 | D13: ='Listado CAPS'!D10 -> H | K13: =IF(J13<>1,0,IF(E13="MABE",IF(SUM(F13:J13)>=3,1,0),IF(E13="MAG",IF(SUM(F13:J13)>=2,1,0),IF(E13<>"MAG, MABE",IF(SUM(F13:J13)>=2,1,0))))) -> 0
A14: ='Listado CAPS'!A11 -> 0 | B14: ='Listado CAPS'!B11 -> 0 | C14: ='Listado CAPS'!C11 -> 0 | D14: ='Listado CAPS'!D11 -> I | K14: =IF(J14<>1,0,IF(E14="MABE",IF(SUM(F14:J14)>=3,1,0),IF(E14="MAG",IF(SUM(F14:J14)>=2,1,0),IF(E14<>"MAG, MABE",IF(SUM(F14:J14)>=2,1,0))))) -> 0
A15: ='Listado CAPS'!A12 -> 0 | B15: ='Listado CAPS'!B12 -> 0 | C15: ='Listado CAPS'!C12 -> 0 | D15: ='Listado CAPS'!D12 -> J | K15: =IF(J15<>1,0,IF(E15="MABE",IF(SUM(F15:J15)>=3,1,0),IF(E15="MAG",IF(SUM(F15:J15)>=2,1,0),IF(E15<>"MAG, MABE",IF(SUM(F15:J15)>=2,1,0))))) -> 0
A16: ='Listado CAPS'!A13 -> 0 | B16: ='Listado CAPS'!B13 -> 0 | C16: ='Listado CAPS'!C13 -> 0 | D16: ='Listado CAPS'!D13 -> K | K16: =IF(J16<>1,0,IF(E16="MABE",IF(SUM(F16:J16)>=3,1,0),IF(E16="MAG",IF(SUM(F16:J16)>=2,1,0),IF(E16<>"MAG, MABE",IF(SUM(F16:J16)>=2,1,0))))) -> 0
A17: ='Listado CAPS'!A14 -> 0 | B17: ='Listado CAPS'!B14 -> 0 | C17: ='Listado CAPS'!C14 -> 0 | D17: ='Listado CAPS'!D14 -> L | K17: =IF(J17<>1,0,IF(E17="MABE",IF(SUM(F17:J17)>=3,1,0),IF(E17="MAG",IF(SUM(F17:J17)>=2,1,0),IF(E17<>"MAG, MABE",IF(SUM(F17:J17)>=2,1,0))))) -> 0
A18: ='Listado CAPS'!A15 -> 0 | B18: ='Listado CAPS'!B15 -> 0 | C18: ='Listado CAPS'!C15 -> 0 | D18: ='Listado CAPS'!D15 -> M | K18: =IF(J18<>1,0,IF(E18="MABE",IF(SUM(F18:J18)>=3,1,0),IF(E18="MAG",IF(SUM(F18:J18)>=2,1,0),IF(E18<>"MAG, MABE",IF(SUM(F18:J18)>=2,1,0))))) -> 0
... A25: ='Listado CAPS'!A22 -> 0 | B25: ='Listado CAPS'!B22 -> 0 | C25: ='Listado CAPS'!C22 -> 0 | D25: ='Listado CAPS'!D22 -> S | K25: =IF(J25<>1,0,IF(E25="MABE",IF(SUM(F25:J25)>=3,1,0),IF(E25="MAG",IF(SUM(F25:J25)>=2,1,0),IF(E25<>"MAG, MABE",IF(SUM(F25:J25)>=2,1,0))))) -> 0
A26: ='Listado CAPS'!A23 -> 0 | B26: ='Listado CAPS'!B23 -> 0 | C26: ='Listado CAPS'!C23 -> 0 | D26: ='Listado CAPS'!D23 -> T | K26: =IF(E26="MABE",IF(SUM(F26:J26)>=3,1,0),IF(E26="MAG",IF(SUM(F26:J26)>=2,1,0),IF(E26<>"MAG, MABE",IF(SUM(F26:J26)>=2,1,0)))) -> 0
A27: ='Listado CAPS'!A24 -> 0 | B27: ='Listado CAPS'!B24 -> 0 | C27: ='Listado CAPS'!C24 -> 0 | D27: ='Listado CAPS'!D24 -> U | K27: =IF(E27="MABE",IF(SUM(F27:J27)>=3,1,0),IF(E27="MAG",IF(SUM(F27:J27)>=2,1,0),IF(E27<>"MAG, MABE",IF(SUM(F27:J27)>=2,1,0)))) -> 0
A28: ='Listado CAPS'!A25 -> 0 | B28: ='Listado CAPS'!B25 -> 0 | C28: ='Listado CAPS'!C25 -> 0 | D28: ='Listado CAPS'!D25 -> V | K28: =IF(E28="MABE",IF(SUM(F28:J28)>=3,1,0),IF(E28="MAG",IF(SUM(F28:J28)>=2,1,0),IF(E28<>"MAG, MABE",IF(SUM(F28:J28)>=2,1,0)))) -> 0
A29: ='Listado CAPS'!A26 -> 0 | B29: ='Listado CAPS'!B26 -> 0 | C29: ='Listado CAPS'!C26 -> 0 | D29: ='Listado CAPS'!D26 -> W | K29: =IF(E29="MABE",IF(SUM(F29:J29)>=3,1,0),IF(E29="MAG",IF(SUM(F29:J29)>=2,1,0),IF(E29<>"MAG, MABE",IF(SUM(F29:J29)>=2,1,0)))) -> 0
A30: ='Listado CAPS'!A27 -> 0 | B30: ='Listado CAPS'!B27 -> 0 | C30: ='Listado CAPS'!C27 -> 0 | D30: ='Listado CAPS'!D27 -> X | K30: =IF(E30="MABE",IF(SUM(F30:J30)>=3,1,0),IF(E30="MAG",IF(SUM(F30:J30)>=2,1,0),IF(E30<>"MAG, MABE",IF(SUM(F30:J30)>=2,1,0)))) -> 0
A31: ='Listado CAPS'!A28 -> 0 | B31: ='Listado CAPS'!B28 -> 0 | C31: ='Listado CAPS'!C28 -> 0 | D31: ='Listado CAPS'!D28 -> Y | K31: =IF(E31="MABE",IF(SUM(F31:J31)>=3,1,0),IF(E31="MAG",IF(SUM(F31:J31)>=2,1,0),IF(E31<>"MAG, MABE",IF(SUM(F31:J31)>=2,1,0)))) -> 0
BM123: 1- El Diamante.
BM124: 2- La Breiera
BM125: 3- Valle de Suni
BM126: 4- El Espino
BM127: 5- San Marcos
BM128: 6- Los Arados
BM129: 7- Lomas de Sacacli
BM130: 8- Sacacli
BM131: 9- Estación Cerro Grande
BM132: 10- Valerio
BM133: 11- Yupali
BM134: 12- Gracalcan
... BM148: 26- El Barro
N383: 1- El Diamante.
N384: 2- La Breiera
N385: 3- Valle de Suni
N386: 4- El Espino
N387: 5- San Marcos
N388: 6- Los Arados
N389: 7- Lomas de Sacacli
N390: 8- Sacacli
N391: 9- Estación Cerro Grande
N392: 10- Valerio
N393: 11- Yupali
N394: 12- Gracalcan
... N408: 26- El Barro

Sheet A.Org_CAPS
C1: Volver a Tabla de contenidos | D1: A. ORGANIZACIÓN DE LOS CAPS | AF1: Ir a Resultados Finales
D2: Instrucciones: 1) Para el llenado de este formato se debe utilizar el Libro de Actas. 2) Este formato se deberá repetir para cada CAPS. Se ha copiado esta tabla a continuación para el siguiente CAPS. 3) Digite los campos: nombre de la actividad, fecha, seleccione quién convoca y en la columna de quorum ponga 1 si hay quorum. (se considera quorum la asistencia de 50%+1); Digite el nùmero de cargos que participa con un 1. 4) El %de asistencia de mujeres en las asambleas se mete en %. Ejemplo: 40%. | R2: Criterio: Miembros activos: Que la suma del total de miembros sea igual o mayor que 4 para miembros activos en la toma de decisiones. Convocatoria: Al menos el 50% reuniones tienen que haber sido convocadas por CAPS. Mujeres: 50%.
A3: Departamento | B3: Municipio | C3: Comunidad | D3: CAPS | E3: No. | F3: Nombre de la actividad | G3: Fecha | H3: Quien Convoca? | I3: Quorum | J3: Valor de la convocatoria | K3: % de asistencia de mujeres en las asambleas | L3: Cargos JD
L4: Presidente | N4: Secretario/a | P4: Tesorero/a | R4: Fiscal | T4: Vocal_1 | V4: Vocal_2 | X4: Vocal_3 | Z4: Vocal_4 | AB4: Vocal_5 | AD4: Total de miembros activos (en%) | AE4: Total de miembros activos (en nº) | AF4: Total de Mujeres que participan | AG4: % De participación de la mujer | AH4: NOTAS
L5: H | M5: M | N5: H | O5: M | P5: H | Q5: M | R5: H | S5: M | T5: H | U5: M | V5: H | W5: M | X5: H | Y5: M | Z5: H | AA5: M | AB5: H | AC5: M | AJ5: CAPS
A6: ='Listado CAPS'!A3 -> Madriz | B6: ='Listado CAPS'!B3 -> Yalaguina | C6: ='Listado CAPS'!C3 -> Los Encuentros | D6: ='Listado CAPS'!D3 -> Los Encuentros | E6: 1 | F6: Asmablea de rendición de cuentas | G6: 45064 | H6: CAPS+OTROS | I6: 1 | J6: =IF(H6<>"OTROS",1,0)*IF(I6=1,1,0) -> 1 | K6: 0.6 | L6: 1 | O6: 1 | Q6: 1 | U6: 1 | AD6: =IF(SUM(L6:AC6)=0,0,SUM(L6:AC6)/'Conformación JD'!$X$7) -> 0.8 | AE6: =SUM(L6:AC6) -> 4 | AF6: =+AC6+AA6+Y6+W6+U6+S6+Q6+O6+M6 -> 3 | AG6: =IF(AE6=0,0,AF6/AE6) -> 0.75 | AJ6: CAPS+OTROS
E7: 2 | J7: =IF(H7<>"OTROS",1,0)*IF(I7=1,1,0) -> 0 | AD7: =IF(SUM(L7:AC7)=0,0,SUM(L7:AC7)/'Conformación JD'!$X$7) -> 0 | AE7: =SUM(L7:AC7) -> 0 | AF7: =+AC7+AA7+Y7+W7+U7+S7+Q7+O7+M7 -> 0 | AG7: =IF(AE7=0,0,AF7/AE7) -> 0 | AJ7: OTROS
E8: 3 | J8: =IF(H8<>"OTROS",1,0)*IF(I8=1,1,0) -> 0 | AD8: =IF(SUM(L8:AC8)=0,0,SUM(L8:AC8)/'Conformación JD'!$X$7) -> 0 | AE8: =SUM(L8:AC8) -> 0 | AF8: =+AC8+AA8+Y8+W8+U8+S8+Q8+O8+M8 -> 0 | AG8: =IF(AE8=0,0,AF8/AE8) -> 0
E9: 4 | J9: =IF(H9<>"OTROS",1,0)*IF(I9=1,1,0) -> 0 | AD9: =IF(SUM(L9:AC9)=0,0,SUM(L9:AC9)/'Conformación JD'!$X$7) -> 0 | AE9: =SUM(L9:AC9) -> 0 | AF9: =+AC9+AA9+Y9+W9+U9+S9+Q9+O9+M9 -> 0 | AG9: =IF(AE9=0,0,AF9/AE9) -> 0
E10: 5 | J10: =IF(H10<>"OTROS",1,0)*IF(I10=1,1,0) -> 0 | AD10: =IF(SUM(L10:AC10)=0,0,SUM(L10:AC10)/'Conformación JD'!$X$7) -> 0 | AE10: =SUM(L10:AC10) -> 0 | AF10: =+AC10+AA10+Y10+W10+U10+S10+Q10+O10+M10 -> 0 | AG10: =IF(AE10=0,0,AF10/AE10) -> 0
E11: 6 | J11: =IF(H11<>"OTROS",1,0)*IF(I11=1,1,0) -> 0 | AD11: =IF(SUM(L11:AC11)=0,0,SUM(L11:AC11)/'Conformación JD'!$X$7) -> 0 | AE11: =SUM(L11:AC11) -> 0 | AF11: =+AC11+AA11+Y11+W11+U11+S11+Q11+O11+M11 -> 0 | AG11: =IF(AE11=0,0,AF11/AE11) -> 0
E12: 7 | J12: =IF(H12<>"OTROS",1,0)*IF(I12=1,1,0) -> 0 | AD12: =IF(SUM(L12:AC12)=0,0,SUM(L12:AC12)/'Conformación JD'!$X$7) -> 0 | AE12: =SUM(L12:AC12) -> 0 | AF12: =+AC12+AA12+Y12+W12+U12+S12+Q12+O12+M12 -> 0 | AG12: =IF(AE12=0,0,AF12/AE12) -> 0
E13: 8 | J13: =IF(H13<>"OTROS",1,0)*IF(I13=1,1,0) -> 0 | AD13: =IF(SUM(L13:AC13)=0,0,SUM(L13:AC13)/'Conformación JD'!$X$7) -> 0 | AE13: =SUM(L13:AC13) -> 0 | AF13: =+AC13+AA13+Y13+W13+U13+S13+Q13+O13+M13 -> 0 | AG13: =IF(AE13=0,0,AF13/AE13) -> 0
E14: 9 | J14: =IF(H14<>"OTROS",1,0)*IF(I14=1,1,0) -> 0 | AD14: =IF(SUM(L14:AC14)=0,0,SUM(L14:AC14)/'Conformación JD'!$X$7) -> 0 | AE14: =SUM(L14:AC14) -> 0 | AF14: =+AC14+AA14+Y14+W14+U14+S14+Q14+O14+M14 -> 0 | AG14: =IF(AE14=0,0,AF14/AE14) -> 0
E15: 10 | J15: =IF(H15<>"OTROS",1,0)*IF(I15=1,1,0) -> 0 | AD15: =IF(SUM(L15:AC15)=0,0,SUM(L15:AC15)/'Conformación JD'!$X$7) -> 0 | AE15: =SUM(L15:AC15) -> 0 | AF15: =+AC15+AA15+Y15+W15+U15+S15+Q15+O15+M15 -> 0 | AG15: =IF(AE15=0,0,AF15/AE15) -> 0
E16: TOTAL | I16: =IF((COUNTIF(G6:G15,"<>"))<>0,SUM(I6:I15)/COUNTIF(G6:G15,"<>"),0) -> 1 | J16: =IF((COUNTIF(H6:H15,"<>"))<>0,SUM(J6:J15)/COUNTIF(H6:H15,"<>"),0) -> 1 | K16: =IF((COUNTIF(H6:H15,"<>"))<>0,SUM(K6:K15)/COUNTIF(H6:H15,"<>"),0) -> 0.6 | L16: =SUM(L6:L15) -> 1 | M16: =SUM(M6:M15) -> 0 | N16: =SUM(N6:N15) -> 0 | O16: =SUM(O6:O15) -> 1 | P16: =SUM(P6:P15) -> 0 | Q16: =SUM(Q6:Q15) -> 1 | R16: =SUM(R6:R15) -> 0 | S16: =SUM(S6:S15) -> 0 | ... AC16: =SUM(AC6:AC15) -> 0 | AD16: =IF(SUM(AD6:AD15)=0,0,SUM(AD6:AD15)/COUNTIF(AD6:AD15,"<>0")) -> 0.8 | AE16: =IF(SUM(AE6:AE15)=0,0,SUM(AE6:AE15)/COUNTIF(AE6:AE15,"<>0")) -> 4 | AF16: =IF(SUM(AF6:AF15)=0,0,SUM(AF6:AF15)/COUNTIF(AF6:AF15,"<>0")) -> 3 | AG16: =IF(SUM(AG6:AG15)=0,0,SUM(AG6:AG15)/COUNTIF(AD6:AD15,"<>0")) -> 0.75
A17: Departamento | B17: Municipio | C17: Comunidad | D17: CAPS | E17: No. | F17: Nombre de la actividad | G17: Fecha | H17: Quien Convoca? | I17: Quorum | J17: Valor de la convocatoria | K17: % de asistencia de mujeres en las asambleas | L17: Cargos JD
L18: Presidente | N18: Secretario/a | P18: Tesorero/a | R18: Fiscal | T18: Vocal_1 | V18: Vocal_2 | X18: Vocal_3 | Z18: Vocal_4 | AB18: Vocal_5 | AD18: Total de miembros activos (en%) | AE18: Total de miembros activos (en nº) | AF18: Total de Mujeres que participan | AG18: % De participación de la mujer | AH18: NOTAS
L19: H | M19: M | N19: H | O19: M | P19: H | Q19: M | R19: H | S19: M | T19: H | U19: M | V19: H | W19: M | X19: H | Y19: M | Z19: H | AA19: M | AB19: H | AC19: M
A20: ='Listado CAPS'!A17 -> 0 | B20: ='Listado CAPS'!B17 -> 0 | C20: ='Listado CAPS'!C17 -> 0 | D20: ='Listado CAPS'!D4 -> B | E20: 1 | J20: =IF(H20<>"OTROS",1,0)*IF(I20=1,1,0) -> 0 | AD20: =IF(SUM(L20:AC20)=0,0,SUM(L20:AC20)/'Conformación JD'!$X$8) -> 0 | AE20: =SUM(L20:AC20) -> 0 | AF20: =+AC20+AA20+Y20+W20+U20+S20+Q20+O20+M20 -> 0 | AG20: =IF(AE20=0,0,AF20/AE20) -> 0
E21: 2 | J21: =IF(H21<>"OTROS",1,0)*IF(I21=1,1,0) -> 0 | AD21: =IF(SUM(L21:AC21)=0,0,SUM(L21:AC21)/'Conformación JD'!$X$8) -> 0 | AE21: =SUM(L21:AC21) -> 0 | AF21: =+AC21+AA21+Y21+W21+U21+S21+Q21+O21+M21 -> 0 | AG21: =IF(AE21=0,0,AF21/AE21) -> 0
E22: 3 | J22: =IF(H22<>"OTROS",1,0)*IF(I22=1,1,0) -> 0 | AD22: =IF(SUM(L22:AC22)=0,0,SUM(L22:AC22)/'Conformación JD'!$X$8) -> 0 | AE22: =SUM(L22:AC22) -> 0 | AF22: =+AC22+AA22+Y22+W22+U22+S22+Q22+O22+M22 -> 0 | AG22: =IF(AE22=0,0,AF22/AE22) -> 0
E23: 4 | J23: =IF(H23<>"OTROS",1,0)*IF(I23=1,1,0) -> 0 | AD23: =IF(SUM(L23:AC23)=0,0,SUM(L23:AC23)/'Conformación JD'!$X$8) -> 0 | AE23: =SUM(L23:AC23) -> 0 | AF23: =+AC23+AA23+Y23+W23+U23+S23+Q23+O23+M23 -> 0 | AG23: =IF(AE23=0,0,AF23/AE23) -> 0
E24: 5 | J24: =IF(H24<>"OTROS",1,0)*IF(I24=1,1,0) -> 0 | AD24: =IF(SUM(L24:AC24)=0,0,SUM(L24:AC24)/'Conformación JD'!$X$8) -> 0 | AE24: =SUM(L24:AC24) -> 0 | AF24: =+AC24+AA24+Y24+W24+U24+S24+Q24+O24+M24 -> 0 | AG24: =IF(AE24=0,0,AF24/AE24) -> 0
E25: 6 | J25: =IF(H25<>"OTROS",1,0)*IF(I25=1,1,0) -> 0 | AD25: =IF(SUM(L25:AC25)=0,0,SUM(L25:AC25)/'Conformación JD'!$X$8) -> 0 | AE25: =SUM(L25:AC25) -> 0 | AF25: =+AC25+AA25+Y25+W25+U25+S25+Q25+O25+M25 -> 0 | AG25: =IF(AE25=0,0,AF25/AE25) -> 0
E26: 7 | J26: =IF(H26<>"OTROS",1,0)*IF(I26=1,1,0) -> 0 | AD26: =IF(SUM(L26:AC26)=0,0,SUM(L26:AC26)/'Conformación JD'!$X$8) -> 0 | AE26: =SUM(L26:AC26) -> 0 | AF26: =+AC26+AA26+Y26+W26+U26+S26+Q26+O26+M26 -> 0 | AG26: =IF(AE26=0,0,AF26/AE26) -> 0
E27: 8 | J27: =IF(H27<>"OTROS",1,0)*IF(I27=1,1,0) -> 0 | AD27: =IF(SUM(L27:AC27)=0,0,SUM(L27:AC27)/'Conformación JD'!$X$8) -> 0 | AE27: =SUM(L27:AC27) -> 0 | AF27: =+AC27+AA27+Y27+W27+U27+S27+Q27+O27+M27 -> 0 | AG27: =IF(AE27=0,0,AF27/AE27) -> 0
E28: 9 | J28: =IF(H28<>"OTROS",1,0)*IF(I28=1,1,0) -> 0 | AD28: =IF(SUM(L28:AC28)=0,0,SUM(L28:AC28)/'Conformación JD'!$X$8) -> 0 | AE28: =SUM(L28:AC28) -> 0 | AF28: =+AC28+AA28+Y28+W28+U28+S28+Q28+O28+M28 -> 0 | AG28: =IF(AE28=0,0,AF28/AE28) -> 0
E29: 10 | J29: =IF(H29<>"OTROS",1,0)*IF(I29=1,1,0) -> 0 | AD29: =IF(SUM(L29:AC29)=0,0,SUM(L29:AC29)/'Conformación JD'!$X$8) -> 0 | AE29: =SUM(L29:AC29) -> 0 | AF29: =+AC29+AA29+Y29+W29+U29+S29+Q29+O29+M29 -> 0 | AG29: =IF(AE29=0,0,AF29/AE29) -> 0
E30: TOTAL | I30: =IF((COUNTIF(G20:G29,"<>"))<>0,SUM(I20:I29)/COUNTIF(G20:G29,"<>"),0) -> 0 | J30: =IF((COUNTIF(H20:H29,"<>"))<>0,SUM(J20:J29)/COUNTIF(H20:H29,"<>"),0) -> 0 | K30: =IF((COUNTIF(H20:H29,"<>"))<>0,SUM(K20:K29)/COUNTIF(H20:H29,"<>"),0) -> 0 | L30: =SUM(L20:L29) -> 0 | M30: =SUM(M20:M29) -> 0 | N30: =SUM(N20:N29) -> 0 | O30: =SUM(O20:O29) -> 0 | P30: =SUM(P20:P29) -> 0 | Q30: =SUM(Q20:Q29) -> 0 | R30: =SUM(R20:R29) -> 0 | S30: =SUM(S20:S29) -> 0 | ... AC30: =SUM(AC20:AC29) -> 0 | AD30: =IF(SUM(AD20:AD29)=0,0,SUM(AD20:AD29)/COUNTIF(AD20:AD29,"<>0")) -> 0 | AE30: =IF(SUM(AE20:AE29)=0,0,SUM(AE20:AE29)/COUNTIF(AE20:AE29,"<>0")) -> 0 | AF30: =IF(SUM(AF20:AF29)=0,0,SUM(AF20:AF29)/COUNTIF(AF20:AF29,"<>0")) -> 0 | AG30: =IF(SUM(AG20:AG29)=0,0,SUM(AG20:AG29)/COUNTIF(AD20:AD29,"<>0")) -> 0
A31: Departamento | B31: Municipio | C31: Comunidad | D31: CAPS | E31: No. | F31: Nombre de la actividad | G31: Fecha | H31: Quien Convoca? | I31: Quorum | J31: Valor de la convocatoria | K31: % de asistencia de mujeres en las asambleas | L31: Cargos JD
L32: Presidente | N32: Secretario/a | P32: Tesorero/a | R32: Fiscal | T32: Vocal_1 | V32: Vocal_2 | X32: Vocal_3 | Z32: Vocal_4 | AB32: Vocal_5 | AD32: Total de miembros activos (en%) | AE32: Total de miembros activos (en nº) | AF32: Total de Mujeres que participan | AG32: % De participación de la mujer | AH32: NOTAS
L33: H | M33: M | N33: H | O33: M | P33: H | Q33: M | R33: H | S33: M | T33: H | U33: M | V33: H | W33: M | X33: H | Y33: M | Z33: H | AA33: M | AB33: H | AC33: M
A34: ='Listado CAPS'!A31 -> 0 | B34: ='Listado CAPS'!B31 -> 0 | C34: ='Listado CAPS'!C31 -> 0 | D34: ='Listado CAPS'!D5 -> C | E34: 1 | J34: =IF(H34<>"OTROS",1,0)*IF(I34=1,1,0) -> 0 | AD34: =IF(SUM(L34:AC34)=0,0,SUM(L34:AC34)/'Conformación JD'!$X$9) -> 0 | AE34: =SUM(L34:AC34) -> 0 | AF34: =+AC34+AA34+Y34+W34+U34+S34+Q34+O34+M34 -> 0 | AG34: =IF(AE34=0,0,AF34/AE34) -> 0
E35: 2 | J35: =IF(H35<>"OTROS",1,0)*IF(I35=1,1,0) -> 0 | AD35: =IF(SUM(L35:AC35)=0,0,SUM(L35:AC35)/'Conformación JD'!$X$9) -> 0 | AE35: =SUM(L35:AC35) -> 0 | AF35: =+AC35+AA35+Y35+W35+U35+S35+Q35+O35+M35 -> 0 | AG35: =IF(AE35=0,0,AF35/AE35) -> 0
E36: 3 | J36: =IF(H36<>"OTROS",1,0)*IF(I36=1,1,0) -> 0 | AD36: =IF(SUM(L36:AC36)=0,0,SUM(L36:AC36)/'Conformación JD'!$X$9) -> 0 | AE36: =SUM(L36:AC36) -> 0 | AF36: =+AC36+AA36+Y36+W36+U36+S36+Q36+O36+M36 -> 0 | AG36: =IF(AE36=0,0,AF36/AE36) -> 0
E37: 4 | J37: =IF(H37<>"OTROS",1,0)*IF(I37=1,1,0) -> 0 | AD37: =IF(SUM(L37:AC37)=0,0,SUM(L37:AC37)/'Conformación JD'!$X$9) -> 0 | AE37: =SUM(L37:AC37) -> 0 | AF37: =+AC37+AA37+Y37+W37+U37+S37+Q37+O37+M37 -> 0 | AG37: =IF(AE37=0,0,AF37/AE37) -> 0
E38: 5 | J38: =IF(H38<>"OTROS",1,0)*IF(I38=1,1,0) -> 0 | AD38: =IF(SUM(L38:AC38)=0,0,SUM(L38:AC38)/'Conformación JD'!$X$9) -> 0 | AE38: =SUM(L38:AC38) -> 0 | AF38: =+AC38+AA38+Y38+W38+U38+S38+Q38+O38+M38 -> 0 | AG38: =IF(AE38=0,0,AF38/AE38) -> 0
E39: 6 | J39: =IF(H39<>"OTROS",1,0)*IF(I39=1,1,0) -> 0 | AD39: =IF(SUM(L39:AC39)=0,0,SUM(L39:AC39)/'Conformación JD'!$X$9) -> 0 | AE39: =SUM(L39:AC39) -> 0 | AF39: =+AC39+AA39+Y39+W39+U39+S39+Q39+O39+M39 -> 0 | AG39: =IF(AE39=0,0,AF39/AE39) -> 0
E40: 7 | J40: =IF(H40<>"OTROS",1,0)*IF(I40=1,1,0) -> 0 | AD40: =IF(SUM(L40:AC40)=0,0,SUM(L40:AC40)/'Conformación JD'!$X$9) -> 0 | AE40: =SUM(L40:AC40) -> 0 | AF40: =+AC40+AA40+Y40+W40+U40+S40+Q40+O40+M40 -> 0 | AG40: =IF(AE40=0,0,AF40/AE40) -> 0
E41: 8 | J41: =IF(H41<>"OTROS",1,0)*IF(I41=1,1,0) -> 0 | AD41: =IF(SUM(L41:AC41)=0,0,SUM(L41:AC41)/'Conformación JD'!$X$9) -> 0 | AE41: =SUM(L41:AC41) -> 0 | AF41: =+AC41+AA41+Y41+W41+U41+S41+Q41+O41+M41 -> 0 | AG41: =IF(AE41=0,0,AF41/AE41) -> 0
E42: 9 | J42: =IF(H42<>"OTROS",1,0)*IF(I42=1,1,0) -> 0 | AD42: =IF(SUM(L42:AC42)=0,0,SUM(L42:AC42)/'Conformación JD'!$X$9) -> 0 | AE42: =SUM(L42:AC42) -> 0 | AF42: =+AC42+AA42+Y42+W42+U42+S42+Q42+O42+M42 -> 0 | AG42: =IF(AE42=0,0,AF42/AE42) -> 0
E43: 10 | J43: =IF(H43<>"OTROS",1,0)*IF(I43=1,1,0) -> 0 | AD43: =IF(SUM(L43:AC43)=0,0,SUM(L43:AC43)/'Conformación JD'!$X$9) -> 0 | AE43: =SUM(L43:AC43) -> 0 | AF43: =+AC43+AA43+Y43+W43+U43+S43+Q43+O43+M43 -> 0 | AG43: =IF(AE43=0,0,AF43/AE43) -> 0
E44: TOTAL | I44: =IF((COUNTIF(G34:G43,"<>"))<>0,SUM(I34:I43)/COUNTIF(G34:G43,"<>"),0) -> 0 | J44: =IF((COUNTIF(H34:H43,"<>"))<>0,SUM(J34:J43)/COUNTIF(H34:H43,"<>"),0) -> 0 | K44: =IF((COUNTIF(H34:H43,"<>"))<>0,SUM(K34:K43)/COUNTIF(H34:H43,"<>"),0) -> 0 | L44: =SUM(L34:L43) -> 0 | M44: =SUM(M34:M43) -> 0 | N44: =SUM(N34:N43) -> 0 | O44: =SUM(O34:O43) -> 0 | P44: =SUM(P34:P43) -> 0 | Q44: =SUM(Q34:Q43) -> 0 | R44: =SUM(R34:R43) -> 0 | S44: =SUM(S34:S43) -> 0 | ... AC44: =SUM(AC34:AC43) -> 0 | AD44: =IF(SUM(AD34:AD43)=0,0,SUM(AD34:AD43)/COUNTIF(AD34:AD43,"<>0")) -> 0 | AE44: =IF(SUM(AE34:AE43)=0,0,SUM(AE34:AE43)/COUNTIF(AE34:AE43,"<>0")) -> 0 | AF44: =IF(SUM(AF34:AF43)=0,0,SUM(AF34:AF43)/COUNTIF(AF34:AF43,"<>0")) -> 0 | AG44: =IF(SUM(AG34:AG43)=0,0,SUM(AG34:AG43)/COUNTIF(AD34:AD43,"<>0")) -> 0
A45: Departamento | B45: Municipio | C45: Comunidad | D45: CAPS | E45: No. | F45: Nombre de la actividad | G45: Fecha | H45: Quien Convoca? | I45: Quorum | J45: Valor de la convocatoria | K45: % de asistencia de mujeres en las asambleas | L45: Cargos JD
L46: Presidente | N46: Secretario/a | P46: Tesorero/a | R46: Fiscal | T46: Vocal_1 | V46: Vocal_2 | X46: Vocal_3 | Z46: Vocal_4 | AB46: Vocal_5 | AD46: Total de miembros activos (en%) | AE46: Total de miembros activos (en nº) | AF46: Total de Mujeres que participan | AG46: % De participación de la mujer | AH46: NOTAS
L47: H | M47: M | N47: H | O47: M | P47: H | Q47: M | R47: H | S47: M | T47: H | U47: M | V47: H | W47: M | X47: H | Y47: M | Z47: H | AA47: M | AB47: H | AC47: M
A48: ='Listado CAPS'!A45 -> 0 | B48: ='Listado CAPS'!B45 -> 0 | C48: ='Listado CAPS'!C45 -> 0 | D48: ='Listado CAPS'!D6 -> D | E48: 1 | J48: =IF(H48<>"OTROS",1,0)*IF(I48=1,1,0) -> 0 | AD48: =IF(SUM(L48:AC48)=0,0,SUM(L48:AC48)/'Conformación JD'!$X$10) -> 0 | AE48: =SUM(L48:AC48) -> 0 | AF48: =+AC48+AA48+Y48+W48+U48+S48+Q48+O48+M48 -> 0 | AG48: =IF(AE48=0,0,AF48/AE48) -> 0
E49: 2 | J49: =IF(H49<>"OTROS",1,0)*IF(I49=1,1,0) -> 0 | AD49: =IF(SUM(L49:AC49)=0,0,SUM(L49:AC49)/'Conformación JD'!$X$10) -> 0 | AE49: =SUM(L49:AC49) -> 0 | AF49: =+AC49+AA49+Y49+W49+U49+S49+Q49+O49+M49 -> 0 | AG49: =IF(AE49=0,0,AF49/AE49) -> 0
E50: 3 | J50: =IF(H50<>"OTROS",1,0)*IF(I50=1,1,0) -> 0 | AD50: =IF(SUM(L50:AC50)=0,0,SUM(L50:AC50)/'Conformación JD'!$X$10) -> 0 | AE50: =SUM(L50:AC50) -> 0 | AF50: =+AC50+AA50+Y50+W50+U50+S50+Q50+O50+M50 -> 0 | AG50: =IF(AE50=0,0,AF50/AE50) -> 0
E51: 4 | J51: =IF(H51<>"OTROS",1,0)*IF(I51=1,1,0) -> 0 | AD51: =IF(SUM(L51:AC51)=0,0,SUM(L51:AC51)/'Conformación JD'!$X$10) -> 0 | AE51: =SUM(L51:AC51) -> 0 | AF51: =+AC51+AA51+Y51+W51+U51+S51+Q51+O51+M51 -> 0 | AG51: =IF(AE51=0,0,AF51/AE51) -> 0
E52: 5 | J52: =IF(H52<>"OTROS",1,0)*IF(I52=1,1,0) -> 0 | AD52: =IF(SUM(L52:AC52)=0,0,SUM(L52:AC52)/'Conformación JD'!$X$10) -> 0 | AE52: =SUM(L52:AC52) -> 0 | AF52: =+AC52+AA52+Y52+W52+U52+S52+Q52+O52+M52 -> 0 | AG52: =IF(AE52=0,0,AF52/AE52) -> 0
E53: 6 | J53: =IF(H53<>"OTROS",1,0)*IF(I53=1,1,0) -> 0 | AD53: =IF(SUM(L53:AC53)=0,0,SUM(L53:AC53)/'Conformación JD'!$X$10) -> 0 | AE53: =SUM(L53:AC53) -> 0 | AF53: =+AC53+AA53+Y53+W53+U53+S53+Q53+O53+M53 -> 0 | AG53: =IF(AE53=0,0,AF53/AE53) -> 0
E54: 7 | J54: =IF(H54<>"OTROS",1,0)*IF(I54=1,1,0) -> 0 | AD54: =IF(SUM(L54:AC54)=0,0,SUM(L54:AC54)/'Conformación JD'!$X$10) -> 0 | AE54: =SUM(L54:AC54) -> 0 | AF54: =+AC54+AA54+Y54+W54+U54+S54+Q54+O54+M54 -> 0 | AG54: =IF(AE54=0,0,AF54/AE54) -> 0
E55: 8 | J55: =IF(H55<>"OTROS",1,0)*IF(I55=1,1,0) -> 0 | AD55: =IF(SUM(L55:AC55)=0,0,SUM(L55:AC55)/'Conformación JD'!$X$10) -> 0 | AE55: =SUM(L55:AC55) -> 0 | AF55: =+AC55+AA55+Y55+W55+U55+S55+Q55+O55+M55 -> 0 | AG55: =IF(AE55=0,0,AF55/AE55) -> 0
E56: 9 | J56: =IF(H56<>"OTROS",1,0)*IF(I56=1,1,0) -> 0 | AD56: =IF(SUM(L56:AC56)=0,0,SUM(L56:AC56)/'Conformación JD'!$X$10) -> 0 | AE56: =SUM(L56:AC56) -> 0 | AF56: =+AC56+AA56+Y56+W56+U56+S56+Q56+O56+M56 -> 0 | AG56: =IF(AE56=0,0,AF56/AE56) -> 0
E57: 10 | J57: =IF(H57<>"OTROS",1,0)*IF(I57=1,1,0) -> 0 | AD57: =IF(SUM(L57:AC57)=0,0,SUM(L57:AC57)/'Conformación JD'!$X$10) -> 0 | AE57: =SUM(L57:AC57) -> 0 | AF57: =+AC57+AA57+Y57+W57+U57+S57+Q57+O57+M57 -> 0 | AG57: =IF(AE57=0,0,AF57/AE57) -> 0
E58: TOTAL | I58: =IF((COUNTIF(G48:G57,"<>"))<>0,SUM(I48:I57)/COUNTIF(G48:G57,"<>"),0) -> 0 | J58: =IF((COUNTIF(H48:H57,"<>"))<>0,SUM(J48:J57)/COUNTIF(H48:H57,"<>"),0) -> 0 | K58: =IF((COUNTIF(H48:H57,"<>"))<>0,SUM(K48:K57)/COUNTIF(H48:H57,"<>"),0) -> 0 | L58: =SUM(L48:L57) -> 0 | M58: =SUM(M48:M57) -> 0 | N58: =SUM(N48:N57) -> 0 | O58: =SUM(O48:O57) -> 0 | P58: =SUM(P48:P57) -> 0 | Q58: =SUM(Q48:Q57) -> 0 | R58: =SUM(R48:R57) -> 0 | S58: =SUM(S48:S57) -> 0 | ... AC58: =SUM(AC48:AC57) -> 0 | AD58: =IF(SUM(AD48:AD57)=0,0,SUM(AD48:AD57)/COUNTIF(AD48:AD57,"<>0")) -> 0 | AE58: =IF(SUM(AE48:AE57)=0,0,SUM(AE48:AE57)/COUNTIF(AE48:AE57,"<>0")) -> 0 | AF58: =IF(SUM(AF48:AF57)=0,0,SUM(AF48:AF57)/COUNTIF(AF48:AF57,"<>0")) -> 0 | AG58: =IF(SUM(AG48:AG57)=0,0,SUM(AG48:AG57)/COUNTIF(AD48:AD57,"<>0")) -> 0
A59: Departamento | B59: Municipio | C59: Comunidad | D59: CAPS | E59: No. | F59: Nombre de la actividad | G59: Fecha | H59: Quien Convoca? | I59: Quorum | J59: Valor de la convocatoria | K59: % de asistencia de mujeres en las asambleas | L59: Cargos JD
L60: Presidente | N60: Secretario/a | P60: Tesorero/a | R60: Fiscal | T60: Vocal_1 | V60: Vocal_2 | X60: Vocal_3 | Z60: Vocal_4 | AB60: Vocal_5 | AD60: Total de miembros activos (en%) | AE60: Total de miembros activos (en nº) | AF60: Total de Mujeres que participan | AG60: % De participación de la mujer | AH60: NOTAS
L61: H | M61: M | N61: H | O61: M | P61: H | Q61: M | R61: H | S61: M | T61: H | U61: M | V61: H | W61: M | X61: H | Y61: M | Z61: H | AA61: M | AB61: H | AC61: M
A62: ='Listado CAPS'!A59 -> 0 | B62: ='Listado CAPS'!B59 -> 0 | C62: ='Listado CAPS'!C59 -> 0 | D62: ='Listado CAPS'!D7 -> E | E62: 1 | J62: =IF(H62<>"OTROS",1,0)*IF(I62=1,1,0) -> 0 | AD62: =IF(SUM(L62:AC62)=0,0,SUM(L62:AC62)/'Conformación JD'!$X$11) -> 0 | AE62: =SUM(L62:AC62) -> 0 | AF62: =+AC62+AA62+Y62+W62+U62+S62+Q62+O62+M62 -> 0 | AG62: =IF(AE62=0,0,AF62/AE62) -> 0
E63: 2 | J63: =IF(H63<>"OTROS",1,0)*IF(I63=1,1,0) -> 0 | AD63: =IF(SUM(L63:AC63)=0,0,SUM(L63:AC63)/'Conformación JD'!$X$11) -> 0 | AE63: =SUM(L63:AC63) -> 0 | AF63: =+AC63+AA63+Y63+W63+U63+S63+Q63+O63+M63 -> 0 | AG63: =IF(AE63=0,0,AF63/AE63) -> 0
E64: 3 | J64: =IF(H64<>"OTROS",1,0)*IF(I64=1,1,0) -> 0 | AD64: =IF(SUM(L64:AC64)=0,0,SUM(L64:AC64)/'Conformación JD'!$X$11) -> 0 | AE64: =SUM(L64:AC64) -> 0 | AF64: =+AC64+AA64+Y64+W64+U64+S64+Q64+O64+M64 -> 0 | AG64: =IF(AE64=0,0,AF64/AE64) -> 0
E65: 4 | J65: =IF(H65<>"OTROS",1,0)*IF(I65=1,1,0) -> 0 | AD65: =IF(SUM(L65:AC65)=0,0,SUM(L65:AC65)/'Conformación JD'!$X$11) -> 0 | AE65: =SUM(L65:AC65) -> 0 | AF65: =+AC65+AA65+Y65+W65+U65+S65+Q65+O65+M65 -> 0 | AG65: =IF(AE65=0,0,AF65/AE65) -> 0
E66: 5 | J66: =IF(H66<>"OTROS",1,0)*IF(I66=1,1,0) -> 0 | AD66: =IF(SUM(L66:AC66)=0,0,SUM(L66:AC66)/'Conformación JD'!$X$11) -> 0 | AE66: =SUM(L66:AC66) -> 0 | AF66: =+AC66+AA66+Y66+W66+U66+S66+Q66+O66+M66 -> 0 | AG66: =IF(AE66=0,0,AF66/AE66) -> 0
E67: 6 | J67: =IF(H67<>"OTROS",1,0)*IF(I67=1,1,0) -> 0 | AD67: =IF(SUM(L67:AC67)=0,0,SUM(L67:AC67)/'Conformación JD'!$X$11) -> 0 | AE67: =SUM(L67:AC67) -> 0 | AF67: =+AC67+AA67+Y67+W67+U67+S67+Q67+O67+M67 -> 0 | AG67: =IF(AE67=0,0,AF67/AE67) -> 0
E68: 7 | J68: =IF(H68<>"OTROS",1,0)*IF(I68=1,1,0) -> 0 | AD68: =IF(SUM(L68:AC68)=0,0,SUM(L68:AC68)/'Conformación JD'!$X$11) -> 0 | AE68: =SUM(L68:AC68) -> 0 | AF68: =+AC68+AA68+Y68+W68+U68+S68+Q68+O68+M68 -> 0 | AG68: =IF(AE68=0,0,AF68/AE68) -> 0
E69: 8 | J69: =IF(H69<>"OTROS",1,0)*IF(I69=1,1,0) -> 0 | AD69: =IF(SUM(L69:AC69)=0,0,SUM(L69:AC69)/'Conformación JD'!$X$11) -> 0 | AE69: =SUM(L69:AC69) -> 0 | AF69: =+AC69+AA69+Y69+W69+U69+S69+Q69+O69+M69 -> 0 | AG69: =IF(AE69=0,0,AF69/AE69) -> 0
E70: 9 | J70: =IF(H70<>"OTROS",1,0)*IF(I70=1,1,0) -> 0 | AD70: =IF(SUM(L70:AC70)=0,0,SUM(L70:AC70)/'Conformación JD'!$X$11) -> 0 | AE70: =SUM(L70:AC70) -> 0 | AF70: =+AC70+AA70+Y70+W70+U70+S70+Q70+O70+M70 -> 0 | AG70: =IF(AE70=0,0,AF70/AE70) -> 0
E71: 10 | J71: =IF(H71<>"OTROS",1,0)*IF(I71=1,1,0) -> 0 | AD71: =IF(SUM(L71:AC71)=0,0,SUM(L71:AC71)/'Conformación JD'!$X$11) -> 0 | AE71: =SUM(L71:AC71) -> 0 | AF71: =+AC71+AA71+Y71+W71+U71+S71+Q71+O71+M71 -> 0 | AG71: =IF(AE71=0,0,AF71/AE71) -> 0
E72: TOTAL | I72: =IF((COUNTIF(G62:G71,"<>"))<>0,SUM(I62:I71)/COUNTIF(G62:G71,"<>"),0) -> 0 | J72: =IF((COUNTIF(H62:H71,"<>"))<>0,SUM(J62:J71)/COUNTIF(H62:H71,"<>"),0) -> 0 | K72: =IF((COUNTIF(H62:H71,"<>"))<>0,SUM(K62:K71)/COUNTIF(H62:H71,"<>"),0) -> 0 | L72: =SUM(L62:L71) -> 0 | M72: =SUM(M62:M71) -> 0 | N72: =SUM(N62:N71) -> 0 | O72: =SUM(O62:O71) -> 0 | P72: =SUM(P62:P71) -> 0 | Q72: =SUM(Q62:Q71) -> 0 | R72: =SUM(R62:R71) -> 0 | S72: =SUM(S62:S71) -> 0 | ... AC72: =SUM(AC62:AC71) -> 0 | AD72: =IF(SUM(AD62:AD71)=0,0,SUM(AD62:AD71)/COUNTIF(AD62:AD71,"<>0")) -> 0 | AE72: =IF(SUM(AE62:AE71)=0,0,SUM(AE62:AE71)/COUNTIF(AE62:AE71,"<>0")) -> 0 | AF72: =IF(SUM(AF62:AF71)=0,0,SUM(AF62:AF71)/COUNTIF(AF62:AF71,"<>0")) -> 0 | AG72: =IF(SUM(AG62:AG71)=0,0,SUM(AG62:AG71)/COUNTIF(AD62:AD71,"<>0")) -> 0
A73: Departamento | B73: Municipio | C73: Comunidad | D73: CAPS | E73: No. | F73: Nombre de la actividad | G73: Fecha | H73: Quien Convoca? | I73: Quorum | J73: Valor de la convocatoria | K73: % de asistencia de mujeres en las asambleas | L73: Cargos JD
L74: Presidente | N74: Secretario/a | P74: Tesorero/a | R74: Fiscal | T74: Vocal_1 | V74: Vocal_2 | X74: Vocal_3 | Z74: Vocal_4 | AB74: Vocal_5 | AD74: Total de miembros activos (en%) | AE74: Total de miembros activos (en nº) | AF74: Total de Mujeres que participan | AG74: % De participación de la mujer | AH74: NOTAS
L75: H | M75: M | N75: H | O75: M | P75: H | Q75: M | R75: H | S75: M | T75: H | U75: M | V75: H | W75: M | X75: H | Y75: M | Z75: H | AA75: M | AB75: H | AC75: M
A76: ='Listado CAPS'!A73 -> 0 | B76: ='Listado CAPS'!B73 -> 0 | C76: ='Listado CAPS'!C73 -> 0 | D76: ='Listado CAPS'!D8 -> F | E76: 1 | J76: =IF(H76<>"OTROS",1,0)*IF(I76=1,1,0) -> 0 | AD76: =IF(SUM(L76:AC76)=0,0,SUM(L76:AC76)/'Conformación JD'!$X$12) -> 0 | AE76: =SUM(L76:AC76) -> 0 | AF76: =+AC76+AA76+Y76+W76+U76+S76+Q76+O76+M76 -> 0 | AG76: =IF(AE76=0,0,AF76/AE76) -> 0
E77: 2 | J77: =IF(H77<>"OTROS",1,0)*IF(I77=1,1,0) -> 0 | AD77: =IF(SUM(L77:AC77)=0,0,SUM(L77:AC77)/'Conformación JD'!$X$12) -> 0 | AE77: =SUM(L77:AC77) -> 0 | AF77: =+AC77+AA77+Y77+W77+U77+S77+Q77+O77+M77 -> 0 | AG77: =IF(AE77=0,0,AF77/AE77) -> 0
E78: 3 | J78: =IF(H78<>"OTROS",1,0)*IF(I78=1,1,0) -> 0 | AD78: =IF(SUM(L78:AC78)=0,0,SUM(L78:AC78)/'Conformación JD'!$X$12) -> 0 | AE78: =SUM(L78:AC78) -> 0 | AF78: =+AC78+AA78+Y78+W78+U78+S78+Q78+O78+M78 -> 0 | AG78: =IF(AE78=0,0,AF78/AE78) -> 0
E79: 4 | J79: =IF(H79<>"OTROS",1,0)*IF(I79=1,1,0) -> 0 | AD79: =IF(SUM(L79:AC79)=0,0,SUM(L79:AC79)/'Conformación JD'!$X$12) -> 0 | AE79: =SUM(L79:AC79) -> 0 | AF79: =+AC79+AA79+Y79+W79+U79+S79+Q79+O79+M79 -> 0 | AG79: =IF(AE79=0,0,AF79/AE79) -> 0
E80: 5 | J80: =IF(H80<>"OTROS",1,0)*IF(I80=1,1,0) -> 0 | AD80: =IF(SUM(L80:AC80)=0,0,SUM(L80:AC80)/'Conformación JD'!$X$12) -> 0 | AE80: =SUM(L80:AC80) -> 0 | AF80: =+AC80+AA80+Y80+W80+U80+S80+Q80+O80+M80 -> 0 | AG80: =IF(AE80=0,0,AF80/AE80) -> 0
E81: 6 | J81: =IF(H81<>"OTROS",1,0)*IF(I81=1,1,0) -> 0 | AD81: =IF(SUM(L81:AC81)=0,0,SUM(L81:AC81)/'Conformación JD'!$X$12) -> 0 | AE81: =SUM(L81:AC81) -> 0 | AF81: =+AC81+AA81+Y81+W81+U81+S81+Q81+O81+M81 -> 0 | AG81: =IF(AE81=0,0,AF81/AE81) -> 0
E82: 7 | J82: =IF(H82<>"OTROS",1,0)*IF(I82=1,1,0) -> 0 | AD82: =IF(SUM(L82:AC82)=0,0,SUM(L82:AC82)/'Conformación JD'!$X$12) -> 0 | AE82: =SUM(L82:AC82) -> 0 | AF82: =+AC82+AA82+Y82+W82+U82+S82+Q82+O82+M82 -> 0 | AG82: =IF(AE82=0,0,AF82/AE82) -> 0
E83: 8 | J83: =IF(H83<>"OTROS",1,0)*IF(I83=1,1,0) -> 0 | AD83: =IF(SUM(L83:AC83)=0,0,SUM(L83:AC83)/'Conformación JD'!$X$12) -> 0 | AE83: =SUM(L83:AC83) -> 0 | AF83: =+AC83+AA83+Y83+W83+U83+S83+Q83+O83+M83 -> 0 | AG83: =IF(AE83=0,0,AF83/AE83) -> 0
E84: 9 | J84: =IF(H84<>"OTROS",1,0)*IF(I84=1,1,0) -> 0 | AD84: =IF(SUM(L84:AC84)=0,0,SUM(L84:AC84)/'Conformación JD'!$X$12) -> 0 | AE84: =SUM(L84:AC84) -> 0 | AF84: =+AC84+AA84+Y84+W84+U84+S84+Q84+O84+M84 -> 0 | AG84: =IF(AE84=0,0,AF84/AE84) -> 0
E85: 10 | J85: =IF(H85<>"OTROS",1,0)*IF(I85=1,1,0) -> 0 | AD85: =IF(SUM(L85:AC85)=0,0,SUM(L85:AC85)/'Conformación JD'!$X$12) -> 0 | AE85: =SUM(L85:AC85) -> 0 | AF85: =+AC85+AA85+Y85+W85+U85+S85+Q85+O85+M85 -> 0 | AG85: =IF(AE85=0,0,AF85/AE85) -> 0
E86: TOTAL | I86: =IF((COUNTIF(G76:G85,"<>"))<>0,SUM(I76:I85)/COUNTIF(G76:G85,"<>"),0) -> 0 | J86: =IF((COUNTIF(H76:H85,"<>"))<>0,SUM(J76:J85)/COUNTIF(H76:H85,"<>"),0) -> 0 | K86: =IF((COUNTIF(H76:H85,"<>"))<>0,SUM(K76:K85)/COUNTIF(H76:H85,"<>"),0) -> 0 | L86: =SUM(L76:L85) -> 0 | M86: =SUM(M76:M85) -> 0 | N86: =SUM(N76:N85) -> 0 | O86: =SUM(O76:O85) -> 0 | P86: =SUM(P76:P85) -> 0 | Q86: =SUM(Q76:Q85) -> 0 | R86: =SUM(R76:R85) -> 0 | S86: =SUM(S76:S85) -> 0 | ... AC86: =SUM(AC76:AC85) -> 0 | AD86: =IF(SUM(AD76:AD85)=0,0,SUM(AD76:AD85)/COUNTIF(AD76:AD85,"<>0")) -> 0 | AE86: =IF(SUM(AE76:AE85)=0,0,SUM(AE76:AE85)/COUNTIF(AE76:AE85,"<>0")) -> 0 | AF86: =IF(SUM(AF76:AF85)=0,0,SUM(AF76:AF85)/COUNTIF(AF76:AF85,"<>0")) -> 0 | AG86: =IF(SUM(AG76:AG85)=0,0,SUM(AG76:AG85)/COUNTIF(AD76:AD85,"<>0")) -> 0
A87: Departamento | B87: Municipio | C87: Comunidad | D87: CAPS | E87: No. | F87: Nombre de la actividad | G87: Fecha | H87: Quien Convoca? | I87: Quorum | J87: Valor de la convocatoria | K87: % de asistencia de mujeres en las asambleas | L87: Cargos JD
L88: Presidente | N88: Secretario/a | P88: Tesorero/a | R88: Fiscal | T88: Vocal_1 | V88: Vocal_2 | X88: Vocal_3 | Z88: Vocal_4 | AB88: Vocal_5 | AD88: Total de miembros activos (en%) | AE88: Total de miembros activos (en nº) | AF88: Total de Mujeres que participan | AG88: % De participación de la mujer | AH88: NOTAS
L89: H | M89: M | N89: H | O89: M | P89: H | Q89: M | R89: H | S89: M | T89: H | U89: M | V89: H | W89: M | X89: H | Y89: M | Z89: H | AA89: M | AB89: H | AC89: M
A90: ='Listado CAPS'!A87 -> 0 | B90: ='Listado CAPS'!B87 -> 0 | C90: ='Listado CAPS'!C87 -> 0 | D90: ='Listado CAPS'!D9 -> G | E90: 1 | J90: =IF(H90<>"OTROS",1,0)*IF(I90=1,1,0) -> 0 | AD90: =IF(SUM(L90:AC90)=0,0,SUM(L90:AC90)/'Conformación JD'!$X$13) -> 0 | AE90: =SUM(L90:AC90) -> 0 | AF90: =+AC90+AA90+Y90+W90+U90+S90+Q90+O90+M90 -> 0 | AG90: =IF(AE90=0,0,AF90/AE90) -> 0
E91: 2 | J91: =IF(H91<>"OTROS",1,0)*IF(I91=1,1,0) -> 0 | AD91: =IF(SUM(L91:AC91)=0,0,SUM(L91:AC91)/'Conformación JD'!$X$13) -> 0 | AE91: =SUM(L91:AC91) -> 0 | AF91: =+AC91+AA91+Y91+W91+U91+S91+Q91+O91+M91 -> 0 | AG91: =IF(AE91=0,0,AF91/AE91) -> 0
E92: 3 | J92: =IF(H92<>"OTROS",1,0)*IF(I92=1,1,0) -> 0 | AD92: =IF(SUM(L92:AC92)=0,0,SUM(L92:AC92)/'Conformación JD'!$X$13) -> 0 | AE92: =SUM(L92:AC92) -> 0 | AF92: =+AC92+AA92+Y92+W92+U92+S92+Q92+O92+M92 -> 0 | AG92: =IF(AE92=0,0,AF92/AE92) -> 0
E93: 4 | J93: =IF(H93<>"OTROS",1,0)*IF(I93=1,1,0) -> 0 | AD93: =IF(SUM(L93:AC93)=0,0,SUM(L93:AC93)/'Conformación JD'!$X$13) -> 0 | AE93: =SUM(L93:AC93) -> 0 | AF93: =+AC93+AA93+Y93+W93+U93+S93+Q93+O93+M93 -> 0 | AG93: =IF(AE93=0,0,AF93/AE93) -> 0
E94: 5 | J94: =IF(H94<>"OTROS",1,0)*IF(I94=1,1,0) -> 0 | AD94: =IF(SUM(L94:AC94)=0,0,SUM(L94:AC94)/'Conformación JD'!$X$13) -> 0 | AE94: =SUM(L94:AC94) -> 0 | AF94: =+AC94+AA94+Y94+W94+U94+S94+Q94+O94+M94 -> 0 | AG94: =IF(AE94=0,0,AF94/AE94) -> 0
E95: 6 | J95: =IF(H95<>"OTROS",1,0)*IF(I95=1,1,0) -> 0 | AD95: =IF(SUM(L95:AC95)=0,0,SUM(L95:AC95)/'Conformación JD'!$X$13) -> 0 | AE95: =SUM(L95:AC95) -> 0 | AF95: =+AC95+AA95+Y95+W95+U95+S95+Q95+O95+M95 -> 0 | AG95: =IF(AE95=0,0,AF95/AE95) -> 0
E96: 7 | J96: =IF(H96<>"OTROS",1,0)*IF(I96=1,1,0) -> 0 | AD96: =IF(SUM(L96:AC96)=0,0,SUM(L96:AC96)/'Conformación JD'!$X$13) -> 0 | AE96: =SUM(L96:AC96) -> 0 | AF96: =+AC96+AA96+Y96+W96+U96+S96+Q96+O96+M96 -> 0 | AG96: =IF(AE96=0,0,AF96/AE96) -> 0
E97: 8 | J97: =IF(H97<>"OTROS",1,0)*IF(I97=1,1,0) -> 0 | AD97: =IF(SUM(L97:AC97)=0,0,SUM(L97:AC97)/'Conformación JD'!$X$13) -> 0 | AE97: =SUM(L97:AC97) -> 0 | AF97: =+AC97+AA97+Y97+W97+U97+S97+Q97+O97+M97 -> 0 | AG97: =IF(AE97=0,0,AF97/AE97) -> 0
E98: 9 | J98: =IF(H98<>"OTROS",1,0)*IF(I98=1,1,0) -> 0 | AD98: =IF(SUM(L98:AC98)=0,0,SUM(L98:AC98)/'Conformación JD'!$X$13) -> 0 | AE98: =SUM(L98:AC98) -> 0 | AF98: =+AC98+AA98+Y98+W98+U98+S98+Q98+O98+M98 -> 0 | AG98: =IF(AE98=0,0,AF98/AE98) -> 0
E99: 10 | J99: =IF(H99<>"OTROS",1,0)*IF(I99=1,1,0) -> 0 | AD99: =IF(SUM(L99:AC99)=0,0,SUM(L99:AC99)/'Conformación JD'!$X$13) -> 0 | AE99: =SUM(L99:AC99) -> 0 | AF99: =+AC99+AA99+Y99+W99+U99+S99+Q99+O99+M99 -> 0 | AG99: =IF(AE99=0,0,AF99/AE99) -> 0
E100: TOTAL | I100: =IF((COUNTIF(G90:G99,"<>"))<>0,SUM(I90:I99)/COUNTIF(G90:G99,"<>"),0) -> 0 | J100: =IF((COUNTIF(H90:H99,"<>"))<>0,SUM(J90:J99)/COUNTIF(H90:H99,"<>"),0) -> 0 | K100: =IF((COUNTIF(H90:H99,"<>"))<>0,SUM(K90:K99)/COUNTIF(H90:H99,"<>"),0) -> 0 | L100: =SUM(L90:L99) -> 0 | M100: =SUM(M90:M99) -> 0 | N100: =SUM(N90:N99) -> 0 | O100: =SUM(O90:O99) -> 0 | P100: =SUM(P90:P99) -> 0 | Q100: =SUM(Q90:Q99) -> 0 | R100: =SUM(R90:R99) -> 0 | S100: =SUM(S90:S99) -> 0 | ... AC100: =SUM(AC90:AC99) -> 0 | AD100: =IF(SUM(AD90:AD99)=0,0,SUM(AD90:AD99)/COUNTIF(AD90:AD99,"<>0")) -> 0 | AE100: =IF(SUM(AE90:AE99)=0,0,SUM(AE90:AE99)/COUNTIF(AE90:AE99,"<>0")) -> 0 | AF100: =IF(SUM(AF90:AF99)=0,0,SUM(AF90:AF99)/COUNTIF(AF90:AF99,"<>0")) -> 0 | AG100: =IF(SUM(AG90:AG99)=0,0,SUM(AG90:AG99)/COUNTIF(AD90:AD99,"<>0")) -> 0
...

Sheet C.Nivel de Servicio
C2: Volver a Tabla de contenidos | D2: C. NIVEL DE SERVICIO | V2: Ir a Resultados Finales
F3: Instrucciones: Rellene las columnas en blanco según cada caso de la lista desplegable, en caso de varias opciones ponga la principal. No modifique la columna "Valor total" por que es la que esta relacionada con la hoja de Resultado final. | T3: Criterios: SEGURA: Si cumple que la fuente de agua es mejorada; ubicada dentro de la vivienda, disponible todo el tiempo y libre de contaminación fecal o sea resultado bacteriológico negativo. BÁSICO: Si cumple que es de fuente mejorada y que el tiempo de acarreo es menor de 30 minutos. LIMITADO: Si cumple que es de fuente mejorada y que el tiempo de acarreo es mayor de 30 minutos. NO MEJORADA: Agua para consumo proveniente de una fuente de agua no mejorada. AGUA DE SUPERFICIE: Si el tipo de sistema se clasifica como; agua para consumo que procede directamente de un río, presa, lago, estanque, arroyo, canal o canal de riego. En el resultado final; la calificacion debería ser “1” si es agua segura; “0.5” si es básico; “0” si esta entre limitado y agua de superficie.
A5: Departamento | B5: Municipio | C5: Comunidad | D5: CAPS | E5: Tipo de sistema | F5: C1. Fuente | G5: C2. Ubicación | H5: C3. Tiempo de acarreo del agua | I5: C4. Disponibilidad | J5: C5. ¿Dotación cumple DHA y norma nacional? | K5: Percepción calidad: olor | L5: Percepción calidad: color | M5: Percepción calidad: sabor | N5: C7, En los ultimos 3 meses ¿analisis bacteriológico? | O5: C8. Calidad | P5: Otras pruebas: arsénico | Q5: Otras pruebas: hierro total | R5: Otras pruebas: turbidez | S5: Otras pruebas: Ph | T5: Valor Total | U5: Medios de Verificación Existe? | V5: Nombre del Medio de Verificación | X5: valor final
A6: ='Listado CAPS'!A3 -> Madriz | B6: ='Listado CAPS'!B3 -> Yalaguina | C6: ='Listado CAPS'!C3 -> Los Encuentros | D6: ='Listado CAPS'!D3 -> Los Encuentros | E6: ='Listado CAPS'!E3 -> MAG | F6: Mejorada | G6: Dentro de la vivienda | H6: Menos de 30 min. | I6: La mayor parte del tiempo tenemos agua | J6: No cumple | K6: Bueno | L6: Bueno | M6: Bueno | N6: Sí | O6: Negativo en E. coli | P6: Si cumple | Q6: Si cumple | R6: Si cumple | S6: Si cumple | T6: =IF(E6="SUPERFICIE",$X$10,IF(F6="No mejorada",$X$9,IF(H6="Más de 30 minutos",$X$8,IF(AND(G6="Dentro de la vivienda",I6="Todo el tiempo tenemos agua",O6="Negativo en E. coli"),$X$6,$X$7)))) -> BÁSICO | W6: Mejorada | X6: SEGURA | Y6: 1 | Z6: Criterios: SEGURA: Si cumple que la fuente de agua es mejorada; ubicada dentro de la vivienda, disponible todo el tiempo y libre de contaminación fecal o sea resultado bacteriológico negativo. BÁSICO: Si cumple que es de fuente mejorada y que el tiempo de acarreo es menor de 30 minutos. LIMITADO: Si cumple que es de fuente mejorada y que el tiempo de acarreo es mayor de 30 minutos. NO MEJORADA: Agua para consumo proveniente de una fuente de agua no mejorada. AGUA DE SUPERFICIE: Si el tipo de sistema se clasifica como; agua para consumo que procede directamente de un río, presa, lago, estanque, arroyo, canal o canal de riego. En el resultado final; la calificacion debería ser “1” si es agua segura; “0.5” si es básico; “0” si esta entre limitado y agua de superficie.
A7: ='Listado CAPS'!A4 -> 0 | B7: ='Listado CAPS'!B4 -> 0 | C7: ='Listado CAPS'!C4 -> 0 | D7: ='Listado CAPS'!D4 -> B | J7: Si cumple | T7: =IF(E7="SUPERFICIE",$X$10,IF(F7="No mejorada",$X$9,IF(H7="Más de 30 minutos",$X$8,IF(AND(G7="Dentro de la vivienda",I7="Todo el tiempo tenemos agua",O7="Negativo en E. coli"),$X$6,$X$7)))) -> BÁSICO | W7: No mejorada | X7: BÁSICO | Y7: 0.5
A8: ='Listado CAPS'!A5 -> 0 | B8: ='Listado CAPS'!B5 -> 0 | C8: ='Listado CAPS'!C5 -> 0 | D8: ='Listado CAPS'!D5 -> C | T8: =IF(E8="SUPERFICIE",$X$10,IF(F8="No mejorada",$X$9,IF(H8="Más de 30 minutos",$X$8,IF(AND(G8="Dentro de la vivienda",I8="Todo el tiempo tenemos agua",O8="Negativo en E. coli"),$X$6,$X$7)))) -> BÁSICO | W8: Dentro de la vivienda | X8: LIMITADO | Y8: 0
A9: ='Listado CAPS'!A6 -> 0 | B9: ='Listado CAPS'!B6 -> 0 | C9: ='Listado CAPS'!C6 -> 0 | D9: ='Listado CAPS'!D6 -> D | T9: =IF(E9="SUPERFICIE",$X$10,IF(F9="No mejorada",$X$9,IF(H9="Más de 30 minutos",$X$8,IF(AND(G9="Dentro de la vivienda",I9="Todo el tiempo tenemos agua",O9="Negativo en E. coli"),$X$6,$X$7)))) -> BÁSICO | W9: En el Patio de la vivienda | X9: NO MEJORADA | Y9: 0
A10: ='Listado CAPS'!A7 -> 0 | B10: ='Listado CAPS'!B7 -> 0 | C10: ='Listado CAPS'!C7 -> 0 | D10: ='Listado CAPS'!D7 -> E | T10: =IF(E10="SUPERFICIE",$X$10,IF(F10="No mejorada",$X$9,IF(H10="Más de 30 minutos",$X$8,IF(AND(G10="Dentro de la vivienda",I10="Todo el tiempo tenemos agua",O10="Negativo en E. coli"),$X$6,$X$7)))) -> BÁSICO | W10: Tubería de un vecino | X10: AGUA DE SUPERFICIE | Y10: 0
A11: ='Listado CAPS'!A8 -> 0 | B11: ='Listado CAPS'!B8 -> 0 | C11: ='Listado CAPS'!C8 -> 0 | D11: ='Listado CAPS'!D8 -> F | T11: =IF(E11="SUPERFICIE",$X$10,IF(F11="No mejorada",$X$9,IF(H11="Más de 30 minutos",$X$8,IF(AND(G11="Dentro de la vivienda",I11="Todo el tiempo tenemos agua",O11="Negativo en E. coli"),$X$6,$X$7)))) -> BÁSICO | W11: Puesto público
A12: ='Listado CAPS'!A9 -> 0 | B12: ='Listado CAPS'!B9 -> 0 | C12: ='Listado CAPS'!C9 -> 0 | D12: ='Listado CAPS'!D9 -> G | T12: =IF(E12="SUPERFICIE",$X$10,IF(F12="No mejorada",$X$9,IF(H12="Más de 30 minutos",$X$8,IF(AND(G12="Dentro de la vivienda",I12="Todo el tiempo tenemos agua",O12="Negativo en E. coli"),$X$6,$X$7)))) -> BÁSICO | W12: Menos de 30 min.
A13: ='Listado CAPS'!A10 -> 0 | B13: ='Listado CAPS'!B10 -> 0 | C13: ='Listado CAPS'!C10 -> 0 | D13: ='Listado CAPS'!D10 -> H | T13: =IF(E13="SUPERFICIE",$X$10,IF(F13="No mejorada",$X$9,IF(H13="Más de 30 minutos",$X$8,IF(AND(G13="Dentro de la vivienda",I13="Todo el tiempo tenemos agua",O13="Negativo en E. coli"),$X$6,$X$7)))) -> BÁSICO | W13: Más de 30 minutos
A14: ='Listado CAPS'!A11 -> 0 | B14: ='Listado CAPS'!B11 -> 0 | C14: ='Listado CAPS'!C11 -> 0 | D14: ='Listado CAPS'!D11 -> I | T14: =IF(E14="SUPERFICIE",$X$10,IF(F14="No mejorada",$X$9,IF(H14="Más de 30 minutos",$X$8,IF(AND(G14="Dentro de la vivienda",I14="Todo el tiempo tenemos agua",O14="Negativo en E. coli"),$X$6,$X$7)))) -> BÁSICO | W14: Todo el tiempo tenemos agua
A15: ='Listado CAPS'!A12 -> 0 | B15: ='Listado CAPS'!B12 -> 0 | C15: ='Listado CAPS'!C12 -> 0 | D15: ='Listado CAPS'!D12 -> J | T15: =IF(E15="SUPERFICIE",$X$10,IF(F15="No mejorada",$X$9,IF(H15="Más de 30 minutos",$X$8,IF(AND(G15="Dentro de la vivienda",I15="Todo el tiempo tenemos agua",O15="Negativo en E. coli"),$X$6,$X$7)))) -> BÁSICO | W15: La mayor parte del tiempo tenemos agua
A16: ='Listado CAPS'!A13 -> 0 | B16: ='Listado CAPS'!B13 -> 0 | C16: ='Listado CAPS'!C13 -> 0 | D16: ='Listado CAPS'!D13 -> K | T16: =IF(E16="SUPERFICIE",$X$10,IF(F16="No mejorada",$X$9,IF(H16="Más de 30 minutos",$X$8,IF(AND(G16="Dentro de la vivienda",I16="Todo el tiempo tenemos agua",O16="Negativo en E. coli"),$X$6,$X$7)))) -> BÁSICO | W16: Sólo a veces tenemos agua
A17: ='Listado CAPS'!A14 -> 0 | B17: ='Listado CAPS'!B14 -> 0 | C17: ='Listado CAPS'!C14 -> 0 | D17: ='Listado CAPS'!D14 -> L | T17: =IF(E17="SUPERFICIE",$X$10,IF(F17="No mejorada",$X$9,IF(H17="Más de 30 minutos",$X$8,IF(AND(G17="Dentro de la vivienda",I17="Todo el tiempo tenemos agua",O17="Negativo en E. coli"),$X$6,$X$7)))) -> BÁSICO | W17: Casi nunca tenemos agua
A18: ='Listado CAPS'!A15 -> 0 | B18: ='Listado CAPS'!B15 -> 0 | C18: ='Listado CAPS'!C15 -> 0 | D18: ='Listado CAPS'!D15 -> M | T18: =IF(E18="SUPERFICIE",$X$10,IF(F18="No mejorada",$X$9,IF(H18="Más de 30 minutos",$X$8,IF(AND(G18="Dentro de la vivienda",I18="Todo el tiempo tenemos agua",O18="Negativo en E. coli"),$X$6,$X$7)))) -> BÁSICO | W18: Negativo en E. coli
A19: ='Listado CAPS'!A16 -> 0 | B19: ='Listado CAPS'!B16 -> 0 | C19: ='Listado CAPS'!C16 -> 0 | D19: ='Listado CAPS'!D16 -> N | T19: =IF(E19="SUPERFICIE",$X$10,IF(F19="No mejorada",$X$9,IF(H19="Más de 30 minutos",$X$8,IF(AND(G19="Dentro de la vivienda",I19="Todo el tiempo tenemos agua",O19="Negativo en E. coli"),$X$6,$X$7)))) -> BÁSICO | W19: Positivo en E. coli
A20: ='Listado CAPS'!A17 -> 0 | B20: ='Listado CAPS'!B17 -> 0 | C20: ='Listado CAPS'!C17 -> 0 | D20: ='Listado CAPS'!D17 -> Ñ | T20: =IF(E20="SUPERFICIE",$X$10,IF(F20="No mejorada",$X$9,IF(H20="Más de 30 minutos",$X$8,IF(AND(G20="Dentro de la vivienda",I20="Todo el tiempo tenemos agua",O20="Negativo en E. coli"),$X$6,$X$7)))) -> BÁSICO | W20: Si cumple
A21: ='Listado CAPS'!A18 -> 0 | B21: ='Listado CAPS'!B18 -> 0 | C21: ='Listado CAPS'!C18 -> 0 | D21: ='Listado CAPS'!D18 -> O | T21: =IF(E21="SUPERFICIE",$X$10,IF(F21="No mejorada",$X$9,IF(H21="Más de 30 minutos",$X$8,IF(AND(G21="Dentro de la vivienda",I21="Todo el tiempo tenemos agua",O21="Negativo en E. coli"),$X$6,$X$7)))) -> BÁSICO | W21: No cumple
A22: ='Listado CAPS'!A19 -> 0 | B22: ='Listado CAPS'!B19 -> 0 | C22: ='Listado CAPS'!C19 -> 0 | D22: ='Listado CAPS'!D19 -> P | T22: =IF(E22="SUPERFICIE",$X$10,IF(F22="No mejorada",$X$9,IF(H22="Más de 30 minutos",$X$8,IF(AND(G22="Dentro de la vivienda",I22="Todo el tiempo tenemos agua",O22="Negativo en E. coli"),$X$6,$X$7)))) -> BÁSICO | W22: Bueno
... A25: ='Listado CAPS'!A22 -> 0 | B25: ='Listado CAPS'!B22 -> 0 | C25: ='Listado CAPS'!C22 -> 0 | D25: ='Listado CAPS'!D22 -> S | T25: =IF(E25="SUPERFICIE",$X$10,IF(F25="No mejorada",$X$9,IF(H25="Más de 30 minutos",$X$8,IF(AND(G25="Dentro de la vivienda",I25="Todo el tiempo tenemos agua",O25="Negativo en E. coli"),$X$6,$X$7)))) -> BÁSICO | W25: No
A26: ='Listado CAPS'!A23 -> 0 | B26: ='Listado CAPS'!B23 -> 0 | C26: ='Listado CAPS'!C23 -> 0 | D26: ='Listado CAPS'!D23 -> T | T26: =IF(E26="SUPERFICIE",$X$10,IF(F26="No mejorada",$X$9,IF(H26="Más de 30 minutos",$X$8,IF(AND(G26="Dentro de la vivienda",I26="Todo el tiempo tenemos agua",O26="Negativo en E. coli"),$X$6,$X$7)))) -> BÁSICO
A27: ='Listado CAPS'!A24 -> 0 | B27: ='Listado CAPS'!B24 -> 0 | C27: ='Listado CAPS'!C24 -> 0 | D27: ='Listado CAPS'!D24 -> U | T27: =IF(E27="SUPERFICIE",$X$10,IF(F27="No mejorada",$X$9,IF(H27="Más de 30 minutos",$X$8,IF(AND(G27="Dentro de la vivienda",I27="Todo el tiempo tenemos agua",O27="Negativo en E. coli"),$X$6,$X$7)))) -> BÁSICO
A28: ='Listado CAPS'!A25 -> 0 | B28: ='Listado CAPS'!B25 -> 0 | C28: ='Listado CAPS'!C25 -> 0 | D28: ='Listado CAPS'!D25 -> V | T28: =IF(E28="SUPERFICIE",$X$10,IF(F28="No mejorada",$X$9,IF(H28="Más de 30 minutos",$X$8,IF(AND(G28="Dentro de la vivienda",I28="Todo el tiempo tenemos agua",O28="Negativo en E. coli"),$X$6,$X$7)))) -> BÁSICO
A29: ='Listado CAPS'!A26 -> 0 | B29: ='Listado CAPS'!B26 -> 0 | C29: ='Listado CAPS'!C26 -> 0 | D29: ='Listado CAPS'!D26 -> W | T29: =IF(E29="SUPERFICIE",$X$10,IF(F29="No mejorada",$X$9,IF(H29="Más de 30 minutos",$X$8,IF(AND(G29="Dentro de la vivienda",I29="Todo el tiempo tenemos agua",O29="Negativo en E. coli"),$X$6,$X$7)))) -> BÁSICO
A30: ='Listado CAPS'!A27 -> 0 | B30: ='Listado CAPS'!B27 -> 0 | C30: ='Listado CAPS'!C27 -> 0 | D30: ='Listado CAPS'!D27 -> X | T30: =IF(E30="SUPERFICIE",$X$10,IF(F30="No mejorada",$X$9,IF(H30="Más de 30 minutos",$X$8,IF(AND(G30="Dentro de la vivienda",I30="Todo el tiempo tenemos agua",O30="Negativo en E. coli"),$X$6,$X$7)))) -> BÁSICO
A31: ='Listado CAPS'!A28 -> 0 | B31: ='Listado CAPS'!B28 -> 0 | C31: ='Listado CAPS'!C28 -> 0 | D31: ='Listado CAPS'!D28 -> Y | T31: =IF(E31="SUPERFICIE",$X$10,IF(F31="No mejorada",$X$9,IF(H31="Más de 30 minutos",$X$8,IF(AND(G31="Dentro de la vivienda",I31="Todo el tiempo tenemos agua",O31="Negativo en E. coli"),$X$6,$X$7)))) -> BÁSICO
BU123: 1- El Diamante.
BU124: 2- La Breiera
BU125: 3- Valle de Suni
BU126: 4- El Espino
BU127: 5- San Marcos
BU128: 6- Los Arados
BU129: 7- Lomas de Sacacli
BU130: 8- Sacacli
BU131: 9- Estación Cerro Grande
BU132: 10- Valerio
BU133: 11- Yupali
BU134: 12- Gracalcan
... BU148: 26- El Barro
W383: 1- El Diamante.
W384: 2- La Breiera
W385: 3- Valle de Suni
W386: 4- El Espino
W387: 5- San Marcos
W388: 6- Los Arados
W389: 7- Lomas de Sacacli
W390: 8- Sacacli
W391: 9- Estación Cerro Grande
W392: 10- Valerio
W393: 11- Yupali
W394: 12- Gracalcan
... W408: 26- El Barro

Sheet D.RecuperacióndeCostes
B1: Volver a Tabla de contenidos | D1: D RECUPERACIÓN DE COSTES | M1: Ir a Resultados Finales
C2: Instrucciones: Se pondrá un 1 si la respuesta es SI. | F2: Instrucciones: Rellene las columnas en blanco según cada caso de la lista desplegable. No modifique la columna "Valor total" por que es la que esta relacionada con la hoja de Resultado final. | J2: Criterios: excepto D2, D1 a D5 cuentan de manera independiente, cada una vale un 25% si es óptima
A3: Departamento | B3: Municipio | C3: Comunidad | D3: CAPS | E3: D1. Disponen de tarifa | F3: D2. Tipo de Tarifa | G3: D3. Cuenta de banco funcional | H3: D4. La cantidad de dinero que tienen ahorrada en su cuenta le permite pagar los costes de O&M del próximo trimestre? | I3: D5. Morosidad | J3: Valor Total | K3: Entrevistado por: | L3: Fecha de la Entrevista | M3: NOTAS
A5: ='Listado CAPS'!A3 -> Madriz | B5: ='Listado CAPS'!B3 -> Yalaguina | C5: ='Listado CAPS'!C3 -> Los Encuentros | D5: ='Listado CAPS'!D3 -> Los Encuentros | E5: 1 | F5: por consumo | G5: 1 | H5: 1 | I5: 6 a 15% | J5: =IF(I5="<5%",((E5+G5+H5+1)/4),((E5+G5+H5)/4)) -> 0.75 | O5: por consumo
A6: ='Listado CAPS'!A4 -> 0 | B6: ='Listado CAPS'!B4 -> 0 | C6: ='Listado CAPS'!C4 -> 0 | D6: ='Listado CAPS'!D4 -> B | J6: =IF(I6="<5%",((E6+G6+H6+1)/4),((E6+G6+H6)/4)) -> 0 | O6: costo promedio
A7: ='Listado CAPS'!A5 -> 0 | B7: ='Listado CAPS'!B5 -> 0 | C7: ='Listado CAPS'!C5 -> 0 | D7: ='Listado CAPS'!D5 -> C | J7: =IF(I7="<5%",((E7+G7+H7+1)/4),((E7+G7+H7)/4)) -> 0 | O7: tarfa fija
A8: ='Listado CAPS'!A6 -> 0 | B8: ='Listado CAPS'!B6 -> 0 | C8: ='Listado CAPS'!C6 -> 0 | D8: ='Listado CAPS'!D6 -> D | J8: =IF(I8="<5%",((E8+G8+H8+1)/4),((E8+G8+H8)/4)) -> 0 | O8: no pagan
A9: ='Listado CAPS'!A7 -> 0 | B9: ='Listado CAPS'!B7 -> 0 | C9: ='Listado CAPS'!C7 -> 0 | D9: ='Listado CAPS'!D7 -> E | J9: =IF(I9="<5%",((E9+G9+H9+1)/4),((E9+G9+H9)/4)) -> 0 | O9: sí
A10: ='Listado CAPS'!A8 -> 0 | B10: ='Listado CAPS'!B8 -> 0 | C10: ='Listado CAPS'!C8 -> 0 | D10: ='Listado CAPS'!D8 -> F | J10: =IF(I10="<5%",((E10+G10+H10+1)/4),((E10+G10+H10)/4)) -> 0 | O10: no
A11: ='Listado CAPS'!A9 -> 0 | B11: ='Listado CAPS'!B9 -> 0 | C11: ='Listado CAPS'!C9 -> 0 | D11: ='Listado CAPS'!D9 -> G | J11: =IF(I11="<5%",((E11+G11+H11+1)/4),((E11+G11+H11)/4)) -> 0 | O11: <5%
A12: ='Listado CAPS'!A10 -> 0 | B12: ='Listado CAPS'!B10 -> 0 | C12: ='Listado CAPS'!C10 -> 0 | D12: ='Listado CAPS'!D10 -> H | J12: =IF(I12="<5%",((E12+G12+H12+1)/4),((E12+G12+H12)/4)) -> 0 | O12: 6 a 15%
A13: ='Listado CAPS'!A11 -> 0 | B13: ='Listado CAPS'!B11 -> 0 | C13: ='Listado CAPS'!C11 -> 0 | D13: ='Listado CAPS'!D11 -> I | J13: =IF(I13="<5%",((E13+G13+H13+1)/4),((E13+G13+H13)/4)) -> 0 | O13: >15%
A14: ='Listado CAPS'!A12 -> 0 | B14: ='Listado CAPS'!B12 -> 0 | C14: ='Listado CAPS'!C12 -> 0 | D14: ='Listado CAPS'!D12 -> J | J14: =IF(I14="<5%",((E14+G14+H14+1)/4),((E14+G14+H14)/4)) -> 0
A15: ='Listado CAPS'!A13 -> 0 | B15: ='Listado CAPS'!B13 -> 0 | C15: ='Listado CAPS'!C13 -> 0 | D15: ='Listado CAPS'!D13 -> K | J15: =IF(I15="<5%",((E15+G15+H15+1)/4),((E15+G15+H15)/4)) -> 0
A16: ='Listado CAPS'!A14 -> 0 | B16: ='Listado CAPS'!B14 -> 0 | C16: ='Listado CAPS'!C14 -> 0 | D16: ='Listado CAPS'!D14 -> L | J16: =IF(I16="<5%",((E16+G16+H16+1)/4),((E16+G16+H16)/4)) -> 0
A17: ='Listado CAPS'!A15 -> 0 | B17: ='Listado CAPS'!B15 -> 0 | C17: ='Listado CAPS'!C15 -> 0 | D17: ='Listado CAPS'!D15 -> M | J17: =IF(I17="<5%",((E17+G17+H17+1)/4),((E17+G17+H17)/4)) -> 0
A18: ='Listado CAPS'!A16 -> 0 | B18: ='Listado CAPS'!B16 -> 0 | C18: ='Listado CAPS'!C16 -> 0 | D18: ='Listado CAPS'!D16 -> N | J18: =IF(I18="<5%",((E18+G18+H18+1)/4),((E18+G18+H18)/4)) -> 0
A19: ='Listado CAPS'!A17 -> 0 | B19: ='Listado CAPS'!B17 -> 0 | C19: ='Listado CAPS'!C17 -> 0 | D19: ='Listado CAPS'!D17 -> Ñ | J19: =IF(I19="<5%",((E19+G19+H19+1)/4),((E19+G19+H19)/4)) -> 0
A20: ='Listado CAPS'!A18 -> 0 | B20: ='Listado CAPS'!B18 -> 0 | C20: ='Listado CAPS'!C18 -> 0 | D20: ='Listado CAPS'!D18 -> O | J20: =IF(I20="<5%",((E20+G20+H20+1)/4),((E20+G20+H20)/4)) -> 0
A21: ='Listado CAPS'!A19 -> 0 | B21: ='Listado CAPS'!B19 -> 0 | C21: ='Listado CAPS'!C19 -> 0 | D21: ='Listado CAPS'!D19 -> P | J21: =IF(I21="<5%",((E21+G21+H21+1)/4),((E21+G21+H21)/4)) -> 0
A22: ='Listado CAPS'!A20 -> 0 | B22: ='Listado CAPS'!B20 -> 0 | C22: ='Listado CAPS'!C20 -> 0 | D22: ='Listado CAPS'!D20 -> Q | J22: =IF(I22="<5%",((E22+G22+H22+1)/4),((E22+G22+H22)/4)) -> 0
A23: ='Listado CAPS'!A21 -> 0 | B23: ='Listado CAPS'!B21 -> 0 | C23: ='Listado CAPS'!C21 -> 0 | D23: ='Listado CAPS'!D21 -> R | J23: =IF(I23="<5%",((E23+G23+H23+1)/4),((E23+G23+H23)/4)) -> 0
A24: ='Listado CAPS'!A22 -> 0 | B24: ='Listado CAPS'!B22 -> 0 | C24: ='Listado CAPS'!C22 -> 0 | D24: ='Listado CAPS'!D22 -> S | J24: =IF(I24="<5%",((E24+G24+H24+1)/4),((E24+G24+H24)/4)) -> 0
A25: ='Listado CAPS'!A23 -> 0 | B25: ='Listado CAPS'!B23 -> 0 | C25: ='Listado CAPS'!C23 -> 0 | D25: ='Listado CAPS'!D23 -> T | J25: =IF(I25="<5%",((E25+G25+H25+1)/4),((E25+G25+H25)/4)) -> 0
... A30: ='Listado CAPS'!A28 -> 0 | B30: ='Listado CAPS'!B28 -> 0 | C30: ='Listado CAPS'!C28 -> 0 | D30: ='Listado CAPS'!D28 -> Y | J30: =IF(I30="<5%",((E30+G30+H30+1)/4),((E30+G30+H30)/4)) -> 0

Sheet E.OperaciónyMantenimiento
B1: Volver a Tabla de contenidos | D1: E. OPERACIÓN Y MANTENIMIENTO | G1: Ir a Resultados Finales
C2: Instrucciones: Se pondrá un 1 si la respuesta es SI. | E2: Criterio: Se tienen que cumplir las 2 para que se cuente como positivo.
A3: Departamento | B3: Municipio | C3: Comunidad | D3: CAPS | E3: E1. El CAPS cuenta con un plan de mantenimiento | F3: E2. Realizan la mayoría de las acciones sustanciales definidas en los planes de O y M. | G3: Entrevistado por: | H3: Fecha de la Entrevista | I3: NOTAS
A5: ='Listado CAPS'!A3 -> Madriz | B5: ='Listado CAPS'!B3 -> Yalaguina | C5: ='Listado CAPS'!C3 -> Los Encuentros | D5: ='Listado CAPS'!D3 -> Los Encuentros | E5: 1 | F5: 1
A6: ='Listado CAPS'!A4 -> 0 | B6: ='Listado CAPS'!B4 -> 0 | C6: ='Listado CAPS'!C4 -> 0 | D6: ='Listado CAPS'!D4 -> B
A7: ='Listado CAPS'!A5 -> 0 | B7: ='Listado CAPS'!B5 -> 0 | C7: ='Listado CAPS'!C5 -> 0 | D7: ='Listado CAPS'!D5 -> C
A8: ='Listado CAPS'!A6 -> 0 | B8: ='Listado CAPS'!B6 -> 0 | C8: ='Listado CAPS'!C6 -> 0 | D8: ='Listado CAPS'!D6 -> D
A9: ='Listado CAPS'!A7 -> 0 | B9: ='Listado CAPS'!B7 -> 0 | C9: ='Listado CAPS'!C7 -> 0 | D9: ='Listado CAPS'!D7 -> E
A10: ='Listado CAPS'!A8 -> 0 | B10: ='Listado CAPS'!B8 -> 0 | C10: ='Listado CAPS'!C8 -> 0 | D10: ='Listado CAPS'!D8 -> F
A11: ='Listado CAPS'!A9 -> 0 | B11: ='Listado CAPS'!B9 -> 0 | C11: ='Listado CAPS'!C9 -> 0 | D11: ='Listado CAPS'!D9 -> G
A12: ='Listado CAPS'!A10 -> 0 | B12: ='Listado CAPS'!B10 -> 0 | C12: ='Listado CAPS'!C10 -> 0 | D12: ='Listado CAPS'!D10 -> H
A13: ='Listado CAPS'!A11 -> 0 | B13: ='Listado CAPS'!B11 -> 0 | C13: ='Listado CAPS'!C11 -> 0 | D13: ='Listado CAPS'!D11 -> I
A14: ='Listado CAPS'!A12 -> 0 | B14: ='Listado CAPS'!B12 -> 0 | C14: ='Listado CAPS'!C12 -> 0 | D14: ='Listado CAPS'!D12 -> J
A15: ='Listado CAPS'!A13 -> 0 | B15: ='Listado CAPS'!B13 -> 0 | C15: ='Listado CAPS'!C13 -> 0 | D15: ='Listado CAPS'!D13 -> K
A16: ='Listado CAPS'!A14 -> 0 | B16: ='Listado CAPS'!B14 -> 0 | C16: ='Listado CAPS'!C14 -> 0 | D16: ='Listado CAPS'!D14 -> L
A17: ='Listado CAPS'!A15 -> 0 | B17: ='Listado CAPS'!B15 -> 0 | C17: ='Listado CAPS'!C15 -> 0 | D17: ='Listado CAPS'!D15 -> M
... A30: ='Listado CAPS'!A28 -> 0 | B30: ='Listado CAPS'!B28 -> 0 | C30: ='Listado CAPS'!C28 -> 0 | D30: ='Listado CAPS'!D28 -> Y

Sheet F.Gestión de riesgos hídricos
C1: Volver a Tabla de contenidos | E1: F. GESTIÓN DE RIESGOS HÍDRICOS | O1: Ir a Resultados Finales
F2: Instrucciones: Marcar con un 1 aquellas actividades que el CAPS ha realizado en el periodo que se quiere evaluar | I2: Criterio: se valoran independientemente, cuantas más acciones más valor positivo tiene este criterio (cada acción vale 0,1 y se suman)
A3: Departamento | B3: Municipio | C3: Comunidad | D3: CAPS | E3: F.1.Campañas de promoción de la higiene con las familias | F3: F.2. Jornadas de limpieza comunitaria | G3: F.3. ¿El CAPS realiza y registra de manera mensual los aforos a la fuente de agua que les abastece? | H3: F.4. ¿El CAPS informa en asamblea de usuarios/as sobre la disponibilidad de agua en el sistema comunitario? | I3: F.5. ¿El CAPS elabora y aplica medidas para ajustar la distribución de agua de acuerdo a los resultados del balance de agua en el periodo? | J3: F.6. ¿cuenta con micromedición funcional, o en el caso de pozos o puestos públicos dispone de mecanismo que contribuye a la distribución racional del agua? | K3: F.7. ¿El CAPS tiene identificado el área de recarga de la fuente de abastecimiento de agua de la comunidad (mapa)? | L3: F.8. ¿El CAPS tiene caracterizada el área de recarga de la fuente de abastecimiento de agua de la comunidad (diagnóstico) ? | M3: F.9. ¿El CAPS ha elaborado un plan de accion para la protección y conservación del área de recarga de la fuente de agua que abastece al SAP? | N3: F.10. ¿Sehan implementado al menos el 70% de las acciones previstas en dicho plan? | O3: Entrevistado por: | P3: Fecha de la Entrevista | Q3: NOTAS
A5: ='Listado CAPS'!A3 -> Madriz | B5: ='Listado CAPS'!B3 -> Yalaguina | C5: ='Listado CAPS'!C3 -> Los Encuentros | D5: ='Listado CAPS'!D3 -> Los Encuentros | F5: 1 | H5: 1 | I5: 1 | J5: 1
A6: ='Listado CAPS'!A4 -> 0 | B6: ='Listado CAPS'!B4 -> 0 | C6: ='Listado CAPS'!C4 -> 0 | D6: ='Listado CAPS'!D4 -> B
A7: ='Listado CAPS'!A5 -> 0 | B7: ='Listado CAPS'!B5 -> 0 | C7: ='Listado CAPS'!C5 -> 0 | D7: ='Listado CAPS'!D5 -> C
A8: ='Listado CAPS'!A6 -> 0 | B8: ='Listado CAPS'!B6 -> 0 | C8: ='Listado CAPS'!C6 -> 0 | D8: ='Listado CAPS'!D6 -> D
A9: ='Listado CAPS'!A7 -> 0 | B9: ='Listado CAPS'!B7 -> 0 | C9: ='Listado CAPS'!C7 -> 0 | D9: ='Listado CAPS'!D7 -> E
A10: ='Listado CAPS'!A8 -> 0 | B10: ='Listado CAPS'!B8 -> 0 | C10: ='Listado CAPS'!C8 -> 0 | D10: ='Listado CAPS'!D8 -> F
A11: ='Listado CAPS'!A9 -> 0 | B11: ='Listado CAPS'!B9 -> 0 | C11: ='Listado CAPS'!C9 -> 0 | D11: ='Listado CAPS'!D9 -> G
A12: ='Listado CAPS'!A10 -> 0 | B12: ='Listado CAPS'!B10 -> 0 | C12: ='Listado CAPS'!C10 -> 0 | D12: ='Listado CAPS'!D10 -> H
A13: ='Listado CAPS'!A11 -> 0 | B13: ='Listado CAPS'!B11 -> 0 | C13: ='Listado CAPS'!C11 -> 0 | D13: ='Listado CAPS'!D11 -> I
A14: ='Listado CAPS'!A12 -> 0 | B14: ='Listado CAPS'!B12 -> 0 | C14: ='Listado CAPS'!C12 -> 0 | D14: ='Listado CAPS'!D12 -> J
A15: ='Listado CAPS'!A13 -> 0 | B15: ='Listado CAPS'!B13 -> 0 | C15: ='Listado CAPS'!C13 -> 0 | D15: ='Listado CAPS'!D13 -> K
A16: ='Listado CAPS'!A14 -> 0 | B16: ='Listado CAPS'!B14 -> 0 | C16: ='Listado CAPS'!C14 -> 0 | D16: ='Listado CAPS'!D14 -> L
A17: ='Listado CAPS'!A15 -> 0 | B17: ='Listado CAPS'!B15 -> 0 | C17: ='Listado CAPS'!C15 -> 0 | D17: ='Listado CAPS'!D15 -> M
... A30: ='Listado CAPS'!A28 -> 0 | B30: ='Listado CAPS'!B28 -> 0 | C30: ='Listado CAPS'!C28 -> 0 | D30: ='Listado CAPS'!D28 -> Y

Sheet G.Rendición de cuentas
B1: Volver a Tabla de contenidos | D1: G. RENDICIÓN DE CUENTAS | M1: Ir a Resultados Finales
E2: Instrucciones: Se pondrá un 1 si la respuesta es SI. | H2: Criterio: Las dos primeras acciones a cumplir, tienen un valor total de 50% a repartir en 25% cada una. El resto de las acciones tienen el otro 50% a repartir entre las 4, a razón de 12,5 % cada una.
A3: Departamento | B3: Municipio | C3: Comunidad | D3: CAPS | E3: G.1 ¿Informa a los usuarios de la situación económica del CAPS de acuerdo a lo establecido en su reglamento interno? | F3: G.2¿Hace una rendición de cuentas a la junta directiva del CAPS de manera mensual? | G3: G.3 ¿Está actualizado el libro de registros contables? | H3: G.4 ¿Está actualizado el libro de usuarios? | I3: G.5 ¿Está actualizado el libro de actas? | J3: G.6 ¿En la rendición de cuentas se informa del % de morosos? | K3: Entrevistado por: | M3: Fecha de la Entrevista | N3: NOTAS
A5: ='Listado CAPS'!A3 -> Madriz | B5: ='Listado CAPS'!B3 -> Yalaguina | C5: ='Listado CAPS'!C3 -> Los Encuentros | D5: ='Listado CAPS'!D3 -> Los Encuentros | E5: 1 | F5: 1 | G5: 1 | H5: 1 | I5: 1 | J5: 1
A6: ='Listado CAPS'!A4 -> 0 | B6: ='Listado CAPS'!B4 -> 0 | C6: ='Listado CAPS'!C4 -> 0 | D6: ='Listado CAPS'!D4 -> B
A7: ='Listado CAPS'!A5 -> 0 | B7: ='Listado CAPS'!B5 -> 0 | C7: ='Listado CAPS'!C5 -> 0 | D7: ='Listado CAPS'!D5 -> C
A8: ='Listado CAPS'!A6 -> 0 | B8: ='Listado CAPS'!B6 -> 0 | C8: ='Listado CAPS'!C6 -> 0 | D8: ='Listado CAPS'!D6 -> D
A9: ='Listado CAPS'!A7 -> 0 | B9: ='Listado CAPS'!B7 -> 0 | C9: ='Listado CAPS'!C7 -> 0 | D9: ='Listado CAPS'!D7 -> E
A10: ='Listado CAPS'!A8 -> 0 | B10: ='Listado CAPS'!B8 -> 0 | C10: ='Listado CAPS'!C8 -> 0 | D10: ='Listado CAPS'!D8 -> F
A11: ='Listado CAPS'!A9 -> 0 | B11: ='Listado CAPS'!B9 -> 0 | C11: ='Listado CAPS'!C9 -> 0 | D11: ='Listado CAPS'!D9 -> G
A12: ='Listado CAPS'!A10 -> 0 | B12: ='Listado CAPS'!B10 -> 0 | C12: ='Listado CAPS'!C10 -> 0 | D12: ='Listado CAPS'!D10 -> H
A13: ='Listado CAPS'!A11 -> 0 | B13: ='Listado CAPS'!B11 -> 0 | C13: ='Listado CAPS'!C11 -> 0 | D13: ='Listado CAPS'!D11 -> I
A14: ='Listado CAPS'!A12 -> 0 | B14: ='Listado CAPS'!B12 -> 0 | C14: ='Listado CAPS'!C12 -> 0 | D14: ='Listado CAPS'!D12 -> J
A15: ='Listado CAPS'!A13 -> 0 | B15: ='Listado CAPS'!B13 -> 0 | C15: ='Listado CAPS'!C13 -> 0 | D15: ='Listado CAPS'!D13 -> K
A16: ='Listado CAPS'!A14 -> 0 | B16: ='Listado CAPS'!B14 -> 0 | C16: ='Listado CAPS'!C14 -> 0 | D16: ='Listado CAPS'!D14 -> L
A17: ='Listado CAPS'!A15 -> 0 | B17: ='Listado CAPS'!B15 -> 0 | C17: ='Listado CAPS'!C15 -> 0 | D17: ='Listado CAPS'!D15 -> M
... A30: ='Listado CAPS'!A28 -> 0 | B30: ='Listado CAPS'!B28 -> 0 | C30: ='Listado CAPS'!C28 -> 0 | D30: ='Listado CAPS'!D28 -> Y

Sheet H.1.Estado_Conserv MABE
B1: Volver a Tabla de contenidos | D1: H1. ESTADO DE CONSERVACION DE LOS SISTEMAS MABE | W1: Ir a Resultados Finales
E2: Instrucciones: no rellenar sobre las celdas sombreadas, esa fila corresponde a un CAPS que tiene otro SAP. Escribir en las blancas. Rellenar con un 1 cuando la respuesta sea SÏ. | N2: Criterio: Estación de bombeo: al menos 3. Tanque de Almacenamiento: al menos 4. El resto al menos 1. En total: las H>3.
A3: Departamento | B3: Municipio | C3: Comunidad | D3: CAPS | E3: TIPO DE SISTEMA | F3: 1) Estación de Bombeo | K3: H1 | L3: 2) Tanque de Almacenamiento | R3: H2 | S3: 3) Clorinador | T3: H3 | U3: 4) Otros | V3: H4 | W3: Entrevistado por: | X3: Fecha de la Entrevista
F4: Tiene cerco de protección el predio del pozo | G4: No hay letrinas ubicadas a menos de 20 mts del pozo | H4: Las paredes y el techo de la caseta de bombeo están en buen estado | I4: La caseta tiene puerta cerrada con llave | J4: Está registrando el macromedidor | L4: El tanque, tiene cerca y está en buen estado | M4: El tanque de almacenamiento no tiene grietas | N4: El tanque de almacenamiento no tiene fugas | O4: El tanque de almacenamiento no rebosa | P4: Las válvulas del tanque están en buen estado | Q4: La tapa de inspección está en buen estado | S4: Está funcionando el sistema de cloración | U4: Durante el recorrido, no hay fugas visibles en el sistema
A5: ='Listado CAPS'!A3 -> Madriz | B5: ='Listado CAPS'!B3 -> Yalaguina | C5: ='Listado CAPS'!C3 -> Los Encuentros | D5: ='Listado CAPS'!D3 -> Los Encuentros | E5: ='Listado CAPS'!E3 -> MAG | F5: 1 | H5: 1 | I5: 1 | J5: 1 | K5: =+SUM(F5:J5) -> 4 | L5: 1 | M5: 1 | N5: 1 | O5: 1 | P5: 1 | Q5: 1 | R5: =+SUM(L5:Q5) -> 6 | T5: =+S5 -> 0 | V5: =+U5 -> 0
A6: ='Listado CAPS'!A4 -> 0 | B6: ='Listado CAPS'!B4 -> 0 | C6: ='Listado CAPS'!C4 -> 0 | D6: ='Listado CAPS'!D4 -> B | K6: =+SUM(F6:J6) -> 0 | R6: =+SUM(L6:Q6) -> 0 | T6: =+S6 -> 0 | V6: =+U6 -> 0
A7: ='Listado CAPS'!A5 -> 0 | B7: ='Listado CAPS'!B5 -> 0 | C7: ='Listado CAPS'!C5 -> 0 | D7: ='Listado CAPS'!D5 -> C | K7: =+SUM(F7:J7) -> 0 | R7: =+SUM(L7:Q7) -> 0 | T7: =+S7 -> 0 | V7: =+U7 -> 0
A8: ='Listado CAPS'!A6 -> 0 | B8: ='Listado CAPS'!B6 -> 0 | C8: ='Listado CAPS'!C6 -> 0 | D8: ='Listado CAPS'!D6 -> D | K8: =+SUM(F8:J8) -> 0 | R8: =+SUM(L8:Q8) -> 0 | T8: =+S8 -> 0 | V8: =+U8 -> 0
A9: ='Listado CAPS'!A7 -> 0 | B9: ='Listado CAPS'!B7 -> 0 | C9: ='Listado CAPS'!C7 -> 0 | D9: ='Listado CAPS'!D7 -> E | K9: =+SUM(F9:J9) -> 0 | R9: =+SUM(L9:Q9) -> 0 | T9: =+S9 -> 0 | V9: =+U9 -> 0
A10: ='Listado CAPS'!A8 -> 0 | B10: ='Listado CAPS'!B8 -> 0 | C10: ='Listado CAPS'!C8 -> 0 | D10: ='Listado CAPS'!D8 -> F | K10: =+SUM(F10:J10) -> 0 | R10: =+SUM(L10:Q10) -> 0 | T10: =+S10 -> 0 | V10: =+U10 -> 0
A11: ='Listado CAPS'!A9 -> 0 | B11: ='Listado CAPS'!B9 -> 0 | C11: ='Listado CAPS'!C9 -> 0 | D11: ='Listado CAPS'!D9 -> G | K11: =+SUM(F11:J11) -> 0 | R11: =+SUM(L11:Q11) -> 0 | T11: =+S11 -> 0 | V11: =+U11 -> 0
A12: ='Listado CAPS'!A10 -> 0 | B12: ='Listado CAPS'!B10 -> 0 | C12: ='Listado CAPS'!C10 -> 0 | D12: ='Listado CAPS'!D10 -> H | K12: =+SUM(F12:J12) -> 0 | R12: =+SUM(L12:Q12) -> 0 | T12: =+S12 -> 0 | V12: =+U12 -> 0
A13: ='Listado CAPS'!A11 -> 0 | B13: ='Listado CAPS'!B11 -> 0 | C13: ='Listado CAPS'!C11 -> 0 | D13: ='Listado CAPS'!D11 -> I | K13: =+SUM(F13:J13) -> 0 | R13: =+SUM(L13:Q13) -> 0 | T13: =+S13 -> 0 | V13: =+U13 -> 0
A14: ='Listado CAPS'!A12 -> 0 | B14: ='Listado CAPS'!B12 -> 0 | C14: ='Listado CAPS'!C12 -> 0 | D14: ='Listado CAPS'!D12 -> J | K14: =+SUM(F14:J14) -> 0 | R14: =+SUM(L14:Q14) -> 0 | T14: =+S14 -> 0 | V14: =+U14 -> 0
A15: ='Listado CAPS'!A13 -> 0 | B15: ='Listado CAPS'!B13 -> 0 | C15: ='Listado CAPS'!C13 -> 0 | D15: ='Listado CAPS'!D13 -> K | K15: =+SUM(F15:J15) -> 0 | R15: =+SUM(L15:Q15) -> 0 | T15: =+S15 -> 0 | V15: =+U15 -> 0
A16: ='Listado CAPS'!A14 -> 0 | B16: ='Listado CAPS'!B14 -> 0 | C16: ='Listado CAPS'!C14 -> 0 | D16: ='Listado CAPS'!D14 -> L | K16: =+SUM(F16:J16) -> 0 | R16: =+SUM(L16:Q16) -> 0 | T16: =+S16 -> 0 | V16: =+U16 -> 0
A17: ='Listado CAPS'!A15 -> 0 | B17: ='Listado CAPS'!B15 -> 0 | C17: ='Listado CAPS'!C15 -> 0 | D17: ='Listado CAPS'!D15 -> M | K17: =+SUM(F17:J17) -> 0 | R17: =+SUM(L17:Q17) -> 0 | T17: =+S17 -> 0 | V17: =+U17 -> 0
... A22: ='Listado CAPS'!A20 -> 0 | B22: ='Listado CAPS'!B20 -> 0 | C22: ='Listado CAPS'!C20 -> 0 | D22: ='Listado CAPS'!D20 -> Q | K22: =+SUM(F22:J22) -> 0 | R22: =+SUM(L22:Q22) -> 0 | T22: =+S22 -> 0 | V22: =+U22 -> 0
A23: ='Listado CAPS'!A21 -> 0 | B23: ='Listado CAPS'!B21 -> 0 | C23: ='Listado CAPS'!C21 -> 0 | D23: ='Listado CAPS'!D21 -> R | E23: ='Listado CAPS'!E21 -> 0 | K23: =+SUM(F23:J23) -> 0 | R23: =+SUM(L23:Q23) -> 0 | T23: =+S23 -> 0 | V23: =+U23 -> 0
A24: ='Listado CAPS'!A22 -> 0 | B24: ='Listado CAPS'!B22 -> 0 | C24: ='Listado CAPS'!C22 -> 0 | D24: ='Listado CAPS'!D22 -> S | E24: ='Listado CAPS'!E22 -> 0 | K24: =+SUM(F24:J24) -> 0 | R24: =+SUM(L24:Q24) -> 0 | T24: =+S24 -> 0 | V24: =+U24 -> 0
A25: ='Listado CAPS'!A23 -> 0 | B25: ='Listado CAPS'!B23 -> 0 | C25: ='Listado CAPS'!C23 -> 0 | D25: ='Listado CAPS'!D23 -> T | E25: ='Listado CAPS'!E23 -> 0 | K25: =+SUM(F25:J25) -> 0 | R25: =+SUM(L25:Q25) -> 0 | T25: =+S25 -> 0 | V25: =+U25 -> 0
A26: ='Listado CAPS'!A24 -> 0 | B26: ='Listado CAPS'!B24 -> 0 | C26: ='Listado CAPS'!C24 -> 0 | D26: ='Listado CAPS'!D24 -> U | E26: ='Listado CAPS'!E24 -> 0 | K26: =+SUM(F26:J26) -> 0 | R26: =+SUM(L26:Q26) -> 0 | T26: =+S26 -> 0 | V26: =+U26 -> 0
A27: ='Listado CAPS'!A25 -> 0 | B27: ='Listado CAPS'!B25 -> 0 | C27: ='Listado CAPS'!C25 -> 0 | D27: ='Listado CAPS'!D25 -> V | E27: ='Listado CAPS'!E25 -> 0 | K27: =+SUM(F27:J27) -> 0 | R27: =+SUM(L27:Q27) -> 0 | T27: =+S27 -> 0 | V27: =+U27 -> 0
A28: ='Listado CAPS'!A26 -> 0 | B28: ='Listado CAPS'!B26 -> 0 | C28: ='Listado CAPS'!C26 -> 0 | D28: ='Listado CAPS'!D26 -> W | E28: ='Listado CAPS'!E26 -> 0 | K28: =+SUM(F28:J28) -> 0 | R28: =+SUM(L28:Q28) -> 0 | T28: =+S28 -> 0 | V28: =+U28 -> 0
A29: ='Listado CAPS'!A27 -> 0 | B29: ='Listado CAPS'!B27 -> 0 | C29: ='Listado CAPS'!C27 -> 0 | D29: ='Listado CAPS'!D27 -> X | E29: ='Listado CAPS'!E27 -> 0 | K29: =+SUM(F29:J29) -> 0 | R29: =+SUM(L29:Q29) -> 0 | T29: =+S29 -> 0 | V29: =+U29 -> 0
A30: ='Listado CAPS'!A28 -> 0 | B30: ='Listado CAPS'!B28 -> 0 | C30: ='Listado CAPS'!C28 -> 0 | D30: ='Listado CAPS'!D28 -> Y | E30: ='Listado CAPS'!E28 -> 0 | K30: =+SUM(F30:J30) -> 0 | R30: =+SUM(L30:Q30) -> 0 | T30: =+S30 -> 0 | V30: =+U30 -> 0

Sheet H.2.Estado_Conserv.MAG
B1: Volver a Tabla de contenidos | D1: H2. ESTADO DE CONSERVACION DE LOS SISTEMAS MAG | V1: Ir a Resultados Finales
J2: Instrucciones: complete con un 1 si es SÍ. | P2: Criterio: Captación: al menos 2. Tanque de Almacenamiento: al menos 4. El resto al menos 1. Luego en conjunto cada H tiene un valor de 0,25.
A3: Departamento | B3: Municipio | C3: Comunidad | D3: CAPS | E3: Tipo de sistema | F3: Características | G3: 1) Captación | J3: H1 | K3: 2)Tanque de almacenamiento | Q3: H2 | R3: 3) Clorinador | S3: H3 | T3: 4) Otros | U3: H4 | V3: 5) Puestos Publicos (solo si NO hay toma domiciliar) | AB3: H5 | AC3: Val
G4: La cerca de la obra de captación está en buen estado | H4: No se observan focos de contaminación (restos de envases de pesticidas, basura, heces…) alrededor de la fuente de agua | I4: No tiene grietas la obra de captación | K4: La cerca del tanque de almacenamiento está en buen estado | L4: No tiene grietas el tanque de almacenamiento | M4: No tiene fugas el tanque de almacenamiento | N4: El tanque no rebosa | O4: Las válvulas del tanque están en buen estado | P4: La tapa de inspección está en buen estado | R4: Está funcionando el sistema de cloración | T4: Durante el recorrido, no hay fugas visibles en el sistema | V4: El canal de desague no tiene grietas | W4: El tubo de concreto esta en buen estado | X4: El pedestal de apoyo esta en buen estado | Y4: La caja recolectora de agua esta en buen estado | Z4: Las llaves de abastecimiento estan en buen estado | AA4: La losa o falda no tiene grietas
A5: ='Listado CAPS'!A3 -> Madriz | B5: ='Listado CAPS'!B3 -> Yalaguina | C5: ='Listado CAPS'!C3 -> Los Encuentros | D5: ='Listado CAPS'!D3 -> Los Encuentros | E5: ='Listado CAPS'!E3 -> MAG | J5: =IF(SUM(G5:I5)>=2,1,0) -> 0 | Q5: =IF(SUM(K5:P5)>=4,1,0) -> 0 | S5: =+R5 -> 0 | U5: =+T5 -> 0 | AB5: =IF(SUM(V5:AA5)>=4,1,0) -> 0 | AC5: =IF(F5="PUESTOS PUBLICOS",SUM(J5*0.2+Q5*0.2+S5*0.2+U5*0.2+AB5*0.2),SUM(J5*0.25+Q5*0.25+S5*0.25+U5*0.25)) -> 0
A6: ='Listado CAPS'!A4 -> 0 | B6: ='Listado CAPS'!B4 -> 0 | C6: ='Listado CAPS'!C4 -> 0 | D6: ='Listado CAPS'!D4 -> B | J6: =IF(SUM(G6:I6)>=2,1,0) -> 0 | Q6: =IF(SUM(K6:P6)>=4,1,0) -> 0 | S6: =+R6 -> 0 | U6: =+T6 -> 0 | AB6: =IF(SUM(V6:AA6)>=4,1,0) -> 0 | AC6: =IF(F6="PUESTOS PUBLICOS",SUM(J6*0.2+Q6*0.2+S6*0.2+U6*0.2+AB6*0.2),SUM(J6*0.25+Q6*0.25+S6*0.25+U6*0.25)) -> 0
A7: ='Listado CAPS'!A5 -> 0 | B7: ='Listado CAPS'!B5 -> 0 | C7: ='Listado CAPS'!C5 -> 0 | D7: ='Listado CAPS'!D5 -> C | J7: =IF(SUM(G7:I7)>=2,1,0) -> 0 | Q7: =IF(SUM(K7:P7)>=4,1,0) -> 0 | S7: =+R7 -> 0 | U7: =+T7 -> 0 | AB7: =IF(SUM(V7:AA7)>=4,1,0) -> 0 | AC7: =IF(F7="PUESTOS PUBLICOS",SUM(J7*0.2+Q7*0.2+S7*0.2+U7*0.2+AB7*0.2),SUM(J7*0.25+Q7*0.25+S7*0.25+U7*0.25)) -> 0
A8: ='Listado CAPS'!A6 -> 0 | B8: ='Listado CAPS'!B6 -> 0 | C8: ='Listado CAPS'!C6 -> 0 | D8: ='Listado CAPS'!D6 -> D | J8: =IF(SUM(G8:I8)>=2,1,0) -> 0 | Q8: =IF(SUM(K8:P8)>=4,1,0) -> 0 | S8: =+R8 -> 0 | U8: =+T8 -> 0 | AB8: =IF(SUM(V8:AA8)>=4,1,0) -> 0 | AC8: =IF(F8="PUESTOS PUBLICOS",SUM(J8*0.2+Q8*0.2+S8*0.2+U8*0.2+AB8*0.2),SUM(J8*0.25+Q8*0.25+S8*0.25+U8*0.25)) -> 0
A9: ='Listado CAPS'!A7 -> 0 | B9: ='Listado CAPS'!B7 -> 0 | C9: ='Listado CAPS'!C7 -> 0 | D9: ='Listado CAPS'!D7 -> E | J9: =IF(SUM(G9:I9)>=2,1,0) -> 0 | Q9: =IF(SUM(K9:P9)>=4,1,0) -> 0 | S9: =+R9 -> 0 | U9: =+T9 -> 0 | AB9: =IF(SUM(V9:AA9)>=4,1,0) -> 0 | AC9: =IF(F9="PUESTOS PUBLICOS",SUM(J9*0.2+Q9*0.2+S9*0.2+U9*0.2+AB9*0.2),SUM(J9*0.25+Q9*0.25+S9*0.25+U9*0.25)) -> 0
A10: ='Listado CAPS'!A8 -> 0 | B10: ='Listado CAPS'!B8 -> 0 | C10: ='Listado CAPS'!C8 -> 0 | D10: ='Listado CAPS'!D8 -> F | J10: =IF(SUM(G10:I10)>=2,1,0) -> 0 | Q10: =IF(SUM(K10:P10)>=4,1,0) -> 0 | S10: =+R10 -> 0 | U10: =+T10 -> 0 | AB10: =IF(SUM(V10:AA10)>=4,1,0) -> 0 | AC10: =IF(F10="PUESTOS PUBLICOS",SUM(J10*0.2+Q10*0.2+S10*0.2+U10*0.2+AB10*0.2),SUM(J10*0.25+Q10*0.25+S10*0.25+U10*0.25)) -> 0
A11: ='Listado CAPS'!A9 -> 0 | B11: ='Listado CAPS'!B9 -> 0 | C11: ='Listado CAPS'!C9 -> 0 | D11: ='Listado CAPS'!D9 -> G | J11: =IF(SUM(G11:I11)>=2,1,0) -> 0 | Q11: =IF(SUM(K11:P11)>=4,1,0) -> 0 | S11: =+R11 -> 0 | U11: =+T11 -> 0 | AB11: =IF(SUM(V11:AA11)>=4,1,0) -> 0 | AC11: =IF(F11="PUESTOS PUBLICOS",SUM(J11*0.2+Q11*0.2+S11*0.2+U11*0.2+AB11*0.2),SUM(J11*0.25+Q11*0.25+S11*0.25+U11*0.25)) -> 0
A12: ='Listado CAPS'!A10 -> 0 | B12: ='Listado CAPS'!B10 -> 0 | C12: ='Listado CAPS'!C10 -> 0 | D12: ='Listado CAPS'!D10 -> H | J12: =IF(SUM(G12:I12)>=2,1,0) -> 0 | Q12: =IF(SUM(K12:P12)>=4,1,0) -> 0 | S12: =+R12 -> 0 | U12: =+T12 -> 0 | AB12: =IF(SUM(V12:AA12)>=4,1,0) -> 0 | AC12: =IF(F12="PUESTOS PUBLICOS",SUM(J12*0.2+Q12*0.2+S12*0.2+U12*0.2+AB12*0.2),SUM(J12*0.25+Q12*0.25+S12*0.25+U12*0.25)) -> 0
A13: ='Listado CAPS'!A11 -> 0 | B13: ='Listado CAPS'!B11 -> 0 | C13: ='Listado CAPS'!C11 -> 0 | D13: ='Listado CAPS'!D11 -> I | J13: =IF(SUM(G13:I13)>=2,1,0) -> 0 | Q13: =IF(SUM(K13:P13)>=4,1,0) -> 0 | S13: =+R13 -> 0 | U13: =+T13 -> 0 | AB13: =IF(SUM(V13:AA13)>=4,1,0) -> 0 | AC13: =IF(F13="PUESTOS PUBLICOS",SUM(J13*0.2+Q13*0.2+S13*0.2+U13*0.2+AB13*0.2),SUM(J13*0.25+Q13*0.25+S13*0.25+U13*0.25)) -> 0
A14: ='Listado CAPS'!A12 -> 0 | B14: ='Listado CAPS'!B12 -> 0 | C14: ='Listado CAPS'!C12 -> 0 | D14: ='Listado CAPS'!D12 -> J | J14: =IF(SUM(G14:I14)>=2,1,0) -> 0 | Q14: =IF(SUM(K14:P14)>=4,1,0) -> 0 | S14: =+R14 -> 0 | U14: =+T14 -> 0 | AB14: =IF(SUM(V14:AA14)>=4,1,0) -> 0 | AC14: =IF(F14="PUESTOS PUBLICOS",SUM(J14*0.2+Q14*0.2+S14*0.2+U14*0.2+AB14*0.2),SUM(J14*0.25+Q14*0.25+S14*0.25+U14*0.25)) -> 0
A15: ='Listado CAPS'!A13 -> 0 | B15: ='Listado CAPS'!B13 -> 0 | C15: ='Listado CAPS'!C13 -> 0 | D15: ='Listado CAPS'!D13 -> K | J15: =IF(SUM(G15:I15)>=2,1,0) -> 0 | Q15: =IF(SUM(K15:P15)>=4,1,0) -> 0 | S15: =+R15 -> 0 | U15: =+T15 -> 0 | AB15: =IF(SUM(V15:AA15)>=4,1,0) -> 0 | AC15: =IF(F15="PUESTOS PUBLICOS",SUM(J15*0.2+Q15*0.2+S15*0.2+U15*0.2+AB15*0.2),SUM(J15*0.25+Q15*0.25+S15*0.25+U15*0.25)) -> 0
A16: ='Listado CAPS'!A14 -> 0 | B16: ='Listado CAPS'!B14 -> 0 | C16: ='Listado CAPS'!C14 -> 0 | D16: ='Listado CAPS'!D14 -> L | J16: =IF(SUM(G16:I16)>=2,1,0) -> 0 | Q16: =IF(SUM(K16:P16)>=4,1,0) -> 0 | S16: =+R16 -> 0 | U16: =+T16 -> 0 | AB16: =IF(SUM(V16:AA16)>=4,1,0) -> 0 | AC16: =IF(F16="PUESTOS PUBLICOS",SUM(J16*0.2+Q16*0.2+S16*0.2+U16*0.2+AB16*0.2),SUM(J16*0.25+Q16*0.25+S16*0.25+U16*0.25)) -> 0
A17: ='Listado CAPS'!A15 -> 0 | B17: ='Listado CAPS'!B15 -> 0 | C17: ='Listado CAPS'!C15 -> 0 | D17: ='Listado CAPS'!D15 -> M | J17: =IF(SUM(G17:I17)>=2,1,0) -> 0 | Q17: =IF(SUM(K17:P17)>=4,1,0) -> 0 | S17: =+R17 -> 0 | U17: =+T17 -> 0 | AB17: =IF(SUM(V17:AA17)>=4,1,0) -> 0 | AC17: =IF(F17="PUESTOS PUBLICOS",SUM(J17*0.2+Q17*0.2+S17*0.2+U17*0.2+AB17*0.2),SUM(J17*0.25+Q17*0.25+S17*0.25+U17*0.25)) -> 0
... A22: ='Listado CAPS'!A20 -> 0 | B22: ='Listado CAPS'!B20 -> 0 | C22: ='Listado CAPS'!C20 -> 0 | D22: ='Listado CAPS'!D20 -> Q | J22: =IF(SUM(G22:I22)>=2,1,0) -> 0 | Q22: =IF(SUM(K22:P22)>=4,1,0) -> 0 | S22: =+R22 -> 0 | U22: =+T22 -> 0 | AB22: =IF(SUM(V22:AA22)>=4,1,0) -> 0 | AC22: =IF(F22="PUESTOS PUBLICOS",SUM(J22*0.2+Q22*0.2+S22*0.2+U22*0.2+AB22*0.2),SUM(J22*0.25+Q22*0.25+S22*0.25+U22*0.25)) -> 0
A23: ='Listado CAPS'!A21 -> 0 | B23: ='Listado CAPS'!B21 -> 0 | C23: ='Listado CAPS'!C21 -> 0 | D23: ='Listado CAPS'!D21 -> R | E23: ='Listado CAPS'!E21 -> 0 | J23: =IF(SUM(G23:I23)>=2,1,0) -> 0 | Q23: =IF(SUM(K23:P23)>=4,1,0) -> 0 | S23: =+R23 -> 0 | U23: =+T23 -> 0 | AB23: =IF(SUM(V23:AA23)>=4,1,0) -> 0 | AC23: =IF(F23="PUESTOS PUBLICOS",SUM(J23*0.2+Q23*0.2+S23*0.2+U23*0.2+AB23*0.2),SUM(J23*0.25+Q23*0.25+S23*0.25+U23*0.25)) -> 0
A24: ='Listado CAPS'!A22 -> 0 | B24: ='Listado CAPS'!B22 -> 0 | C24: ='Listado CAPS'!C22 -> 0 | D24: ='Listado CAPS'!D22 -> S | E24: ='Listado CAPS'!E22 -> 0 | J24: =IF(SUM(G24:I24)>=2,1,0) -> 0 | Q24: =IF(SUM(K24:P24)>=4,1,0) -> 0 | S24: =+R24 -> 0 | U24: =+T24 -> 0 | AB24: =IF(SUM(V24:AA24)>=4,1,0) -> 0 | AC24: =IF(F24="PUESTOS PUBLICOS",SUM(J24*0.2+Q24*0.2+S24*0.2+U24*0.2+AB24*0.2),SUM(J24*0.25+Q24*0.25+S24*0.25+U24*0.25)) -> 0
A25: ='Listado CAPS'!A23 -> 0 | B25: ='Listado CAPS'!B23 -> 0 | C25: ='Listado CAPS'!C23 -> 0 | D25: ='Listado CAPS'!D23 -> T | E25: ='Listado CAPS'!E23 -> 0 | J25: =IF(SUM(G25:I25)>=2,1,0) -> 0 | Q25: =IF(SUM(K25:P25)>=4,1,0) -> 0 | S25: =+R25 -> 0 | U25: =+T25 -> 0 | AB25: =IF(SUM(V25:AA25)>=4,1,0) -> 0 | AC25: =IF(F25="PUESTOS PUBLICOS",SUM(J25*0.2+Q25*0.2+S25*0.2+U25*0.2+AB25*0.2),SUM(J25*0.25+Q25*0.25+S25*0.25+U25*0.25)) -> 0
A26: ='Listado CAPS'!A24 -> 0 | B26: ='Listado CAPS'!B24 -> 0 | C26: ='Listado CAPS'!C24 -> 0 | D26: ='Listado CAPS'!D24 -> U | E26: ='Listado CAPS'!E24 -> 0 | J26: =IF(SUM(G26:I26)>=2,1,0) -> 0 | Q26: =IF(SUM(K26:P26)>=4,1,0) -> 0 | S26: =+R26 -> 0 | U26: =+T26 -> 0 | AB26: =IF(SUM(V26:AA26)>=4,1,0) -> 0 | AC26: =IF(F26="PUESTOS PUBLICOS",SUM(J26*0.2+Q26*0.2+S26*0.2+U26*0.2+AB26*0.2),SUM(J26*0.25+Q26*0.25+S26*0.25+U26*0.25)) -> 0
A27: ='Listado CAPS'!A25 -> 0 | B27: ='Listado CAPS'!B25 -> 0 | C27: ='Listado CAPS'!C25 -> 0 | D27: ='Listado CAPS'!D25 -> V | E27: ='Listado CAPS'!E25 -> 0 | J27: =IF(SUM(G27:I27)>=2,1,0) -> 0 | Q27: =IF(SUM(K27:P27)>=4,1,0) -> 0 | S27: =+R27 -> 0 | U27: =+T27 -> 0 | AB27: =IF(SUM(V27:AA27)>=4,1,0) -> 0 | AC27: =IF(F27="PUESTOS PUBLICOS",SUM(J27*0.2+Q27*0.2+S27*0.2+U27*0.2+AB27*0.2),SUM(J27*0.25+Q27*0.25+S27*0.25+U27*0.25)) -> 0
A28: ='Listado CAPS'!A26 -> 0 | B28: ='Listado CAPS'!B26 -> 0 | C28: ='Listado CAPS'!C26 -> 0 | D28: ='Listado CAPS'!D26 -> W | E28: ='Listado CAPS'!E26 -> 0 | J28: =IF(SUM(G28:I28)>=2,1,0) -> 0 | Q28: =IF(SUM(K28:P28)>=4,1,0) -> 0 | S28: =+R28 -> 0 | U28: =+T28 -> 0 | AB28: =IF(SUM(V28:AA28)>=4,1,0) -> 0 | AC28: =IF(F28="PUESTOS PUBLICOS",SUM(J28*0.2+Q28*0.2+S28*0.2+U28*0.2+AB28*0.2),SUM(J28*0.25+Q28*0.25+S28*0.25+U28*0.25)) -> 0
A29: ='Listado CAPS'!A27 -> 0 | B29: ='Listado CAPS'!B27 -> 0 | C29: ='Listado CAPS'!C27 -> 0 | D29: ='Listado CAPS'!D27 -> X | E29: ='Listado CAPS'!E27 -> 0 | J29: =IF(SUM(G29:I29)>=2,1,0) -> 0 | Q29: =IF(SUM(K29:P29)>=4,1,0) -> 0 | S29: =+R29 -> 0 | U29: =+T29 -> 0 | AB29: =IF(SUM(V29:AA29)>=4,1,0) -> 0 | AC29: =IF(F29="PUESTOS PUBLICOS",SUM(J29*0.2+Q29*0.2+S29*0.2+U29*0.2+AB29*0.2),SUM(J29*0.25+Q29*0.25+S29*0.25+U29*0.25)) -> 0
A30: ='Listado CAPS'!A28 -> 0 | B30: ='Listado CAPS'!B28 -> 0 | C30: ='Listado CAPS'!C28 -> 0 | D30: ='Listado CAPS'!D28 -> Y | E30: ='Listado CAPS'!E28 -> 0 | J30: =IF(SUM(G30:I30)>=2,1,0) -> 0 | Q30: =IF(SUM(K30:P30)>=4,1,0) -> 0 | S30: =+R30 -> 0 | U30: =+T30 -> 0 | AB30: =IF(SUM(V30:AA30)>=4,1,0) -> 0 | AC30: =IF(F30="PUESTOS PUBLICOS",SUM(J30*0.2+Q30*0.2+S30*0.2+U30*0.2+AB30*0.2),SUM(J30*0.25+Q30*0.25+S30*0.25+U30*0.25)) -> 0

Sheet H.3.Estado_Conserv.Pozos
B1: Volver a Tabla de contenidos | D1: H3. ESTADO DE CONSERVACION DE LOS POZOS PERFORADOS Y ESCAVADOS EQUIPADOS CON BOMBA MANUAL | V1: Ir a Resultados Finales
I2: Instrucciones: complete con un 1 si es SÍ. La loza del Brocal se completa sólo en el caso de pozos excavados.
A3: Departamento | B3: Municipio | C3: Comunidad | D3: CAPS | E3: Tipo de Sistema | F3: Características | G3: Pozo | I3: H1 | J3: Bomba manual | O3: H2 | P3: Delantal | R3: H3 | S3: Canal de Drenaje | U3: H4 | V3: Resumidero | X3: H5 | Y3: Loza del Brocal (Solo en Excavados) | AA3: H6 | AB3: Val
G4: Tiene cerco de protección el predio del pozo | H4: No hay letrinas ubicadas a menos de 20 mts del pozo | J4: El estado del mecate y los pistones están en buen estado | K4: La estructura metálica de la bomba está en buen estado | L4: Los cojinetes, la palanca, los ejes de la bomba están en buen estado | M4: La tubería de subida de la Bomba está en buen estado | N4: No hay grietas en la base de la bomba | P4: No hay fisuras o grietas en los bordillos del delantal | Q4: No hay fisuras o grietas en el delantal del pozo | S4: No hay elementos que obstruyan el canal | T4: No hay fisuras o grietas en el canal de drenaje | V4: El filtro de grava está en buen estado | W4: No tienen sedimentos acumulados en el fondo del filtro | Y4: No hay fisuras o grietas en la loza del brocal | Z4: No hay oxidación en la tapa metálica de visita
A5: ='Listado CAPS'!A3 -> Madriz | B5: ='Listado CAPS'!B3 -> Yalaguina | C5: ='Listado CAPS'!C3 -> Los Encuentros | D5: ='Listado CAPS'!D3 -> Los Encuentros | E5: ='Listado CAPS'!E3 -> MAG | I5: =IF(SUM(G5:H5)=2,1,0) -> 0 | O5: =IF(SUM(J5:N5)>=4,1,0) -> 0 | R5: =IF(SUM(P5:Q5)=2,1,0) -> 0 | U5: =IF(SUM(S5:T5)=1,1,0) -> 0 | X5: =IF(SUM(V5:W5)=2,1,0) -> 0 | AA5: =IF(SUM(Y5:Z5)=2,1,0) -> 0 | AB5: =IF(E6<>"EXCAVADO EBM",SUM(I5*0.2+O5*0.2+R5*0.2+U5*0.2+X5*0.2),SUM(I5*0.16+O5*0.16+R5*0.16+U5*0.16+X5*0.16+AA5*0.16)) -> 0
A6: ='Listado CAPS'!A4 -> 0 | B6: ='Listado CAPS'!B4 -> 0 | C6: ='Listado CAPS'!C4 -> 0 | D6: ='Listado CAPS'!D4 -> B | I6: =IF(SUM(G6:H6)=2,1,0) -> 0 | O6: =IF(SUM(J6:N6)>=4,1,0) -> 0 | R6: =IF(SUM(P6:Q6)=2,1,0) -> 0 | U6: =IF(SUM(S6:T6)=1,1,0) -> 0 | X6: =IF(SUM(V6:W6)=2,1,0) -> 0 | AA6: =IF(SUM(Y6:Z6)=2,1,0) -> 0 | AB6: =IF(E7<>"EXCAVADO EBM",SUM(I6*0.2+O6*0.2+R6*0.2+U6*0.2+X6*0.2),SUM(I6*0.16+O6*0.16+R6*0.16+U6*0.16+X6*0.16+AA6*0.16)) -> 0
A7: ='Listado CAPS'!A5 -> 0 | B7: ='Listado CAPS'!B5 -> 0 | C7: ='Listado CAPS'!C5 -> 0 | D7: ='Listado CAPS'!D5 -> C | I7: =IF(SUM(G7:H7)=2,1,0) -> 0 | O7: =IF(SUM(J7:N7)>=4,1,0) -> 0 | R7: =IF(SUM(P7:Q7)=2,1,0) -> 0 | U7: =IF(SUM(S7:T7)=1,1,0) -> 0 | X7: =IF(SUM(V7:W7)=2,1,0) -> 0 | AA7: =IF(SUM(Y7:Z7)=2,1,0) -> 0 | AB7: =IF(E8<>"EXCAVADO EBM",SUM(I7*0.2+O7*0.2+R7*0.2+U7*0.2+X7*0.2),SUM(I7*0.16+O7*0.16+R7*0.16+U7*0.16+X7*0.16+AA7*0.16)) -> 0
A8: ='Listado CAPS'!A6 -> 0 | B8: ='Listado CAPS'!B6 -> 0 | C8: ='Listado CAPS'!C6 -> 0 | D8: ='Listado CAPS'!D6 -> D | I8: =IF(SUM(G8:H8)=2,1,0) -> 0 | O8: =IF(SUM(J8:N8)>=4,1,0) -> 0 | R8: =IF(SUM(P8:Q8)=2,1,0) -> 0 | U8: =IF(SUM(S8:T8)=1,1,0) -> 0 | X8: =IF(SUM(V8:W8)=2,1,0) -> 0 | AA8: =IF(SUM(Y8:Z8)=2,1,0) -> 0 | AB8: =IF(E9<>"EXCAVADO EBM",SUM(I8*0.2+O8*0.2+R8*0.2+U8*0.2+X8*0.2),SUM(I8*0.16+O8*0.16+R8*0.16+U8*0.16+X8*0.16+AA8*0.16)) -> 0
A9: ='Listado CAPS'!A7 -> 0 | B9: ='Listado CAPS'!B7 -> 0 | C9: ='Listado CAPS'!C7 -> 0 | D9: ='Listado CAPS'!D7 -> E | I9: =IF(SUM(G9:H9)=2,1,0) -> 0 | O9: =IF(SUM(J9:N9)>=4,1,0) -> 0 | R9: =IF(SUM(P9:Q9)=2,1,0) -> 0 | U9: =IF(SUM(S9:T9)=1,1,0) -> 0 | X9: =IF(SUM(V9:W9)=2,1,0) -> 0 | AA9: =IF(SUM(Y9:Z9)=2,1,0) -> 0 | AB9: =IF(E10<>"EXCAVADO EBM",SUM(I9*0.2+O9*0.2+R9*0.2+U9*0.2+X9*0.2),SUM(I9*0.16+O9*0.16+R9*0.16+U9*0.16+X9*0.16+AA9*0.16)) -> 0
A10: ='Listado CAPS'!A8 -> 0 | B10: ='Listado CAPS'!B8 -> 0 | C10: ='Listado CAPS'!C8 -> 0 | D10: ='Listado CAPS'!D8 -> F | I10: =IF(SUM(G10:H10)=2,1,0) -> 0 | O10: =IF(SUM(J10:N10)>=4,1,0) -> 0 | R10: =IF(SUM(P10:Q10)=2,1,0) -> 0 | U10: =IF(SUM(S10:T10)=1,1,0) -> 0 | X10: =IF(SUM(V10:W10)=2,1,0) -> 0 | AA10: =IF(SUM(Y10:Z10)=2,1,0) -> 0 | AB10: =IF(E11<>"EXCAVADO EBM",SUM(I10*0.2+O10*0.2+R10*0.2+U10*0.2+X10*0.2),SUM(I10*0.16+O10*0.16+R10*0.16+U10*0.16+X10*0.16+AA10*0.16)) -> 0
A11: ='Listado CAPS'!A9 -> 0 | B11: ='Listado CAPS'!B9 -> 0 | C11: ='Listado CAPS'!C9 -> 0 | D11: ='Listado CAPS'!D9 -> G | I11: =IF(SUM(G11:H11)=2,1,0) -> 0 | O11: =IF(SUM(J11:N11)>=4,1,0) -> 0 | R11: =IF(SUM(P11:Q11)=2,1,0) -> 0 | U11: =IF(SUM(S11:T11)=1,1,0) -> 0 | X11: =IF(SUM(V11:W11)=2,1,0) -> 0 | AA11: =IF(SUM(Y11:Z11)=2,1,0) -> 0 | AB11: =IF(E12<>"EXCAVADO EBM",SUM(I11*0.2+O11*0.2+R11*0.2+U11*0.2+X11*0.2),SUM(I11*0.16+O11*0.16+R11*0.16+U11*0.16+X11*0.16+AA11*0.16)) -> 0
A12: ='Listado CAPS'!A10 -> 0 | B12: ='Listado CAPS'!B10 -> 0 | C12: ='Listado CAPS'!C10 -> 0 | D12: ='Listado CAPS'!D10 -> H | I12: =IF(SUM(G12:H12)=2,1,0) -> 0 | O12: =IF(SUM(J12:N12)>=4,1,0) -> 0 | R12: =IF(SUM(P12:Q12)=2,1,0) -> 0 | U12: =IF(SUM(S12:T12)=1,1,0) -> 0 | X12: =IF(SUM(V12:W12)=2,1,0) -> 0 | AA12: =IF(SUM(Y12:Z12)=2,1,0) -> 0 | AB12: =IF(E13<>"EXCAVADO EBM",SUM(I12*0.2+O12*0.2+R12*0.2+U12*0.2+X12*0.2),SUM(I12*0.16+O12*0.16+R12*0.16+U12*0.16+X12*0.16+AA12*0.16)) -> 0
A13: ='Listado CAPS'!A11 -> 0 | B13: ='Listado CAPS'!B11 -> 0 | C13: ='Listado CAPS'!C11 -> 0 | D13: ='Listado CAPS'!D11 -> I | I13: =IF(SUM(G13:H13)=2,1,0) -> 0 | O13: =IF(SUM(J13:N13)>=4,1,0) -> 0 | R13: =IF(SUM(P13:Q13)=2,1,0) -> 0 | U13: =IF(SUM(S13:T13)=1,1,0) -> 0 | X13: =IF(SUM(V13:W13)=2,1,0) -> 0 | AA13: =IF(SUM(Y13:Z13)=2,1,0) -> 0 | AB13: =IF(E14<>"EXCAVADO EBM",SUM(I13*0.2+O13*0.2+R13*0.2+U13*0.2+X13*0.2),SUM(I13*0.16+O13*0.16+R13*0.16+U13*0.16+X13*0.16+AA13*0.16)) -> 0
A14: ='Listado CAPS'!A12 -> 0 | B14: ='Listado CAPS'!B12 -> 0 | C14: ='Listado CAPS'!C12 -> 0 | D14: ='Listado CAPS'!D12 -> J | I14: =IF(SUM(G14:H14)=2,1,0) -> 0 | O14: =IF(SUM(J14:N14)>=4,1,0) -> 0 | R14: =IF(SUM(P14:Q14)=2,1,0) -> 0 | U14: =IF(SUM(S14:T14)=1,1,0) -> 0 | X14: =IF(SUM(V14:W14)=2,1,0) -> 0 | AA14: =IF(SUM(Y14:Z14)=2,1,0) -> 0 | AB14: =IF(E15<>"EXCAVADO EBM",SUM(I14*0.2+O14*0.2+R14*0.2+U14*0.2+X14*0.2),SUM(I14*0.16+O14*0.16+R14*0.16+U14*0.16+X14*0.16+AA14*0.16)) -> 0
A15: ='Listado CAPS'!A13 -> 0 | B15: ='Listado CAPS'!B13 -> 0 | C15: ='Listado CAPS'!C13 -> 0 | D15: ='Listado CAPS'!D13 -> K | I15: =IF(SUM(G15:H15)=2,1,0) -> 0 | O15: =IF(SUM(J15:N15)>=4,1,0) -> 0 | R15: =IF(SUM(P15:Q15)=2,1,0) -> 0 | U15: =IF(SUM(S15:T15)=1,1,0) -> 0 | X15: =IF(SUM(V15:W15)=2,1,0) -> 0 | AA15: =IF(SUM(Y15:Z15)=2,1,0) -> 0 | AB15: =IF(E16<>"EXCAVADO EBM",SUM(I15*0.2+O15*0.2+R15*0.2+U15*0.2+X15*0.2),SUM(I15*0.16+O15*0.16+R15*0.16+U15*0.16+X15*0.16+AA15*0.16)) -> 0
A16: ='Listado CAPS'!A14 -> 0 | B16: ='Listado CAPS'!B14 -> 0 | C16: ='Listado CAPS'!C14 -> 0 | D16: ='Listado CAPS'!D14 -> L | I16: =IF(SUM(G16:H16)=2,1,0) -> 0 | O16: =IF(SUM(J16:N16)>=4,1,0) -> 0 | R16: =IF(SUM(P16:Q16)=2,1,0) -> 0 | U16: =IF(SUM(S16:T16)=1,1,0) -> 0 | X16: =IF(SUM(V16:W16)=2,1,0) -> 0 | AA16: =IF(SUM(Y16:Z16)=2,1,0) -> 0 | AB16: =IF(E17<>"EXCAVADO EBM",SUM(I16*0.2+O16*0.2+R16*0.2+U16*0.2+X16*0.2),SUM(I16*0.16+O16*0.16+R16*0.16+U16*0.16+X16*0.16+AA16*0.16)) -> 0
A17: ='Listado CAPS'!A15 -> 0 | B17: ='Listado CAPS'!B15 -> 0 | C17: ='Listado CAPS'!C15 -> 0 | D17: ='Listado CAPS'!D15 -> M | I17: =IF(SUM(G17:H17)=2,1,0) -> 0 | O17: =IF(SUM(J17:N17)>=4,1,0) -> 0 | R17: =IF(SUM(P17:Q17)=2,1,0) -> 0 | U17: =IF(SUM(S17:T17)=1,1,0) -> 0 | X17: =IF(SUM(V17:W17)=2,1,0) -> 0 | AA17: =IF(SUM(Y17:Z17)=2,1,0) -> 0 | AB17: =IF(E18<>"EXCAVADO EBM",SUM(I17*0.2+O17*0.2+R17*0.2+U17*0.2+X17*0.2),SUM(I17*0.16+O17*0.16+R17*0.16+U17*0.16+X17*0.16+AA17*0.16)) -> 0
... A22: ='Listado CAPS'!A20 -> 0 | B22: ='Listado CAPS'!B20 -> 0 | C22: ='Listado CAPS'!C20 -> 0 | D22: ='Listado CAPS'!D20 -> Q | I22: =IF(SUM(G22:H22)=2,1,0) -> 0 | O22: =IF(SUM(J22:N22)>=4,1,0) -> 0 | R22: =IF(SUM(P22:Q22)=2,1,0) -> 0 | U22: =IF(SUM(S22:T22)=1,1,0) -> 0 | X22: =IF(SUM(V22:W22)=2,1,0) -> 0 | AA22: =IF(SUM(Y22:Z22)=2,1,0) -> 0 | AB22: =IF(E23<>"EXCAVADO EBM",SUM(I22*0.2+O22*0.2+R22*0.2+U22*0.2+X22*0.2),SUM(I22*0.16+O22*0.16+R22*0.16+U22*0.16+X22*0.16+AA22*0.16)) -> 0
A23: ='Listado CAPS'!A21 -> 0 | B23: ='Listado CAPS'!B21 -> 0 | C23: ='Listado CAPS'!C21 -> 0 | D23: ='Listado CAPS'!D21 -> R | E23: ='Listado CAPS'!E21 -> 0 | I23: =IF(SUM(G23:H23)=2,1,0) -> 0 | O23: =IF(SUM(J23:N23)>=4,1,0) -> 0 | R23: =IF(SUM(P23:Q23)=2,1,0) -> 0 | U23: =IF(SUM(S23:T23)=1,1,0) -> 0 | X23: =IF(SUM(V23:W23)=2,1,0) -> 0 | AA23: =IF(SUM(Y23:Z23)=2,1,0) -> 0 | AB23: =IF(E24<>"EXCAVADO EBM",SUM(I23*0.2+O23*0.2+R23*0.2+U23*0.2+X23*0.2),SUM(I23*0.16+O23*0.16+R23*0.16+U23*0.16+X23*0.16+AA23*0.16)) -> 0
A24: ='Listado CAPS'!A22 -> 0 | B24: ='Listado CAPS'!B22 -> 0 | C24: ='Listado CAPS'!C22 -> 0 | D24: ='Listado CAPS'!D22 -> S | E24: ='Listado CAPS'!E22 -> 0 | I24: =IF(SUM(G24:H24)=2,1,0) -> 0 | O24: =IF(SUM(J24:N24)>=4,1,0) -> 0 | R24: =IF(SUM(P24:Q24)=2,1,0) -> 0 | U24: =IF(SUM(S24:T24)=1,1,0) -> 0 | X24: =IF(SUM(V24:W24)=2,1,0) -> 0 | AA24: =IF(SUM(Y24:Z24)=2,1,0) -> 0 | AB24: =IF(E25<>"EXCAVADO EBM",SUM(I24*0.2+O24*0.2+R24*0.2+U24*0.2+X24*0.2),SUM(I24*0.16+O24*0.16+R24*0.16+U24*0.16+X24*0.16+AA24*0.16)) -> 0
A25: ='Listado CAPS'!A23 -> 0 | B25: ='Listado CAPS'!B23 -> 0 | C25: ='Listado CAPS'!C23 -> 0 | D25: ='Listado CAPS'!D23 -> T | E25: ='Listado CAPS'!E23 -> 0 | I25: =IF(SUM(G25:H25)=2,1,0) -> 0 | O25: =IF(SUM(J25:N25)>=4,1,0) -> 0 | R25: =IF(SUM(P25:Q25)=2,1,0) -> 0 | U25: =IF(SUM(S25:T25)=1,1,0) -> 0 | X25: =IF(SUM(V25:W25)=2,1,0) -> 0 | AA25: =IF(SUM(Y25:Z25)=2,1,0) -> 0 | AB25: =IF(E26<>"EXCAVADO EBM",SUM(I25*0.2+O25*0.2+R25*0.2+U25*0.2+X25*0.2),SUM(I25*0.16+O25*0.16+R25*0.16+U25*0.16+X25*0.16+AA25*0.16)) -> 0
A26: ='Listado CAPS'!A24 -> 0 | B26: ='Listado CAPS'!B24 -> 0 | C26: ='Listado CAPS'!C24 -> 0 | D26: ='Listado CAPS'!D24 -> U | E26: ='Listado CAPS'!E24 -> 0 | I26: =IF(SUM(G26:H26)=2,1,0) -> 0 | O26: =IF(SUM(J26:N26)>=4,1,0) -> 0 | R26: =IF(SUM(P26:Q26)=2,1,0) -> 0 | U26: =IF(SUM(S26:T26)=1,1,0) -> 0 | X26: =IF(SUM(V26:W26)=2,1,0) -> 0 | AA26: =IF(SUM(Y26:Z26)=2,1,0) -> 0 | AB26: =IF(E27<>"EXCAVADO EBM",SUM(I26*0.2+O26*0.2+R26*0.2+U26*0.2+X26*0.2),SUM(I26*0.16+O26*0.16+R26*0.16+U26*0.16+X26*0.16+AA26*0.16)) -> 0
A27: ='Listado CAPS'!A25 -> 0 | B27: ='Listado CAPS'!B25 -> 0 | C27: ='Listado CAPS'!C25 -> 0 | D27: ='Listado CAPS'!D25 -> V | E27: ='Listado CAPS'!E25 -> 0 | I27: =IF(SUM(G27:H27)=2,1,0) -> 0 | O27: =IF(SUM(J27:N27)>=4,1,0) -> 0 | R27: =IF(SUM(P27:Q27)=2,1,0) -> 0 | U27: =IF(SUM(S27:T27)=1,1,0) -> 0 | X27: =IF(SUM(V27:W27)=2,1,0) -> 0 | AA27: =IF(SUM(Y27:Z27)=2,1,0) -> 0 | AB27: =IF(E28<>"EXCAVADO EBM",SUM(I27*0.2+O27*0.2+R27*0.2+U27*0.2+X27*0.2),SUM(I27*0.16+O27*0.16+R27*0.16+U27*0.16+X27*0.16+AA27*0.16)) -> 0
A28: ='Listado CAPS'!A26 -> 0 | B28: ='Listado CAPS'!B26 -> 0 | C28: ='Listado CAPS'!C26 -> 0 | D28: ='Listado CAPS'!D26 -> W | E28: ='Listado CAPS'!E26 -> 0 | I28: =IF(SUM(G28:H28)=2,1,0) -> 0 | O28: =IF(SUM(J28:N28)>=4,1,0) -> 0 | R28: =IF(SUM(P28:Q28)=2,1,0) -> 0 | U28: =IF(SUM(S28:T28)=1,1,0) -> 0 | X28: =IF(SUM(V28:W28)=2,1,0) -> 0 | AA28: =IF(SUM(Y28:Z28)=2,1,0) -> 0 | AB28: =IF(E29<>"EXCAVADO EBM",SUM(I28*0.2+O28*0.2+R28*0.2+U28*0.2+X28*0.2),SUM(I28*0.16+O28*0.16+R28*0.16+U28*0.16+X28*0.16+AA28*0.16)) -> 0
A29: ='Listado CAPS'!A27 -> 0 | B29: ='Listado CAPS'!B27 -> 0 | C29: ='Listado CAPS'!C27 -> 0 | D29: ='Listado CAPS'!D27 -> X | E29: ='Listado CAPS'!E27 -> 0 | I29: =IF(SUM(G29:H29)=2,1,0) -> 0 | O29: =IF(SUM(J29:N29)>=4,1,0) -> 0 | R29: =IF(SUM(P29:Q29)=2,1,0) -> 0 | U29: =IF(SUM(S29:T29)=1,1,0) -> 0 | X29: =IF(SUM(V29:W29)=2,1,0) -> 0 | AA29: =IF(SUM(Y29:Z29)=2,1,0) -> 0 | AB29: =IF(E30<>"EXCAVADO EBM",SUM(I29*0.2+O29*0.2+R29*0.2+U29*0.2+X29*0.2),SUM(I29*0.16+O29*0.16+R29*0.16+U29*0.16+X29*0.16+AA29*0.16)) -> 0
A30: ='Listado CAPS'!A28 -> 0 | B30: ='Listado CAPS'!B28 -> 0 | C30: ='Listado CAPS'!C28 -> 0 | D30: ='Listado CAPS'!D28 -> Y | E30: ='Listado CAPS'!E28 -> 0 | I30: =IF(SUM(G30:H30)=2,1,0) -> 0 | O30: =IF(SUM(J30:N30)>=4,1,0) -> 0 | R30: =IF(SUM(P30:Q30)=2,1,0) -> 0 | U30: =IF(SUM(S30:T30)=1,1,0) -> 0 | X30: =IF(SUM(V30:W30)=2,1,0) -> 0 | AA30: =IF(SUM(Y30:Z30)=2,1,0) -> 0 | AB30: =IF(E31<>"EXCAVADO EBM",SUM(I30*0.2+O30*0.2+R30*0.2+U30*0.2+X30*0.2),SUM(I30*0.16+O30*0.16+R30*0.16+U30*0.16+X30*0.16+AA30*0.16)) -> 0

Sheet I.Genero 
B2: Volver a Tabla de contenidos | D2: I. GÉNERO | K2: Ir a Resultados Finales
E3: Instrucciones: Las 3 primeras acciones positivas de la JD se autocompletan con los datos de la hoja "Conformación de la JD". No rellenar. Solo las columnas en blanco. | I3: Criterio A: cada una de las 3 acciones vale 0,33. Criterio B: cada una de las 2 acciones vale 0,5.
A4: Departamento | B4: Municipio | C4: Comunidad | D4: CAPS | E4: A. Acciones positivas de la JD | H4: A | I4: B.Acciones positivas dirigidas a promover la participación de mujeres. | K4: B
E6: ¿El 50 % de la JD está conformada por mujeres? | F6: ¿Hay mujeres en los puestos de Presidenta o Tesorera? | G6: Al menos un 40% de asistencia de mujeres en las Asambleas | I6: ¿Ha realizado adendum a su reglamento para la promoción de acciones positivas que promuevan la participación de la mujer? | J6: ¿Se ha cumplido al menos el 50% de las acciones positivas que se habían propuesto?
A7: ='Listado CAPS'!A3 -> Madriz | B7: ='Listado CAPS'!B3 -> Yalaguina | C7: ='Listado CAPS'!C3 -> Los Encuentros | D7: ='Listado CAPS'!D3 -> Los Encuentros | E7: =IF('Conformación JD'!AA7>=50%,1,0) -> 1 | F7: =IF('Conformación JD'!Z7>=1,1,0) -> 1 | G7: =IF('A.Org_CAPS'!K16>=40%,1,0) -> 1 | H7: =SUM(E7+F7+G7)/3 -> 1 | I7: 1 | J7: 1 | K7: =SUM(I7+J7)/2 -> 1
A8: ='Listado CAPS'!A4 -> 0 | B8: ='Listado CAPS'!B4 -> 0 | C8: ='Listado CAPS'!C4 -> 0 | D8: ='Listado CAPS'!D4 -> B | E8: =IF('Conformación JD'!AA8>=50%,1,0) -> 0 | F8: =IF('Conformación JD'!Z8>=1,1,0) -> 0 | G8: =IF('A.Org_CAPS'!K30>=40%,1,0) -> 0 | H8: =SUM(E8+F8+G8)/3 -> 0 | K8: =SUM(I8+J8)/2 -> 0
A9: ='Listado CAPS'!A5 -> 0 | B9: ='Listado CAPS'!B5 -> 0 | C9: ='Listado CAPS'!C5 -> 0 | D9: ='Listado CAPS'!D5 -> C | E9: =IF('Conformación JD'!AA9>=50%,1,0) -> 0 | F9: =IF('Conformación JD'!Z9>=1,1,0) -> 0 | G9: =IF('A.Org_CAPS'!K44>=40%,1,0) -> 0 | H9: =SUM(E9+F9+G9)/3 -> 0 | K9: =SUM(I9+J9)/2 -> 0
A10: ='Listado CAPS'!A6 -> 0 | B10: ='Listado CAPS'!B6 -> 0 | C10: ='Listado CAPS'!C6 -> 0 | D10: ='Listado CAPS'!D6 -> D | E10: =IF('Conformación JD'!AA10>=50%,1,0) -> 0 | F10: =IF('Conformación JD'!Z10>=1,1,0) -> 0 | G10: =IF('A.Org_CAPS'!K58>=40%,1,0) -> 0 | H10: =SUM(E10+F10+G10)/3 -> 0 | K10: =SUM(I10+J10)/2 -> 0
A11: ='Listado CAPS'!A7 -> 0 | B11: ='Listado CAPS'!B7 -> 0 | C11: ='Listado CAPS'!C7 -> 0 | D11: ='Listado CAPS'!D7 -> E | E11: =IF('Conformación JD'!AA11>=50%,1,0) -> 0 | F11: =IF('Conformación JD'!Z11>=1,1,0) -> 0 | G11: =IF('A.Org_CAPS'!K72>=40%,1,0) -> 0 | H11: =SUM(E11+F11+G11)/3 -> 0 | K11: =SUM(I11+J11)/2 -> 0
A12: ='Listado CAPS'!A8 -> 0 | B12: ='Listado CAPS'!B8 -> 0 | C12: ='Listado CAPS'!C8 -> 0 | D12: ='Listado CAPS'!D8 -> F | E12: =IF('Conformación JD'!AA12>=50%,1,0) -> 0 | F12: =IF('Conformación JD'!Z12>=1,1,0) -> 0 | G12: =IF('A.Org_CAPS'!K86>=40%,1,0) -> 0 | H12: =SUM(E12+F12+G12)/3 -> 0 | K12: =SUM(I12+J12)/2 -> 0
A13: ='Listado CAPS'!A9 -> 0 | B13: ='Listado CAPS'!B9 -> 0 | C13: ='Listado CAPS'!C9 -> 0 | D13: ='Listado CAPS'!D9 -> G | E13: =IF('Conformación JD'!AA13>=50%,1,0) -> 0 | F13: =IF('Conformación JD'!Z13>=1,1,0) -> 0 | G13: =IF('A.Org_CAPS'!K100>=40%,1,0) -> 0 | H13: =SUM(E13+F13+G13)/3 -> 0 | K13: =SUM(I13+J13)/2 -> 0
A14: ='Listado CAPS'!A10 -> 0 | B14: ='Listado CAPS'!B10 -> 0 | C14: ='Listado CAPS'!C10 -> 0 | D14: ='Listado CAPS'!D10 -> H | E14: =IF('Conformación JD'!AA14>=50%,1,0) -> 0 | F14: =IF('Conformación JD'!Z14>=1,1,0) -> 0 | G14: =IF('A.Org_CAPS'!K114>=40%,1,0) -> 0 | H14: =SUM(E14+F14+G14)/3 -> 0 | K14: =SUM(I14+J14)/2 -> 0
A15: ='Listado CAPS'!A11 -> 0 | B15: ='Listado CAPS'!B11 -> 0 | C15: ='Listado CAPS'!C11 -> 0 | D15: ='Listado CAPS'!D11 -> I | E15: =IF('Conformación JD'!AA15>=50%,1,0) -> 0 | F15: =IF('Conformación JD'!Z15>=1,1,0) -> 0 | G15: =IF('A.Org_CAPS'!K128>=40%,1,0) -> 0 | H15: =SUM(E15+F15+G15)/3 -> 0 | K15: =SUM(I15+J15)/2 -> 0
A16: ='Listado CAPS'!A12 -> 0 | B16: ='Listado CAPS'!B12 -> 0 | C16: ='Listado CAPS'!C12 -> 0 | D16: ='Listado CAPS'!D12 -> J | E16: =IF('Conformación JD'!AA16>=50%,1,0) -> 0 | F16: =IF('Conformación JD'!Z16>=1,1,0) -> 0 | G16: =IF('A.Org_CAPS'!K142>=40%,1,0) -> 0 | H16: =SUM(E16+F16+G16)/3 -> 0 | K16: =SUM(I16+J16)/2 -> 0
A17: ='Listado CAPS'!A13 -> 0 | B17: ='Listado CAPS'!B13 -> 0 | C17: ='Listado CAPS'!C13 -> 0 | D17: ='Listado CAPS'!D13 -> K | E17: =IF('Conformación JD'!AA17>=50%,1,0) -> 0 | F17: =IF('Conformación JD'!Z17>=1,1,0) -> 0 | G17: =IF('A.Org_CAPS'!K156>=40%,1,0) -> 0 | H17: =SUM(E17+F17+G17)/3 -> 0 | K17: =SUM(I17+J17)/2 -> 0
A18: ='Listado CAPS'!A14 -> 0 | B18: ='Listado CAPS'!B14 -> 0 | C18: ='Listado CAPS'!C14 -> 0 | D18: ='Listado CAPS'!D14 -> L | E18: =IF('Conformación JD'!AA18>=50%,1,0) -> 0 | F18: =IF('Conformación JD'!Z18>=1,1,0) -> 0 | G18: =IF('A.Org_CAPS'!K170>=40%,1,0) -> 0 | H18: =SUM(E18+F18+G18)/3 -> 0 | K18: =SUM(I18+J18)/2 -> 0
A19: ='Listado CAPS'!A15 -> 0 | B19: ='Listado CAPS'!B15 -> 0 | C19: ='Listado CAPS'!C15 -> 0 | D19: ='Listado CAPS'!D15 -> M | E19: =IF('Conformación JD'!AA19>=50%,1,0) -> 0 | F19: =IF('Conformación JD'!Z19>=1,1,0) -> 0 | G19: =IF('A.Org_CAPS'!K184>=40%,1,0) -> 0 | H19: =SUM(E19+F19+G19)/3 -> 0 | K19: =SUM(I19+J19)/2 -> 0
A20: ='Listado CAPS'!A16 -> 0 | B20: ='Listado CAPS'!B16 -> 0 | C20: ='Listado CAPS'!C16 -> 0 | D20: ='Listado CAPS'!D16 -> N | E20: =IF('Conformación JD'!AA20>=50%,1,0) -> 0 | F20: =IF('Conformación JD'!Z20>=1,1,0) -> 0 | G20: =IF('A.Org_CAPS'!K198>=40%,1,0) -> 0 | H20: =SUM(E20+F20+G20)/3 -> 0 | K20: =SUM(I20+J20)/2 -> 0
A21: ='Listado CAPS'!A17 -> 0 | B21: ='Listado CAPS'!B17 -> 0 | C21: ='Listado CAPS'!C17 -> 0 | D21: ='Listado CAPS'!D17 -> Ñ | E21: =IF('Conformación JD'!AA21>=50%,1,0) -> 0 | F21: =IF('Conformación JD'!Z21>=1,1,0) -> 0 | G21: =IF('A.Org_CAPS'!K212>=40%,1,0) -> 0 | H21: =SUM(E21+F21+G21)/3 -> 0 | K21: =SUM(I21+J21)/2 -> 0
A22: ='Listado CAPS'!A18 -> 0 | B22: ='Listado CAPS'!B18 -> 0 | C22: ='Listado CAPS'!C18 -> 0 | D22: ='Listado CAPS'!D18 -> O | E22: =IF('Conformación JD'!AA22>=50%,1,0) -> 0 | F22: =IF('Conformación JD'!Z22>=1,1,0) -> 0 | G22: =IF('A.Org_CAPS'!K226=40%,1,0) -> 0 | H22: =SUM(E22+F22+G22)/3 -> 0 | K22: =SUM(I22+J22)/2 -> 0
A23: ='Listado CAPS'!A19 -> 0 | B23: ='Listado CAPS'!B19 -> 0 | C23: ='Listado CAPS'!C19 -> 0 | D23: ='Listado CAPS'!D19 -> P | E23: =IF('Conformación JD'!AA23>=50%,1,0) -> 0 | F23: =IF('Conformación JD'!Z23>=1,1,0) -> 0 | G23: =IF('A.Org_CAPS'!K240>=40%,1,0) -> 0 | H23: =SUM(E23+F23+G23)/3 -> 0 | K23: =SUM(I23+J23)/2 -> 0
A24: ='Listado CAPS'!A20 -> 0 | B24: ='Listado CAPS'!B20 -> 0 | C24: ='Listado CAPS'!C20 -> 0 | D24: ='Listado CAPS'!D20 -> Q | E24: =IF('Conformación JD'!AA24>=50%,1,0) -> 0 | F24: =IF('Conformación JD'!Z24>=1,1,0) -> 0 | G24: =IF('A.Org_CAPS'!K254>=40%,1,0) -> 0 | H24: =SUM(E24+F24+G24)/3 -> 0 | K24: =SUM(I24+J24)/2 -> 0
A25: ='Listado CAPS'!A21 -> 0 | B25: ='Listado CAPS'!B21 -> 0 | C25: ='Listado CAPS'!C21 -> 0 | D25: ='Listado CAPS'!D21 -> R | E25: =IF('Conformación JD'!AA25>=50%,1,0) -> 0 | F25: =IF('Conformación JD'!Z25>=1,1,0) -> 0 | G25: =IF('A.Org_CAPS'!K268>=40%,1,0) -> 0 | H25: =SUM(E25+F25+G25)/3 -> 0 | K25: =SUM(I25+J25)/2 -> 0
A26: ='Listado CAPS'!A22 -> 0 | B26: ='Listado CAPS'!B22 -> 0 | C26: ='Listado CAPS'!C22 -> 0 | D26: ='Listado CAPS'!D22 -> S | E26: =IF('Conformación JD'!AA26>=50%,1,0) -> 0 | F26: =IF('Conformación JD'!Z26>=1,1,0) -> 0 | G26: =IF('A.Org_CAPS'!K282>=40%,1,0) -> 0 | H26: =SUM(E26+F26+G26)/3 -> 0 | K26: =SUM(I26+J26)/2 -> 0
A27: ='Listado CAPS'!A23 -> 0 | B27: ='Listado CAPS'!B23 -> 0 | C27: ='Listado CAPS'!C23 -> 0 | D27: ='Listado CAPS'!D23 -> T | E27: =IF('Conformación JD'!AA27>=50%,1,0) -> 0 | F27: =IF('Conformación JD'!Z27>=1,1,0) -> 0 | G27: =IF('A.Org_CAPS'!K296>=40%,1,0) -> 0 | H27: =SUM(E27+F27+G27)/3 -> 0 | K27: =SUM(I27+J27)/2 -> 0
A28: ='Listado CAPS'!A24 -> 0 | B28: ='Listado CAPS'!B24 -> 0 | C28: ='Listado CAPS'!C24 -> 0 | D28: ='Listado CAPS'!D24 -> U | E28: =IF('Conformación JD'!AA28>=50%,1,0) -> 0 | F28: =IF('Conformación JD'!Z28>=1,1,0) -> 0 | G28: =IF('A.Org_CAPS'!K310>=40%,1,0) -> 0 | H28: =SUM(E28+F28+G28)/3 -> 0 | K28: =SUM(I28+J28)/2 -> 0
A29: ='Listado CAPS'!A25 -> 0 | B29: ='Listado CAPS'!B25 -> 0 | C29: ='Listado CAPS'!C25 -> 0 | D29: ='Listado CAPS'!D25 -> V | E29: =IF('Conformación JD'!AA29>=50%,1,0) -> 0 | F29: =IF('Conformación JD'!Z29>=1,1,0) -> 0 | G29: =IF('A.Org_CAPS'!K324>=40%,1,0) -> 0 | H29: =SUM(E29+F29+G29)/3 -> 0 | K29: =SUM(I29+J29)/2 -> 0
A30: ='Listado CAPS'!A26 -> 0 | B30: ='Listado CAPS'!B26 -> 0 | C30: ='Listado CAPS'!C26 -> 0 | D30: ='Listado CAPS'!D26 -> W | E30: =IF('Conformación JD'!AA30>=50%,1,0) -> 0 | F30: =IF('Conformación JD'!Z30>=1,1,0) -> 0 | G30: =IF('A.Org_CAPS'!K338>=40%,1,0) -> 0 | H30: =SUM(E30+F30+G30)/3 -> 0 | K30: =SUM(I30+J30)/2 -> 0
A31: ='Listado CAPS'!A27 -> 0 | B31: ='Listado CAPS'!B27 -> 0 | C31: ='Listado CAPS'!C27 -> 0 | D31: ='Listado CAPS'!D27 -> X | E31: =IF('Conformación JD'!AA31>=50%,1,0) -> 0 | F31: =IF('Conformación JD'!Z31>=1,1,0) -> 0 | G31: =IF('A.Org_CAPS'!K352>=40%,1,0) -> 0 | H31: =SUM(E31+F31+G31)/3 -> 0 | K31: =SUM(I31+J31)/2 -> 0
A32: ='Listado CAPS'!A28 -> 0 | B32: ='Listado CAPS'!B28 -> 0 | C32: ='Listado CAPS'!C28 -> 0 | D32: ='Listado CAPS'!D28 -> Y | E32: =IF('Conformación JD'!AA32>=50%,1,0) -> 0 | F32: =IF('Conformación JD'!Z32>=1,1,0) -> 0 | G32: =IF('A.Org_CAPS'!K366>=40%,1,0) -> 0 | H32: =SUM(E32+F32+G32)/3 -> 0 | K32: =SUM(I32+J32)/2 -> 0

Sheet J.AutoGestionCAPS
B1: Volver a Tabla de contenidos | D1: C. AUTOGESTION DE LOS CAPS | L1: Ir a Resultados Finales
E2: Instrucciones: Si el CAPS ha tenido algún porblema que exceda su capacidad rellene 1 y siga. La clasificación del tipo de gestión se rellena con una X.. | H2: Criterio: al menos el 50 % de los problemas gestionados, aunque no se hayan solucionado.
A3: Departamento | B3: Municipio | C3: Comunidad | D3: CAPS | E3: Se ha presentado algún problema que trascienda a su capacidad de respuesta? Si (rellene con 1) y complete los demás puntos. | F3: Describa brevemente el problema | G3: ¿Realizó gestión para solucionarlo? (escriba 1 si es que SÍ) | H3: ¿A quién acudió? | I3: ¿Se solucionó? (escriba 1 si es que SÍ) | J3: Clasifique el tipo de gestión (marque con una X)
J4: Administrativa | K4: Legal | L4: Organizativa | M4: Técnica | N4: O&T | O4: Otros | P4: No tocar | Q4: x
A5: ='Listado CAPS'!A3 -> Madriz | B5: ='Listado CAPS'!B3 -> Yalaguina | C5: ='Listado CAPS'!C3 -> Los Encuentros | D5: ='Listado CAPS'!D3 -> Los Encuentros | E5: 1 | F5: Fuente de agua colapsada | G5: 1 | H5: 1 | I5: 1 | M5: x
A15: TOTAL | E15: =AVERAGE(E5:E14) -> 1 | G15: =IF(E15<>0,SUM(G5:G14)/E15,0) -> 1 | I15: =IF(E15<>0,SUM(I5:I14)/E15,0) -> 1 | J15: =COUNTIF(J5:J14,$Q$4) -> 0 | K15: =COUNTIF(K5:K14,$Q$4) -> 0 | L15: =COUNTIF(L5:L14,$Q$4) -> 0 | M15: =COUNTIF(M5:M14,$Q$4) -> 1 | N15: =COUNTIF(N5:N14,$Q$4) -> 0 | O15: =COUNTIF(O5:O14,$Q$4) -> 0
A16: ='Listado CAPS'!A4 -> 0 | B16: ='Listado CAPS'!B4 -> 0 | C16: ='Listado CAPS'!C4 -> 0 | D16: ='Listado CAPS'!D4 -> B | E16: 0
A26: TOTAL | E26: =AVERAGE(E16:E25) -> 0 | G26: =IF(E26<>0,SUM(G16:G25)/E26,0) -> 0 | I26: =IF(E26<>0,SUM(I16:I25)/E26,0) -> 0 | J26: =COUNTIF(J16:J25,$Q$4) -> 0 | K26: =COUNTIF(K16:K25,$Q$4) -> 0 | L26: =COUNTIF(L16:L25,$Q$4) -> 0 | M26: =COUNTIF(M16:M25,$Q$4) -> 0 | N26: =COUNTIF(N16:N25,$Q$4) -> 0 | O26: =COUNTIF(O16:O25,$Q$4) -> 0
A27: ='Listado CAPS'!A5 -> 0 | B27: ='Listado CAPS'!B5 -> 0 | C27: ='Listado CAPS'!C5 -> 0 | D27: ='Listado CAPS'!D5 -> C | E27: 0
A37: TOTAL | E37: =AVERAGE(E27:E36) -> 0 | G37: =IF(E37<>0,SUM(G27:G36)/E37,0) -> 0 | I37: =IF(E37<>0,SUM(I27:I36)/E37,0) -> 0 | J37: =COUNTIF(J27:J36,$Q$4) -> 0 | K37: =COUNTIF(K27:K36,$Q$4) -> 0 | L37: =COUNTIF(L27:L36,$Q$4) -> 0 | M37: =COUNTIF(M27:M36,$Q$4) -> 0 | N37: =COUNTIF(N27:N36,$Q$4) -> 0 | O37: =COUNTIF(O27:O36,$Q$4) -> 0
A38: ='Listado CAPS'!A6 -> 0 | B38: ='Listado CAPS'!B6 -> 0 | C38: ='Listado CAPS'!C6 -> 0 | D38: ='Listado CAPS'!D6 -> D | E38: 0
A48: TOTAL | E48: =AVERAGE(E38:E47) -> 0 | G48: =IF(E48<>0,SUM(G38:G47)/E48,0) -> 0 | I48: =IF(E48<>0,SUM(I38:I47)/E48,0) -> 0 | J48: =COUNTIF(J38:J47,$Q$4) -> 0 | K48: =COUNTIF(K38:K47,$Q$4) -> 0 | L48: =COUNTIF(L38:L47,$Q$4) -> 0 | M48: =COUNTIF(M38:M47,$Q$4) -> 0 | N48: =COUNTIF(N38:N47,$Q$4) -> 0 | O48: =COUNTIF(O38:O47,$Q$4) -> 0
A49: ='Listado CAPS'!A7 -> 0 | B49: ='Listado CAPS'!B7 -> 0 | C49: ='Listado CAPS'!C7 -> 0 | D49: ='Listado CAPS'!D7 -> E | E49: 0
A59: TOTAL | E59: =AVERAGE(E49:E58) -> 0 | G59: =IF(E59<>0,SUM(G49:G58)/E59,0) -> 0 | I59: =IF(E59<>0,SUM(I49:I58)/E59,0) -> 0 | J59: =COUNTIF(J49:J58,$Q$4) -> 0 | K59: =COUNTIF(K49:K58,$Q$4) -> 0 | L59: =COUNTIF(L49:L58,$Q$4) -> 0 | M59: =COUNTIF(M49:M58,$Q$4) -> 0 | N59: =COUNTIF(N49:N58,$Q$4) -> 0 | O59: =COUNTIF(O49:O58,$Q$4) -> 0
A60: ='Listado CAPS'!A8 -> 0 | B60: ='Listado CAPS'!B8 -> 0 | C60: ='Listado CAPS'!C8 -> 0 | D60: ='Listado CAPS'!D8 -> F | E60: 0
A70: TOTAL | E70: =AVERAGE(E60:E69) -> 0 | G70: =IF(E70<>0,SUM(G60:G69)/E70,0) -> 0 | I70: =IF(E70<>0,SUM(I60:I69)/E70,0) -> 0 | J70: =COUNTIF(J60:J69,$Q$4) -> 0 | K70: =COUNTIF(K60:K69,$Q$4) -> 0 | L70: =COUNTIF(L60:L69,$Q$4) -> 0 | M70: =COUNTIF(M60:M69,$Q$4) -> 0 | N70: =COUNTIF(N60:N69,$Q$4) -> 0 | O70: =COUNTIF(O60:O69,$Q$4) -> 0
A71: ='Listado CAPS'!A9 -> 0 | B71: ='Listado CAPS'!B9 -> 0 | C71: ='Listado CAPS'!C9 -> 0 | D71: ='Listado CAPS'!D9 -> G | E71: 0
A81: TOTAL | E81: =AVERAGE(E71:E80) -> 0 | G81: =IF(E81<>0,SUM(G71:G80)/E81,0) -> 0 | I81: =IF(E81<>0,SUM(I71:I80)/E81,0) -> 0 | J81: =COUNTIF(J71:J80,$Q$4) -> 0 | K81: =COUNTIF(K71:K80,$Q$4) -> 0 | L81: =COUNTIF(L71:L80,$Q$4) -> 0 | M81: =COUNTIF(M71:M80,$Q$4) -> 0 | N81: =COUNTIF(N71:N80,$Q$4) -> 0 | O81: =COUNTIF(O71:O80,$Q$4) -> 0
A82: ='Listado CAPS'!A10 -> 0 | B82: ='Listado CAPS'!B10 -> 0 | C82: ='Listado CAPS'!C10 -> 0 | D82: ='Listado CAPS'!D10 -> H | E82: 0
A92: TOTAL | E92: =AVERAGE(E82:E91) -> 0 | G92: =IF(E92<>0,SUM(G82:G91)/E92,0) -> 0 | I92: =IF(E92<>0,SUM(I82:I91)/E92,0) -> 0 | J92: =COUNTIF(J82:J91,$Q$4) -> 0 | K92: =COUNTIF(K82:K91,$Q$4) -> 0 | L92: =COUNTIF(L82:L91,$Q$4) -> 0 | M92: =COUNTIF(M82:M91,$Q$4) -> 0 | N92: =COUNTIF(N82:N91,$Q$4) -> 0 | O92: =COUNTIF(O82:O91,$Q$4) -> 0
A93: ='Listado CAPS'!A11 -> 0 | B93: ='Listado CAPS'!B11 -> 0 | C93: ='Listado CAPS'!C11 -> 0 | D93: ='Listado CAPS'!D11 -> I | E93: 0
A103: TOTAL | E103: =AVERAGE(E93:E102) -> 0 | G103: =IF(E103<>0,SUM(G93:G102)/E103,0) -> 0 | I103: =IF(E103<>0,SUM(I93:I102)/E103,0) -> 0 | J103: =COUNTIF(J93:J102,$Q$4) -> 0 | K103: =COUNTIF(K93:K102,$Q$4) -> 0 | L103: =COUNTIF(L93:L102,$Q$4) -> 0 | M103: =COUNTIF(M93:M102,$Q$4) -> 0 | N103: =COUNTIF(N93:N102,$Q$4) -> 0 | O103: =COUNTIF(O93:O102,$Q$4) -> 0
A104: ='Listado CAPS'!A12 -> 0 | B104: ='Listado CAPS'!B12 -> 0 | C104: ='Listado CAPS'!C12 -> 0 | D104: ='Listado CAPS'!D12 -> J | E104: 0
A114: TOTAL | E114: =AVERAGE(E104:E113) -> 0 | G114: =IF(E114<>0,SUM(G104:G113)/E114,0) -> 0 | I114: =IF(E114<>0,SUM(I104:I113)/E114,0) -> 0 | J114: =COUNTIF(J104:J113,$Q$4) -> 0 | K114: =COUNTIF(K104:K113,$Q$4) -> 0 | L114: =COUNTIF(L104:L113,$Q$4) -> 0 | M114: =COUNTIF(M104:M113,$Q$4) -> 0 | N114: =COUNTIF(N104:N113,$Q$4) -> 0 | O114: =COUNTIF(O104:O113,$Q$4) -> 0
A115: ='Listado CAPS'!A13 -> 0 | B115: ='Listado CAPS'!B13 -> 0 | C115: ='Listado CAPS'!C13 -> 0 | D115: ='Listado CAPS'!D13 -> K | E115: 0
A125: TOTAL | E125: =AVERAGE(E115:E124) -> 0 | G125: =IF(E125<>0,SUM(G115:G124)/E125,0) -> 0 | I125: =IF(E125<>0,SUM(I115:I124)/E125,0) -> 0 | J125: =COUNTIF(J115:J124,$Q$4) -> 0 | K125: =COUNTIF(K115:K124,$Q$4) -> 0 | L125: =COUNTIF(L115:L124,$Q$4) -> 0 | M125: =COUNTIF(M115:M124,$Q$4) -> 0 | N125: =COUNTIF(N115:N124,$Q$4) -> 0 | O125: =COUNTIF(O115:O124,$Q$4) -> 0
A126: ='Listado CAPS'!A14 -> 0 | B126: ='Listado CAPS'!B14 -> 0 | C126: ='Listado CAPS'!C14 -> 0 | D126: ='Listado CAPS'!D14 -> L | E126: 0
A136: TOTAL | E136: =AVERAGE(E126:E135) -> 0 | G136: =IF(E136<>0,SUM(G126:G135)/E136,0) -> 0 | I136: =IF(E136<>0,SUM(I126:I135)/E136,0) -> 0 | J136: =COUNTIF(J126:J135,$Q$4) -> 0 | K136: =COUNTIF(K126:K135,$Q$4) -> 0 | L136: =COUNTIF(L126:L135,$Q$4) -> 0 | M136: =COUNTIF(M126:M135,$Q$4) -> 0 | N136: =COUNTIF(N126:N135,$Q$4) -> 0 | O136: =COUNTIF(O126:O135,$Q$4) -> 0
A137: ='Listado CAPS'!A15 -> 0 | B137: ='Listado CAPS'!B15 -> 0 | C137: ='Listado CAPS'!C15 -> 0 | D137: ='Listado CAPS'!D15 -> M | E137: 0
A147: TOTAL | E147: =AVERAGE(E137:E146) -> 0 | G147: =IF(E147<>0,SUM(G137:G146)/E147,0) -> 0 | I147: =IF(E147<>0,SUM(I137:I146)/E147,0) -> 0 | J147: =COUNTIF(J137:J146,$Q$4) -> 0 | K147: =COUNTIF(K137:K146,$Q$4) -> 0 | L147: =COUNTIF(L137:L146,$Q$4) -> 0 | M147: =COUNTIF(M137:M146,$Q$4) -> 0 | N147: =COUNTIF(N137:N146,$Q$4) -> 0 | O147: =COUNTIF(O137:O146,$Q$4) -> 0
A148: ='Listado CAPS'!A16 -> 0 | B148: ='Listado CAPS'!B16 -> 0 | C148: ='Listado CAPS'!C16 -> 0 | D148: ='Listado CAPS'!D16 -> N | E148: 0
A158: TOTAL | E158: =AVERAGE(E148:E157) -> 0 | G158: =IF(E158<>0,SUM(G148:G157)/E158,0) -> 0 | I158: =IF(E158<>0,SUM(I148:I157)/E158,0) -> 0 | J158: =COUNTIF(J148:J157,$Q$4) -> 0 | K158: =COUNTIF(K148:K157,$Q$4) -> 0 | L158: =COUNTIF(L148:L157,$Q$4) -> 0 | M158: =COUNTIF(M148:M157,$Q$4) -> 0 | N158: =COUNTIF(N148:N157,$Q$4) -> 0 | O158: =COUNTIF(O148:O157,$Q$4) -> 0
A159: ='Listado CAPS'!A17 -> 0 | B159: ='Listado CAPS'!B17 -> 0 | C159: ='Listado CAPS'!C17 -> 0 | D159: ='Listado CAPS'!D17 -> Ñ | E159: 0
A169: TOTAL | E169: =AVERAGE(E159:E168) -> 0 | G169: =IF(E169<>0,SUM(G159:G168)/E169,0) -> 0 | I169: =IF(E169<>0,SUM(I159:I168)/E169,0) -> 0 | J169: =COUNTIF(J159:J168,$Q$4) -> 0 | K169: =COUNTIF(K159:K168,$Q$4) -> 0 | L169: =COUNTIF(L159:L168,$Q$4) -> 0 | M169: =COUNTIF(M159:M168,$Q$4) -> 0 | N169: =COUNTIF(N159:N168,$Q$4) -> 0 | O169: =COUNTIF(O159:O168,$Q$4) -> 0
A170: ='Listado CAPS'!A18 -> 0 | B170: ='Listado CAPS'!B18 -> 0 | C170: ='Listado CAPS'!C18 -> 0 | D170: ='Listado CAPS'!D18 -> O | E170: 0
A180: TOTAL | E180: =AVERAGE(E170:E179) -> 0 | G180: =IF(E180<>0,SUM(G170:G179)/E180,0) -> 0 | I180: =IF(E180<>0,SUM(I170:I179)/E180,0) -> 0 | J180: =COUNTIF(J170:J179,$Q$4) -> 0 | K180: =COUNTIF(K170:K179,$Q$4) -> 0 | L180: =COUNTIF(L170:L179,$Q$4) -> 0 | M180: =COUNTIF(M170:M179,$Q$4) -> 0 | N180: =COUNTIF(N170:N179,$Q$4) -> 0 | O180: =COUNTIF(O170:O179,$Q$4) -> 0
A181: ='Listado CAPS'!A19 -> 0 | B181: ='Listado CAPS'!B19 -> 0 | C181: ='Listado CAPS'!C19 -> 0 | D181: ='Listado CAPS'!D19 -> P | E181: 0
A191: TOTAL | E191: =AVERAGE(E181:E190) -> 0 | G191: =IF(E191<>0,SUM(G181:G190)/E191,0) -> 0 | I191: =IF(E191<>0,SUM(I181:I190)/E191,0) -> 0 | J191: =COUNTIF(J181:J190,$Q$4) -> 0 | K191: =COUNTIF(K181:K190,$Q$4) -> 0 | L191: =COUNTIF(L181:L190,$Q$4) -> 0 | M191: =COUNTIF(M181:M190,$Q$4) -> 0 | N191: =COUNTIF(N181:N190,$Q$4) -> 0 | O191: =COUNTIF(O181:O190,$Q$4) -> 0
A192: ='Listado CAPS'!A20 -> 0 | B192: ='Listado CAPS'!B20 -> 0 | C192: ='Listado CAPS'!C20 -> 0 | D192: ='Listado CAPS'!D20 -> Q | E192: 0
A202: TOTAL | E202: =AVERAGE(E192:E201) -> 0 | G202: =IF(E202<>0,SUM(G192:G201)/E202,0) -> 0 | I202: =IF(E202<>0,SUM(I192:I201)/E202,0) -> 0 | J202: =COUNTIF(J192:J201,$Q$4) -> 0 | K202: =COUNTIF(K192:K201,$Q$4) -> 0 | L202: =COUNTIF(L192:L201,$Q$4) -> 0 | M202: =COUNTIF(M192:M201,$Q$4) -> 0 | N202: =COUNTIF(N192:N201,$Q$4) -> 0 | O202: =COUNTIF(O192:O201,$Q$4) -> 0
A203: ='Listado CAPS'!A21 -> 0 | B203: ='Listado CAPS'!B21 -> 0 | C203: ='Listado CAPS'!C21 -> 0 | D203: ='Listado CAPS'!D21 -> R | E203: 0
A213: TOTAL | E213: =AVERAGE(E203:E212) -> 0 | G213: =IF(E213<>0,SUM(G203:G212)/E213,0) -> 0 | I213: =IF(E213<>0,SUM(I203:I212)/E213,0) -> 0 | J213: =COUNTIF(J203:J212,$Q$4) -> 0 | K213: =COUNTIF(K203:K212,$Q$4) -> 0 | L213: =COUNTIF(L203:L212,$Q$4) -> 0 | M213: =COUNTIF(M203:M212,$Q$4) -> 0 | N213: =COUNTIF(N203:N212,$Q$4) -> 0 | O213: =COUNTIF(O203:O212,$Q$4) -> 0
A214: ='Listado CAPS'!A22 -> 0 | B214: ='Listado CAPS'!B22 -> 0 | C214: ='Listado CAPS'!C22 -> 0 | D214: ='Listado CAPS'!D22 -> S | E214: 0
A224: TOTAL | E224: =AVERAGE(E214:E223) -> 0 | G224: =IF(E224<>0,SUM(G214:G223)/E224,0) -> 0 | I224: =IF(E224<>0,SUM(I214:I223)/E224,0) -> 0 | J224: =COUNTIF(J214:J223,$Q$4) -> 0 | K224: =COUNTIF(K214:K223,$Q$4) -> 0 | L224: =COUNTIF(L214:L223,$Q$4) -> 0 | M224: =COUNTIF(M214:M223,$Q$4) -> 0 | N224: =COUNTIF(N214:N223,$Q$4) -> 0 | O224: =COUNTIF(O214:O223,$Q$4) -> 0
A225: ='Listado CAPS'!A23 -> 0 | B225: ='Listado CAPS'!B23 -> 0 | C225: ='Listado CAPS'!C23 -> 0 | D225: ='Listado CAPS'!D23 -> T | E225: 0
A235: TOTAL | E235: =AVERAGE(E225:E234) -> 0 | G235: =IF(E235<>0,SUM(G225:G234)/E235,0) -> 0 | I235: =IF(E235<>0,SUM(I225:I234)/E235,0) -> 0 | J235: =COUNTIF(J225:J234,$Q$4) -> 0 | K235: =COUNTIF(K225:K234,$Q$4) -> 0 | L235: =COUNTIF(L225:L234,$Q$4) -> 0 | M235: =COUNTIF(M225:M234,$Q$4) -> 0 | N235: =COUNTIF(N225:N234,$Q$4) -> 0 | O235: =COUNTIF(O225:O234,$Q$4) -> 0
A236: ='Listado CAPS'!A24 -> 0 | B236: ='Listado CAPS'!B24 -> 0 | C236: ='Listado CAPS'!C24 -> 0 | D236: ='Listado CAPS'!D24 -> U | E236: 0
A246: TOTAL | E246: =AVERAGE(E236:E245) -> 0 | G246: =IF(E246<>0,SUM(G236:G245)/E246,0) -> 0 | I246: =IF(E246<>0,SUM(I236:I245)/E246,0) -> 0 | J246: =COUNTIF(J236:J245,$Q$4) -> 0 | K246: =COUNTIF(K236:K245,$Q$4) -> 0 | L246: =COUNTIF(L236:L245,$Q$4) -> 0 | M246: =COUNTIF(M236:M245,$Q$4) -> 0 | N246: =COUNTIF(N236:N245,$Q$4) -> 0 | O246: =COUNTIF(O236:O245,$Q$4) -> 0
A247: ='Listado CAPS'!A25 -> 0 | B247: ='Listado CAPS'!B25 -> 0 | C247: ='Listado CAPS'!C25 -> 0 | D247: ='Listado CAPS'!D25 -> V | E247: 0
A257: TOTAL | E257: =AVERAGE(E247:E256) -> 0 | G257: =IF(E257<>0,SUM(G247:G256)/E257,0) -> 0 | I257: =IF(E257<>0,SUM(I247:I256)/E257,0) -> 0 | J257: =COUNTIF(J247:J256,$Q$4) -> 0 | K257: =COUNTIF(K247:K256,$Q$4) -> 0 | L257: =COUNTIF(L247:L256,$Q$4) -> 0 | M257: =COUNTIF(M247:M256,$Q$4) -> 0 | N257: =COUNTIF(N247:N256,$Q$4) -> 0 | O257: =COUNTIF(O247:O256,$Q$4) -> 0
A258: ='Listado CAPS'!A26 -> 0 | B258: ='Listado CAPS'!B26 -> 0 | C258: ='Listado CAPS'!C26 -> 0 | D258: ='Listado CAPS'!D26 -> W | E258: 0
A268: TOTAL | E268: =AVERAGE(E258:E267) -> 0 | G268: =IF(E268<>0,SUM(G258:G267)/E268,0) -> 0 | I268: =IF(E268<>0,SUM(I258:I267)/E268,0) -> 0 | J268: =COUNTIF(J258:J267,$Q$4) -> 0 | K268: =COUNTIF(K258:K267,$Q$4) -> 0 | L268: =COUNTIF(L258:L267,$Q$4) -> 0 | M268: =COUNTIF(M258:M267,$Q$4) -> 0 | N268: =COUNTIF(N258:N267,$Q$4) -> 0 | O268: =COUNTIF(O258:O267,$Q$4) -> 0
A269: ='Listado CAPS'!A27 -> 0 | B269: ='Listado CAPS'!B27 -> 0 | C269: ='Listado CAPS'!C27 -> 0 | D269: ='Listado CAPS'!D27 -> X | E269: 0
A279: TOTAL | E279: =AVERAGE(E269:E278) -> 0 | G279: =IF(E279<>0,SUM(G269:G278)/E279,0) -> 0 | I279: =IF(E279<>0,SUM(I269:I278)/E279,0) -> 0 | J279: =COUNTIF(J269:J278,$Q$4) -> 0 | K279: =COUNTIF(K269:K278,$Q$4) -> 0 | L279: =COUNTIF(L269:L278,$Q$4) -> 0 | M279: =COUNTIF(M269:M278,$Q$4) -> 0 | N279: =COUNTIF(N269:N278,$Q$4) -> 0 | O279: =COUNTIF(O269:O278,$Q$4) -> 0
A280: ='Listado CAPS'!A28 -> 0 | B280: ='Listado CAPS'!B28 -> 0 | C280: ='Listado CAPS'!C28 -> 0 | D280: ='Listado CAPS'!D28 -> Y | E280: 0
A290: TOTAL | E290: =AVERAGE(E280:E289) -> 0 | G290: =IF(E290<>0,SUM(G280:G289)/E290,0) -> 0 | I290: =IF(E290<>0,SUM(I280:I289)/E290,0) -> 0 | J290: =COUNTIF(J280:J289,$Q$4) -> 0 | K290: =COUNTIF(K280:K289,$Q$4) -> 0 | L290: =COUNTIF(L280:L289,$Q$4) -> 0 | M290: =COUNTIF(M280:M289,$Q$4) -> 0 | N290: =COUNTIF(N280:N289,$Q$4) -> 0 | O290: =COUNTIF(O280:O289,$Q$4) -> 0
J291: Administrativa | K291: Legal | L291: Organizativa | M291: Técnica | N291: O&T | O291: Otros
I292: TIPO DE GESTIÓN MÁS SOLICITADA | J292: =SUM(J290+J279+J268+J257+J246+J235+J224+J213+J202+J191+J180+J169+J158+J147+J136+J125+J114+J103+J92+J81+J70+J59+J48+J37+J26+J15) -> 0 | K292: =SUM(K290+K279+K268+K257+K246+K235+K224+K213+K202+K191+K180+K169+K158+K147+K136+K125+K114+K103+K92+K81+K70+K59+K48+K37+K26+K15) -> 0 | L292: =SUM(L290+L279+L268+L257+L246+L235+L224+L213+L202+L191+L180+L169+L158+L147+L136+L125+L114+L103+L92+L81+L70+L59+L48+L37+L26+L15) -> 0 | M292: =SUM(M290+M279+M268+M257+M246+M235+M224+M213+M202+M191+M180+M169+M158+M147+M136+M125+M114+M103+M92+M81+M70+M59+M48+M37+M26+M15) -> 1 | N292: =SUM(N290+N279+N268+N257+N246+N235+N224+N213+N202+N191+N180+N169+N158+N147+N136+N125+N114+N103+N92+N81+N70+N59+N48+N37+N26+N15) -> 0 | O292: =SUM(O290+O279+O268+O257+O246+O235+O224+O213+O202+O191+O180+O169+O158+O147+O136+O125+O114+O103+O92+O81+O70+O59+O48+O37+O26+O15) -> 0

Sheet RESULTADO FINAL SOSTENIBILIDAD
C1: Volver a Tabla de contenidos | J1: RESULTADO FINAL DEL ÍNDICE DE SOSTENIBILIDAD DE LOS CAPS
D2: Nota: Las celdas de los criterios (Fila 3) están linkadas a las hojas donde se encuentran los datos tomados. | H2: Instrucciones: No modifique nada de esta tabla, se autocompleta sola con los datos de las pestañas anteriores.
A3: Departamento | B3: Municipio | C3: Comunidad | D3: Microregión /Distrito | E3: CAPS | F3: Tipo de Sistema | G3: Tiempo de Conformación | H3: A.Organización | P3: C. Nivel de Servicio | W3: D.Recuperación de costes | AB3: E.Operación & Mantenimiento | AE3: F. GIRH | AP3: G.Rendición de cuentas | AW3: H.2 Estado y conservación sistema MAG | AX3: H.1 Estado y conservación sistema MABE | BE3: H.3 Estado y conservación sistema Pozos | BF3: I.Incorporaciòn del enfoque de Gènero | BI3: J.Autogestión | BJ3: Indice de Sostenibilidad MABE | BM3: Indice de Sostenibilidad MAG | BQ3: Indice de Sostenibilidad POZO
H4: nº miembros activos totales | I4: Val | J4: Legalización | K4: Participación de Mujeres en la JD | L4: Val | M4: Capacidad de convocatoria | N4: Val | O4: A | P4: C1 | Q4: C2 | R4: C3 | S4: C4 | T4: C7 | U4: C8 | V4: C | W4: D1 | X4: D3 | Y4: D4 | Z4: D5 | AA4: D | AB4: E1 | AC4: E2 | AD4: E | AE4: F1 | AF4: F2 | AG4: F3 | AH4: F4 | AI4: F5 | AJ4: F6 | AK4: F7 | AL4: F8 | AM4: F9 | AN4: F10 | AO4: F | AP4: G1 | AQ4: G2 | AR4: G3 | AS4: G4 | AT4: G5 | AU4: G6 | AV4: G | AW4: H | AX4: H1 | AY4: Val | AZ4: H2 | BA4: Val | BB4: H3 | BC4: H4 | BD4: H | BE4: H | BF4: A | BG4: B | BH4: I | BI4: Val | BJ4: 1 | BK4: 2 | BL4: 3 | BM4: 1 | BN4: 2 | BO4: 3 | BP4: INSTRUCCIONES PARA EL CALCULO DEL INDICE DE SOSTENIBILIDAD | BQ4: 1 | BR4: 2 | BS4: 3 | BU4: RESULTADOS MABE | BV4: RESULTADOS MAG | BW4: RESULTADOS OTRO
A5: ='Listado CAPS'!A3 -> Madriz | B5: ='Listado CAPS'!B3 -> Yalaguina | C5: ='Listado CAPS'!C3 -> Los Encuentros | D5: ='Listado CAPS'!C3 -> Los Encuentros | E5: ='Listado CAPS'!D3 -> Los Encuentros | F5: ='Listado CAPS'!E3 -> MAG | G5: ='Listado CAPS'!F3 -> 1 | H5: ='A.Org_CAPS'!AD16 -> 0.8 | I5: =IF(H5>=60%,1,IF(H5<4,0)) -> 1 | J5: =+' A.Legalización '!K6 -> 1 | K5: ='A.Org_CAPS'!AG16 -> 0.75 | L5: =IF(K5>=0.5,1,0) -> 1 | M5: ='A.Org_CAPS'!J16 -> 1 | N5: =IF(M5>=0.5,1,0) -> 1 | O5: =SUM(I5*0.25+J5*0.25+L5*0.25+N5*0.25) -> 1 | P5: =IF('C.Nivel de Servicio'!F6="Mejorada",1,0) -> 1 | Q5: =IF('C.Nivel de Servicio'!G6="Dentro de la vivienda",1,0) -> 1 | R5: =IF('C.Nivel de Servicio'!H6="Menos de 30 min.",1,0) -> 1 | S5: =IF('C.Nivel de Servicio'!I6="Todo el tiempo tenemos agua",1,0) -> 0 | T5: =IF('C.Nivel de Servicio'!N6="Sí",1,0) -> 1 | U5: =IF('C.Nivel de Servicio'!O6="Negativo en E. coli",1,0) -> 1 | V5: =IF('C.Nivel de Servicio'!T6="SEGURA",1,IF('C.Nivel de Servicio'!T6="BÁSICO",0.5,0)) -> 0.5 | W5: ='D.RecuperacióndeCostes'!E5 -> 1 | X5: ='D.RecuperacióndeCostes'!H5 -> 1 | Y5: ='D.RecuperacióndeCostes'!H5 -> 1 | Z5: =IF('D.RecuperacióndeCostes'!I5="<5%",1,0) -> 0 | AA5: =0.25*W5+0.25*X5+0.25*Y5+0.25*Z5 -> 0.75 | AB5: ='E.OperaciónyMantenimiento'!E5 -> 1 | AC5: ='E.OperaciónyMantenimiento'!F5 -> 1 | AD5: =AB5*AC5 -> 1 | AE5: ='F.Gestión de riesgos hídricos'!E5 -> 0 | AF5: ='F.Gestión de riesgos hídricos'!F5 -> 1 | AG5: ='F.Gestión de riesgos hídricos'!G5 -> 0 | AH5: ='F.Gestión de riesgos hídricos'!H5 -> 1 | AI5: ='F.Gestión de riesgos hídricos'!I5 -> 1 | AJ5: ='F.Gestión de riesgos hídricos'!J5 -> 1 | AK5: ='F.Gestión de riesgos hídricos'!K5 -> 0 | AL5: ='F.Gestión de riesgos hídricos'!L5 -> 0 | ... AN5: ='F.Gestión de riesgos hídricos'!N5 -> 0 | AO5: =SUM(AE5:AN5)/10 -> 0.4 | AP5: ='G.Rendición de cuentas'!E5 -> 1 | AQ5: ='G.Rendición de cuentas'!F5 -> 1 | AR5: ='G.Rendición de cuentas'!G5 -> 1 | AS5: ='G.Rendición de cuentas'!H5 -> 1 | AT5: ='G.Rendición de cuentas'!I5 -> 1 | AU5: ='G.Rendición de cuentas'!J5 -> 1 | AV5: =(AP5*0.25)+(AQ5*0.25)+(AR5*0.125)+(AS5*0.125)+(AT5*0.125)+(AU5*0.125) -> 1 | AW5: ='H.2.Estado_Conserv.MAG'!AC5 -> 0 | AX5: ='H.1.Estado_Conserv MABE'!K5 -> 4 | AY5: =IF(AX5>=3,1,0) -> 1 | AZ5: ='H.1.Estado_Conserv MABE'!R5 -> 6 | BA5: =IF(AZ5>=4,1,0) -> 1 | BB5: ='H.1.Estado_Conserv MABE'!T5 -> 0 | BC5: ='H.1.Estado_Conserv MABE'!V5 -> 0 | BD5: =(AY5*0.25)+(BA5*0.25)+(BB5*0.25)+(BC5*0.25) -> 0.5 | BE5: ='H.3.Estado_Conserv.Pozos'!AB5 -> 0 | BF5: =+'I.Genero '!H7 -> 1 | BG5: =+'I.Genero '!K7 -> 1 | BH5: =+(BF5*0.5)+(BG5*0.5) -> 1 | BI5: =IF(+'J.AutoGestionCAPS'!G15>=0.5,1,0) -> 1 | BJ5: =IF(AND($G5=$BJ$4,$F5="MABE"),((O5*'Ind.Sostenib.'!$B$5)+(V5*'Ind.Sostenib.'!$C$5)+(AA5*'Ind.Sostenib.'!$D$5)+(AD5*'Ind.Sostenib.'!$E$5)+(AO5*'Ind.Sostenib.'!$F$5)+(AV5*'Ind.Sostenib.'!$G$5)+(BD5*'Ind.Sostenib.'!$H$5)+(BH5*'Ind.Sostenib.'!$I$5)+(BI5*'Ind.Sostenib.'!$J$5))*100,"") | BK5: =IF(AND($G5=$BK$4,$F5="MABE"),((O5*'Ind.Sostenib.'!$B$6)+(V5*'Ind.Sostenib.'!$C$5)+(AA5*'Ind.Sostenib.'!$D$5)+(AD5*'Ind.Sostenib.'!$E$5)+(AO5*'Ind.Sostenib.'!$F$5)+(AV5*'Ind.Sostenib.'!$G$5)+(BD5*'Ind.Sostenib.'!$H$5)+(BH5*'Ind.Sostenib.'!$I$5)+(BI5*'Ind.Sostenib.'!$J$5))*100,"") | BL5: =IF(AND(G5=$BL$4,F5="MABE"),((O5*'Ind.Sostenib.'!$B$7)+(V5*'Ind.Sostenib.'!$C$7)+(AA5*'Ind.Sostenib.'!$D$7)+(AD5*'Ind.Sostenib.'!$E$7)+(AO5*'Ind.Sostenib.'!$F$7)+(AV5*'Ind.Sostenib.'!$G$7)+(BD5*'Ind.Sostenib.'!$H$7)+(BH5*'Ind.Sostenib.'!$I$7)+(BI5*'Ind.Sostenib.'!$J$7))*100,"") | BM5: =IF(AND(G5=$BM$4,F5="MAG"),((O5*'Ind.Sostenib.'!$B$12)+(V5*'Ind.Sostenib.'!$C$12)+(AA5*'Ind.Sostenib.'!$D$12)+(AD5*'Ind.Sostenib.'!$E$12)+(AO5*'Ind.Sostenib.'!$F$12)+(AV5*'Ind.Sostenib.'!$G$12)+(AW5*'Ind.Sostenib.'!$H$12)+(BH5*'Ind.Sostenib.'!$I$12)+(BI5*'Ind.Sostenib.'!$J$12))*100,"") -> 80.75 | BN5: =IF(AND(G5=$BN$4,F5="MAG"),((O5*'Ind.Sostenib.'!$B$13)+(V5*'Ind.Sostenib.'!$C$13)+(AA5*'Ind.Sostenib.'!$D$13)+(AD5*'Ind.Sostenib.'!$E$13)+(AO5*'Ind.Sostenib.'!$F$13)+(AV5*'Ind.Sostenib.'!$G$13)+(AW5*'Ind.Sostenib.'!$H$13)+(BH5*'Ind.Sostenib.'!$I$13)+(BI5*'Ind.Sostenib.'!$J$13))*100,"") | BO5: =IF(AND(G5=$BO$4,F5="MAG"),((O5*'Ind.Sostenib.'!$B$14)+(V5*'Ind.Sostenib.'!$C$14)+(AA5*'Ind.Sostenib.'!$D$14)+(AD5*'Ind.Sostenib.'!$E$14)+(AO5*'Ind.Sostenib.'!$F$14)+(AV5*'Ind.Sostenib.'!$G$14)+(AW5*'Ind.Sostenib.'!$H$14)+(BH5*'Ind.Sostenib.'!$I$14)+(BI5*'Ind.Sostenib.'!$J$14))*100,"") | BP5: Para el càlculo del Indice de la sostenibilidad de los sistemas se utilizará la tabla de la hoja Indic_sostenibilidad ( porcentajes según el sistema y conservación construcción),la fórmula a colocar será la suma de la ùltima columna, ejemplo la A,B,C.... H de cada medición pòr el porcentaje correspondiente segùn tabla de indicadores. Para ejemplificar: ((M6*0,15)+(T6*0,05)+(V6+0,15)+(Y6*0,15)+(AB6*0,15)+(AI6*0,15)+(AM6*0,05)+(AT6*0,10)+(AW6*0,10)+100) | BQ5: =IF(AND(G5=$BQ$4,F5<>"MAG",F5<>"MABE"),((O5*'Ind.Sostenib.'!$B$12)+(V5*'Ind.Sostenib.'!$C$12)+(AA5*'Ind.Sostenib.'!$D$12)+(AD5*'Ind.Sostenib.'!$E$12)+(AO5*'Ind.Sostenib.'!$F$12)+(AV5*'Ind.Sostenib.'!$G$12)+(BE5*'Ind.Sostenib.'!$H$12)+(BH5*'Ind.Sostenib.'!$I$12)+(BI5*'Ind.Sostenib.'!$J$12))*100,"") | BR5: =IF(AND(G5=$BR$4,F5<>"MABE",F5<>"MAG"),((O5*'Ind.Sostenib.'!$B$13)+(V5*'Ind.Sostenib.'!$C$13)+(AA5*'Ind.Sostenib.'!$D$13)+(AD5*'Ind.Sostenib.'!$E$13)+(AO5*'Ind.Sostenib.'!$F$13)+(AV5*'Ind.Sostenib.'!$G$13)+(BE5*'Ind.Sostenib.'!$H$13)+(BH5*'Ind.Sostenib.'!$I$13)+(BI5*'Ind.Sostenib.'!$J$13))*100,"") | BS5: =IF(AND(G5=$BS$4,F5<>"MAG",F5<>"MABE"),((O5*'Ind.Sostenib.'!$B$14)+(V5*'Ind.Sostenib.'!$C$14)+(AA5*'Ind.Sostenib.'!$D$14)+(AD5*'Ind.Sostenib.'!$E$14)+(AO5*'Ind.Sostenib.'!$F$14)+(AV5*'Ind.Sostenib.'!$G$14)+(BE5*'Ind.Sostenib.'!$H$14)+(BH5*'Ind.Sostenib.'!$I$14)+(BI5*'Ind.Sostenib.'!$J$14))*100,"") | BT5: CATEGORIA DE 80-100 | BU5: =AVERAGEIF(BJ5:BL30,">=80") -> #DIV/0! | BV5: =AVERAGEIF(BM5:BO30,">=80") -> 80.75 | BW5: =AVERAGEIF((BQ5:BS30),">=80") -> #DIV/0!
A6: ='Listado CAPS'!A4 -> 0 | B6: ='Listado CAPS'!B4 -> 0 | C6: ='Listado CAPS'!C4 -> 0 | E6: ='Listado CAPS'!D4 -> B | F6: ='Listado CAPS'!E4 -> 0 | G6: ='Listado CAPS'!F4 -> 0 | H6: ='A.Org_CAPS'!AD30 -> 0 | I6: =IF(H6>=60%,1,IF(H6<4,0)) -> 0 | J6: =+' A.Legalización '!K7 -> 0 | K6: ='A.Org_CAPS'!AG30 -> 0 | L6: =IF(K6>=0.5,1,0) -> 0 | M6: ='A.Org_CAPS'!J30 -> 0 | N6: =IF(M6>=0.5,1,0) -> 0 | O6: =SUM(I6*0.25+J6*0.25+L6*0.25+N6*0.25) -> 0 | P6: =IF('C.Nivel de Servicio'!F7="Mejorada",1,0) -> 0 | Q6: =IF('C.Nivel de Servicio'!G7="Dentro de la vivienda",1,0) -> 0 | R6: =IF('C.Nivel de Servicio'!H7="Menos de 30 min.",1,0) -> 0 | S6: =IF('C.Nivel de Servicio'!I7="Todo el tiempo tenemos agua",1,0) -> 0 | T6: =IF('C.Nivel de Servicio'!N7="Todo el tiempo tenemos agua",1,0) -> 0 | U6: =IF('C.Nivel de Servicio'!O7="Negativo en E. coli",1,0) -> 0 | V6: =IF('C.Nivel de Servicio'!T7="SEGURA",1,IF('C.Nivel de Servicio'!T7="BÁSICO",0.5,0)) -> 0.5 | W6: ='D.RecuperacióndeCostes'!E6 -> 0 | X6: ='D.RecuperacióndeCostes'!H6 -> 0 | Y6: ='D.RecuperacióndeCostes'!H6 -> 0 | Z6: =IF('D.RecuperacióndeCostes'!I6="<5%",1,0) -> 0 | AA6: =0.25*W6+0.25*X6+0.25*Y6+0.25*Z6 -> 0 | AB6: ='E.OperaciónyMantenimiento'!E6 -> 0 | AC6: ='E.OperaciónyMantenimiento'!F6 -> 0 | AD6: =AB6*AC6 -> 0 | AE6: ='F.Gestión de riesgos hídricos'!E6 -> 0 | AF6: ='F.Gestión de riesgos hídricos'!F6 -> 0 | AG6: ='F.Gestión de riesgos hídricos'!G6 -> 0 | AH6: ='F.Gestión de riesgos hídricos'!H6 -> 0 | AI6: ='F.Gestión de riesgos hídricos'!I6 -> 0 | AJ6: ='F.Gestión de riesgos hídricos'!J6 -> 0 | AK6: ='F.Gestión de riesgos hídricos'!K6 -> 0 | AL6: ='F.Gestión de riesgos hídricos'!L6 -> 0 | ... AN6: ='F.Gestión de riesgos hídricos'!N6 -> 0 | AO6: =SUM(AE6:AN6)/10 -> 0 | AP6: ='G.Rendición de cuentas'!E6 -> 0 | AQ6: ='G.Rendición de cuentas'!F6 -> 0 | AR6: ='G.Rendición de cuentas'!G6 -> 0 | AS6: ='G.Rendición de cuentas'!H6 -> 0 | AT6: ='G.Rendición de cuentas'!I6 -> 0 | AU6: ='G.Rendición de cuentas'!J6 -> 0 | AV6: =(AP6*0.25)+(AQ6*0.25)+(AR6*0.125)+(AS6*0.125)+(AT6*0.125)+(AU6*0.125) -> 0 | AW6: ='H.2.Estado_Conserv.MAG'!AC6 -> 0 | AX6: ='H.1.Estado_Conserv MABE'!K6 -> 0 | AY6: =IF(AX6>=3,1,0) -> 0 | AZ6: ='H.1.Estado_Conserv MABE'!R6 -> 0 | BA6: =IF(AZ6>=4,1,0) -> 0 | BB6: ='H.1.Estado_Conserv MABE'!T6 -> 0 | BC6: ='H.1.Estado_Conserv MABE'!V6 -> 0 | BD6: =(AY6*0.25)+(BA6*0.25)+(BB6*0.25)+(BC6*0.25) -> 0 | BE6: ='H.3.Estado_Conserv.Pozos'!AB6 -> 0 | BF6: =+'I.Genero '!H8 -> 0 | BG6: =+'I.Genero '!K8 -> 0 | BH6: =+(BF6*0.5)+(BG6*0.5) -> 0 | BI6: =IF(+'J.AutoGestionCAPS'!G16>=0.5,1,0) -> 0 | BJ6: =IF(AND($G6=$BJ$4,$F6="MABE"),((O6*'Ind.Sostenib.'!$B$5)+(V6*'Ind.Sostenib.'!$C$5)+(AA6*'Ind.Sostenib.'!$D$5)+(AD6*'Ind.Sostenib.'!$E$5)+(AO6*'Ind.Sostenib.'!$F$5)+(AV6*'Ind.Sostenib.'!$G$5)+(BD6*'Ind.Sostenib.'!$H$5)+(BH6*'Ind.Sostenib.'!$I$5)+(BI6*'Ind.Sostenib.'!$J$5))*100,"") | BK6: =IF(AND($G6=$BK$4,$F6="MABE"),((O6*'Ind.Sostenib.'!$B$6)+(V6*'Ind.Sostenib.'!$C$5)+(AA6*'Ind.Sostenib.'!$D$5)+(AD6*'Ind.Sostenib.'!$E$5)+(AO6*'Ind.Sostenib.'!$F$5)+(AV6*'Ind.Sostenib.'!$G$5)+(BD6*'Ind.Sostenib.'!$H$5)+(BH6*'Ind.Sostenib.'!$I$5)+(BI6*'Ind.Sostenib.'!$J$5))*100,"") | BL6: =IF(AND(G6=$BL$4,F6="MABE"),((O6*'Ind.Sostenib.'!$B$7)+(V6*'Ind.Sostenib.'!$C$7)+(AA6*'Ind.Sostenib.'!$D$7)+(AD6*'Ind.Sostenib.'!$E$7)+(AO6*'Ind.Sostenib.'!$F$7)+(AV6*'Ind.Sostenib.'!$G$7)+(BD6*'Ind.Sostenib.'!$H$7)+(BH6*'Ind.Sostenib.'!$I$7)+(BI6*'Ind.Sostenib.'!$J$7))*100,"") | BM6: =IF(AND(G6=$BM$4,F6="MAG"),((O6*'Ind.Sostenib.'!$B$12)+(V6*'Ind.Sostenib.'!$C$12)+(AA6*'Ind.Sostenib.'!$D$12)+(AD6*'Ind.Sostenib.'!$E$12)+(AO6*'Ind.Sostenib.'!$F$12)+(AV6*'Ind.Sostenib.'!$G$12)+(AW6*'Ind.Sostenib.'!$H$12)+(BH6*'Ind.Sostenib.'!$I$12)+(BI6*'Ind.Sostenib.'!$J$12))*100,"") | BN6: =IF(AND(G6=$BN$4,F6="MAG"),((O6*'Ind.Sostenib.'!$B$13)+(V6*'Ind.Sostenib.'!$C$13)+(AA6*'Ind.Sostenib.'!$D$13)+(AD6*'Ind.Sostenib.'!$E$13)+(AO6*'Ind.Sostenib.'!$F$13)+(AV6*'Ind.Sostenib.'!$G$13)+(AW6*'Ind.Sostenib.'!$H$13)+(BH6*'Ind.Sostenib.'!$I$13)+(BI6*'Ind.Sostenib.'!$J$13))*100,"") | BO6: =IF(AND(G6=$BO$4,F6="MAG"),((O6*'Ind.Sostenib.'!$B$14)+(V6*'Ind.Sostenib.'!$C$14)+(AA6*'Ind.Sostenib.'!$D$14)+(AD6*'Ind.Sostenib.'!$E$14)+(AO6*'Ind.Sostenib.'!$F$14)+(AV6*'Ind.Sostenib.'!$G$14)+(AW6*'Ind.Sostenib.'!$H$14)+(BH6*'Ind.Sostenib.'!$I$14)+(BI6*'Ind.Sostenib.'!$J$14))*100,"") | BQ6: =IF(AND(G6=$BQ$4,F6<>"MAG",F6<>"MABE"),((O6*'Ind.Sostenib.'!$B$12)+(V6*'Ind.Sostenib.'!$C$12)+(AA6*'Ind.Sostenib.'!$D$12)+(AD6*'Ind.Sostenib.'!$E$12)+(AO6*'Ind.Sostenib.'!$F$12)+(AV6*'Ind.Sostenib.'!$G$12)+(BE6*'Ind.Sostenib.'!$H$12)+(BH6*'Ind.Sostenib.'!$I$12)+(BI6*'Ind.Sostenib.'!$J$12))*100,"") | BR6: =IF(AND(G6=$BR$4,F6<>"MABE",F6<>"MAG"),((O6*'Ind.Sostenib.'!$B$13)+(V6*'Ind.Sostenib.'!$C$13)+(AA6*'Ind.Sostenib.'!$D$13)+(AD6*'Ind.Sostenib.'!$E$13)+(AO6*'Ind.Sostenib.'!$F$13)+(AV6*'Ind.Sostenib.'!$G$13)+(BE6*'Ind.Sostenib.'!$H$13)+(BH6*'Ind.Sostenib.'!$I$13)+(BI6*'Ind.Sostenib.'!$J$13))*100,"") | BS6: =IF(AND(G6=$BS$4,F6<>"MAG",F6<>"MABE"),((O6*'Ind.Sostenib.'!$B$14)+(V6*'Ind.Sostenib.'!$C$14)+(AA6*'Ind.Sostenib.'!$D$14)+(AD6*'Ind.Sostenib.'!$E$14)+(AO6*'Ind.Sostenib.'!$F$14)+(AV6*'Ind.Sostenib.'!$G$14)+(BE6*'Ind.Sostenib.'!$H$14)+(BH6*'Ind.Sostenib.'!$I$14)+(BI6*'Ind.Sostenib.'!$J$14))*100,"") | BT6: CATEGORÍA DE 50-79 | BU6: =AVERAGEIFS(BJ5:BL30,BJ5:BL30,">50",BJ5:BL30,"<=79") -> #DIV/0! | BV6: =AVERAGEIFS(BM5:BO30,BM5:BO30,">50",BM5:BO30,"<=79") -> #DIV/0! | BW6: =AVERAGEIFS(BQ5:BS30,BQ5:BS30,">50",BQ5:BS30,"<=79") -> #DIV/0!
A7: ='Listado CAPS'!A5 -> 0 | B7: ='Listado CAPS'!B5 -> 0 | C7: ='Listado CAPS'!C5 -> 0 | E7: ='Listado CAPS'!D5 -> C | F7: ='Listado CAPS'!E5 -> 0 | G7: ='Listado CAPS'!F5 -> 0 | H7: ='A.Org_CAPS'!AD44 -> 0 | I7: =IF(H7>=60%,1,IF(H7<4,0)) -> 0 | J7: =+' A.Legalización '!K8 -> 0 | K7: ='A.Org_CAPS'!AG44 -> 0 | L7: =IF(K7>=0.5,1,0) -> 0 | M7: ='A.Org_CAPS'!J44 -> 0 | N7: =IF(M7>=0.5,1,0) -> 0 | O7: =SUM(I7*0.25+J7*0.25+L7*0.25+N7*0.25) -> 0 | P7: =IF('C.Nivel de Servicio'!F8="Mejorada",1,0) -> 0 | Q7: =IF('C.Nivel de Servicio'!G8="Dentro de la vivienda",1,0) -> 0 | R7: =IF('C.Nivel de Servicio'!H8="Menos de 30 min.",1,0) -> 0 | S7: =IF('C.Nivel de Servicio'!I8="Todo el tiempo tenemos agua",1,0) -> 0 | T7: =IF('C.Nivel de Servicio'!N8="Todo el tiempo tenemos agua",1,0) -> 0 | U7: =IF('C.Nivel de Servicio'!O8="Negativo en E. coli",1,0) -> 0 | V7: =IF('C.Nivel de Servicio'!T8="SEGURA",1,IF('C.Nivel de Servicio'!T8="BÁSICO",0.5,0)) -> 0.5 | W7: ='D.RecuperacióndeCostes'!E7 -> 0 | X7: ='D.RecuperacióndeCostes'!H7 -> 0 | Y7: ='D.RecuperacióndeCostes'!H7 -> 0 | Z7: =IF('D.RecuperacióndeCostes'!I7="<5%",1,0) -> 0 | AA7: =0.25*W7+0.25*X7+0.25*Y7+0.25*Z7 -> 0 | AB7: ='E.OperaciónyMantenimiento'!E7 -> 0 | AC7: ='E.OperaciónyMantenimiento'!F7 -> 0 | AD7: =AB7*AC7 -> 0 | AE7: ='F.Gestión de riesgos hídricos'!E7 -> 0 | AF7: ='F.Gestión de riesgos hídricos'!F7 -> 0 | AG7: ='F.Gestión de riesgos hídricos'!G7 -> 0 | AH7: ='F.Gestión de riesgos hídricos'!H7 -> 0 | AI7: ='F.Gestión de riesgos hídricos'!I7 -> 0 | AJ7: ='F.Gestión de riesgos hídricos'!J7 -> 0 | AK7: ='F.Gestión de riesgos hídricos'!K7 -> 0 | AL7: ='F.Gestión de riesgos hídricos'!L7 -> 0 | ... AN7: ='F.Gestión de riesgos hídricos'!N7 -> 0 | AO7: =SUM(AE7:AN7)/10 -> 0 | AP7: ='G.Rendición de cuentas'!E7 -> 0 | AQ7: ='G.Rendición de cuentas'!F7 -> 0 | AR7: ='G.Rendición de cuentas'!G7 -> 0 | AS7: ='G.Rendición de cuentas'!H7 -> 0 | AT7: ='G.Rendición de cuentas'!I7 -> 0 | AU7: ='G.Rendición de cuentas'!J7 -> 0 | AV7: =(AP7*0.25)+(AQ7*0.25)+(AR7*0.125)+(AS7*0.125)+(AT7*0.125)+(AU7*0.125) -> 0 | AW7: ='H.2.Estado_Conserv.MAG'!AC7 -> 0 | AX7: ='H.1.Estado_Conserv MABE'!K7 -> 0 | AY7: =IF(AX7>=3,1,0) -> 0 | AZ7: ='H.1.Estado_Conserv MABE'!R7 -> 0 | BA7: =IF(AZ7>=4,1,0) -> 0 | BB7: ='H.1.Estado_Conserv MABE'!T7 -> 0 | BC7: ='H.1.Estado_Conserv MABE'!V7 -> 0 | BD7: =(AY7*0.25)+(BA7*0.25)+(BB7*0.25)+(BC7*0.25) -> 0 | BE7: ='H.3.Estado_Conserv.Pozos'!AB7 -> 0 | BF7: =+'I.Genero '!H9 -> 0 | BG7: =+'I.Genero '!K9 -> 0 | BH7: =+(BF7*0.5)+(BG7*0.5) -> 0 | BI7: =IF(+'J.AutoGestionCAPS'!G17>=0.5,1,0) -> 0 | BJ7: =IF(AND($G7=$BJ$4,$F7="MABE"),((O7*'Ind.Sostenib.'!$B$5)+(V7*'Ind.Sostenib.'!$C$5)+(AA7*'Ind.Sostenib.'!$D$5)+(AD7*'Ind.Sostenib.'!$E$5)+(AO7*'Ind.Sostenib.'!$F$5)+(AV7*'Ind.Sostenib.'!$G$5)+(BD7*'Ind.Sostenib.'!$H$5)+(BH7*'Ind.Sostenib.'!$I$5)+(BI7*'Ind.Sostenib.'!$J$5))*100,"") | BK7: =IF(AND($G7=$BK$4,$F7="MABE"),((O7*'Ind.Sostenib.'!$B$6)+(V7*'Ind.Sostenib.'!$C$5)+(AA7*'Ind.Sostenib.'!$D$5)+(AD7*'Ind.Sostenib.'!$E$5)+(AO7*'Ind.Sostenib.'!$F$5)+(AV7*'Ind.Sostenib.'!$G$5)+(BD7*'Ind.Sostenib.'!$H$5)+(BH7*'Ind.Sostenib.'!$I$5)+(BI7*'Ind.Sostenib.'!$J$5))*100,"") | BL7: =IF(AND(G7=$BL$4,F7="MABE"),((O7*'Ind.Sostenib.'!$B$7)+(V7*'Ind.Sostenib.'!$C$7)+(AA7*'Ind.Sostenib.'!$D$7)+(AD7*'Ind.Sostenib.'!$E$7)+(AO7*'Ind.Sostenib.'!$F$7)+(AV7*'Ind.Sostenib.'!$G$7)+(BD7*'Ind.Sostenib.'!$H$7)+(BH7*'Ind.Sostenib.'!$I$7)+(BI7*'Ind.Sostenib.'!$J$7))*100,"") | BM7: =IF(AND(G7=$BM$4,F7="MAG"),((O7*'Ind.Sostenib.'!$B$12)+(V7*'Ind.Sostenib.'!$C$12)+(AA7*'Ind.Sostenib.'!$D$12)+(AD7*'Ind.Sostenib.'!$E$12)+(AO7*'Ind.Sostenib.'!$F$12)+(AV7*'Ind.Sostenib.'!$G$12)+(AW7*'Ind.Sostenib.'!$H$12)+(BH7*'Ind.Sostenib.'!$I$12)+(BI7*'Ind.Sostenib.'!$J$12))*100,"") | BN7: =IF(AND(G7=$BN$4,F7="MAG"),((O7*'Ind.Sostenib.'!$B$13)+(V7*'Ind.Sostenib.'!$C$13)+(AA7*'Ind.Sostenib.'!$D$13)+(AD7*'Ind.Sostenib.'!$E$13)+(AO7*'Ind.Sostenib.'!$F$13)+(AV7*'Ind.Sostenib.'!$G$13)+(AW7*'Ind.Sostenib.'!$H$13)+(BH7*'Ind.Sostenib.'!$I$13)+(BI7*'Ind.Sostenib.'!$J$13))*100,"") | BO7: =IF(AND(G7=$BO$4,F7="MAG"),((O7*'Ind.Sostenib.'!$B$14)+(V7*'Ind.Sostenib.'!$C$14)+(AA7*'Ind.Sostenib.'!$D$14)+(AD7*'Ind.Sostenib.'!$E$14)+(AO7*'Ind.Sostenib.'!$F$14)+(AV7*'Ind.Sostenib.'!$G$14)+(AW7*'Ind.Sostenib.'!$H$14)+(BH7*'Ind.Sostenib.'!$I$14)+(BI7*'Ind.Sostenib.'!$J$14))*100,"") | BQ7: =IF(AND(G7=$BQ$4,F7<>"MAG",F7<>"MABE"),((O7*'Ind.Sostenib.'!$B$12)+(V7*'Ind.Sostenib.'!$C$12)+(AA7*'Ind.Sostenib.'!$D$12)+(AD7*'Ind.Sostenib.'!$E$12)+(AO7*'Ind.Sostenib.'!$F$12)+(AV7*'Ind.Sostenib.'!$G$12)+(BE7*'Ind.Sostenib.'!$H$12)+(BH7*'Ind.Sostenib.'!$I$12)+(BI7*'Ind.Sostenib.'!$J$12))*100,"") | BR7: =IF(AND(G7=$BR$4,F7<>"MABE",F7<>"MAG"),((O7*'Ind.Sostenib.'!$B$13)+(V7*'Ind.Sostenib.'!$C$13)+(AA7*'Ind.Sostenib.'!$D$13)+(AD7*'Ind.Sostenib.'!$E$13)+(AO7*'Ind.Sostenib.'!$F$13)+(AV7*'Ind.Sostenib.'!$G$13)+(BE7*'Ind.Sostenib.'!$H$13)+(BH7*'Ind.Sostenib.'!$I$13)+(BI7*'Ind.Sostenib.'!$J$13))*100,"") | BS7: =IF(AND(G7=$BS$4,F7<>"MAG",F7<>"MABE"),((O7*'Ind.Sostenib.'!$B$14)+(V7*'Ind.Sostenib.'!$C$14)+(AA7*'Ind.Sostenib.'!$D$14)+(AD7*'Ind.Sostenib.'!$E$14)+(AO7*'Ind.Sostenib.'!$F$14)+(AV7*'Ind.Sostenib.'!$G$14)+(BE7*'Ind.Sostenib.'!$H$14)+(BH7*'Ind.Sostenib.'!$I$14)+(BI7*'Ind.Sostenib.'!$J$14))*100,"") | BT7: CATEGORÍA DE 0-49 | BU7: =AVERAGEIF(BJ5:BL30,"<=49") -> #DIV/0! | BV7: =AVERAGEIF(BM5:BO30,"<=49") -> #DIV/0! | BW7: =AVERAGEIF(BQ5:BS30,"<=49") -> #DIV/0!
A8: ='Listado CAPS'!A6 -> 0 | B8: ='Listado CAPS'!B6 -> 0 | C8: ='Listado CAPS'!C6 -> 0 | E8: ='Listado CAPS'!D6 -> D | F8: ='Listado CAPS'!E6 -> 0 | G8: ='Listado CAPS'!F6 -> 0 | H8: ='A.Org_CAPS'!AD58 -> 0 | I8: =IF(H8>=60%,1,IF(H8<4,0)) -> 0 | J8: =+' A.Legalización '!K9 -> 0 | K8: ='A.Org_CAPS'!AG58 -> 0 | L8: =IF(K8>=0.5,1,0) -> 0 | M8: ='A.Org_CAPS'!J58 -> 0 | N8: =IF(M8>=0.5,1,0) -> 0 | O8: =SUM(I8*0.25+J8*0.25+L8*0.25+N8*0.25) -> 0 | P8: =IF('C.Nivel de Servicio'!F9="Mejorada",1,0) -> 0 | Q8: =IF('C.Nivel de Servicio'!G9="Dentro de la vivienda",1,0) -> 0 | R8: =IF('C.Nivel de Servicio'!H9="Menos de 30 min.",1,0) -> 0 | S8: =IF('C.Nivel de Servicio'!I9="Todo el tiempo tenemos agua",1,0) -> 0 | T8: =IF('C.Nivel de Servicio'!N9="Todo el tiempo tenemos agua",1,0) -> 0 | U8: =IF('C.Nivel de Servicio'!O9="Negativo en E. coli",1,0) -> 0 | V8: =IF('C.Nivel de Servicio'!T9="SEGURA",1,IF('C.Nivel de Servicio'!T9="BÁSICO",0.5,0)) -> 0.5 | W8: ='D.RecuperacióndeCostes'!E8 -> 0 | X8: ='D.RecuperacióndeCostes'!H8 -> 0 | Y8: ='D.RecuperacióndeCostes'!H8 -> 0 | Z8: =IF('D.RecuperacióndeCostes'!I8="<5%",1,0) -> 0 | AA8: =0.25*W8+0.25*X8+0.25*Y8+0.25*Z8 -> 0 | AB8: ='E.OperaciónyMantenimiento'!E8 -> 0 | AC8: ='E.OperaciónyMantenimiento'!F8 -> 0 | AD8: =AB8*AC8 -> 0 | AE8: ='F.Gestión de riesgos hídricos'!E8 -> 0 | AF8: ='F.Gestión de riesgos hídricos'!F8 -> 0 | AG8: ='F.Gestión de riesgos hídricos'!G8 -> 0 | AH8: ='F.Gestión de riesgos hídricos'!H8 -> 0 | AI8: ='F.Gestión de riesgos hídricos'!I8 -> 0 | AJ8: 0 | AK8: ='F.Gestión de riesgos hídricos'!K8 -> 0 | AL8: ='F.Gestión de riesgos hídricos'!L8 -> 0 | AM8: ='F.Gestión de riesgos hídricos'!M8 -> 0 | AN8: ='F.Gestión de riesgos hídricos'!N8 -> 0 | AO8: =SUM(AE8:AN8)/10 -> 0 | AP8: ='G.Rendición de cuentas'!E8 -> 0 | AQ8: ='G.Rendición de cuentas'!F8 -> 0 | AR8: ='G.Rendición de cuentas'!G8 -> 0 | AS8: ='G.Rendición de cuentas'!H8 -> 0 | AT8: ='G.Rendición de cuentas'!I8 -> 0 | AU8: ='G.Rendición de cuentas'!J8 -> 0 | AV8: =(AP8*0.25)+(AQ8*0.25)+(AR8*0.125)+(AS8*0.125)+(AT8*0.125)+(AU8*0.125) -> 0 | AW8: ='H.2.Estado_Conserv.MAG'!AC8 -> 0 | AX8: ='H.1.Estado_Conserv MABE'!K8 -> 0 | AY8: =IF(AX8>=3,1,0) -> 0 | AZ8: ='H.1.Estado_Conserv MABE'!R8 -> 0 | BA8: =IF(AZ8>=4,1,0) -> 0 | BB8: ='H.1.Estado_Conserv MABE'!T8 -> 0 | BC8: ='H.1.Estado_Conserv MABE'!V8 -> 0 | BD8: =(AY8*0.25)+(BA8*0.25)+(BB8*0.25)+(BC8*0.25) -> 0 | BE8: ='H.3.Estado_Conserv.Pozos'!AB8 -> 0 | BF8: =+'I.Genero '!H10 -> 0 | BG8: =+'I.Genero '!K10 -> 0 | BH8: =+(BF8*0.5)+(BG8*0.5) -> 0 | BI8: =IF(+'J.AutoGestionCAPS'!G18>=0.5,1,0) -> 0 | BJ8: =IF(AND($G8=$BJ$4,$F8="MABE"),((O8*'Ind.Sostenib.'!$B$5)+(V8*'Ind.Sostenib.'!$C$5)+(AA8*'Ind.Sostenib.'!$D$5)+(AD8*'Ind.Sostenib.'!$E$5)+(AO8*'Ind.Sostenib.'!$F$5)+(AV8*'Ind.Sostenib.'!$G$5)+(BD8*'Ind.Sostenib.'!$H$5)+(BH8*'Ind.Sostenib.'!$I$5)+(BI8*'Ind.Sostenib.'!$J$5))*100,"") | BK8: =IF(AND($G8=$BK$4,$F8="MABE"),((O8*'Ind.Sostenib.'!$B$6)+(V8*'Ind.Sostenib.'!$C$5)+(AA8*'Ind.Sostenib.'!$D$5)+(AD8*'Ind.Sostenib.'!$E$5)+(AO8*'Ind.Sostenib.'!$F$5)+(AV8*'Ind.Sostenib.'!$G$5)+(BD8*'Ind.Sostenib.'!$H$5)+(BH8*'Ind.Sostenib.'!$I$5)+(BI8*'Ind.Sostenib.'!$J$5))*100,"") | BL8: =IF(AND(G8=$BL$4,F8="MABE"),((O8*'Ind.Sostenib.'!$B$7)+(V8*'Ind.Sostenib.'!$C$7)+(AA8*'Ind.Sostenib.'!$D$7)+(AD8*'Ind.Sostenib.'!$E$7)+(AO8*'Ind.Sostenib.'!$F$7)+(AV8*'Ind.Sostenib.'!$G$7)+(BD8*'Ind.Sostenib.'!$H$7)+(BH8*'Ind.Sostenib.'!$I$7)+(BI8*'Ind.Sostenib.'!$J$7))*100,"") | BM8: =IF(AND(G8=$BM$4,F8="MAG"),((O8*'Ind.Sostenib.'!$B$12)+(V8*'Ind.Sostenib.'!$C$12)+(AA8*'Ind.Sostenib.'!$D$12)+(AD8*'Ind.Sostenib.'!$E$12)+(AO8*'Ind.Sostenib.'!$F$12)+(AV8*'Ind.Sostenib.'!$G$12)+(AW8*'Ind.Sostenib.'!$H$12)+(BH8*'Ind.Sostenib.'!$I$12)+(BI8*'Ind.Sostenib.'!$J$12))*100,"") | BN8: =IF(AND(G8=$BN$4,F8="MAG"),((O8*'Ind.Sostenib.'!$B$13)+(V8*'Ind.Sostenib.'!$C$13)+(AA8*'Ind.Sostenib.'!$D$13)+(AD8*'Ind.Sostenib.'!$E$13)+(AO8*'Ind.Sostenib.'!$F$13)+(AV8*'Ind.Sostenib.'!$G$13)+(AW8*'Ind.Sostenib.'!$H$13)+(BH8*'Ind.Sostenib.'!$I$13)+(BI8*'Ind.Sostenib.'!$J$13))*100,"") | BO8: =IF(AND(G8=$BO$4,F8="MAG"),((O8*'Ind.Sostenib.'!$B$14)+(V8*'Ind.Sostenib.'!$C$14)+(AA8*'Ind.Sostenib.'!$D$14)+(AD8*'Ind.Sostenib.'!$E$14)+(AO8*'Ind.Sostenib.'!$F$14)+(AV8*'Ind.Sostenib.'!$G$14)+(AW8*'Ind.Sostenib.'!$H$14)+(BH8*'Ind.Sostenib.'!$I$14)+(BI8*'Ind.Sostenib.'!$J$14))*100,"") | BQ8: =IF(AND(G8=$BQ$4,F8<>"MAG",F8<>"MABE"),((O8*'Ind.Sostenib.'!$B$12)+(V8*'Ind.Sostenib.'!$C$12)+(AA8*'Ind.Sostenib.'!$D$12)+(AD8*'Ind.Sostenib.'!$E$12)+(AO8*'Ind.Sostenib.'!$F$12)+(AV8*'Ind.Sostenib.'!$G$12)+(BE8*'Ind.Sostenib.'!$H$12)+(BH8*'Ind.Sostenib.'!$I$12)+(BI8*'Ind.Sostenib.'!$J$12))*100,"") | BR8: =IF(AND(G8=$BR$4,F8<>"MABE",F8<>"MAG"),((O8*'Ind.Sostenib.'!$B$13)+(V8*'Ind.Sostenib.'!$C$13)+(AA8*'Ind.Sostenib.'!$D$13)+(AD8*'Ind.Sostenib.'!$E$13)+(AO8*'Ind.Sostenib.'!$F$13)+(AV8*'Ind.Sostenib.'!$G$13)+(BE8*'Ind.Sostenib.'!$H$13)+(BH8*'Ind.Sostenib.'!$I$13)+(BI8*'Ind.Sostenib.'!$J$13))*100,"") | BS8: =IF(AND(G8=$BS$4,F8<>"MAG",F8<>"MABE"),((O8*'Ind.Sostenib.'!$B$14)+(V8*'Ind.Sostenib.'!$C$14)+(AA8*'Ind.Sostenib.'!$D$14)+(AD8*'Ind.Sostenib.'!$E$14)+(AO8*'Ind.Sostenib.'!$F$14)+(AV8*'Ind.Sostenib.'!$G$14)+(BE8*'Ind.Sostenib.'!$H$14)+(BH8*'Ind.Sostenib.'!$I$14)+(BI8*'Ind.Sostenib.'!$J$14))*100,"")
A9: ='Listado CAPS'!A7 -> 0 | B9: ='Listado CAPS'!B7 -> 0 | C9: ='Listado CAPS'!C7 -> 0 | E9: ='Listado CAPS'!D7 -> E | F9: ='Listado CAPS'!E7 -> 0 | G9: ='Listado CAPS'!F7 -> 0 | H9: ='A.Org_CAPS'!AD72 -> 0 | I9: =IF(H9>=60%,1,IF(H9<4,0)) -> 0 | J9: =+' A.Legalización '!K10 -> 0 | K9: ='A.Org_CAPS'!AG72 -> 0 | L9: =IF(K9>=0.5,1,0) -> 0 | M9: ='A.Org_CAPS'!J72 -> 0 | N9: =IF(M9>=0.5,1,0) -> 0 | O9: =SUM(I9*0.25+J9*0.25+L9*0.25+N9*0.25) -> 0 | P9: =IF('C.Nivel de Servicio'!F10="Mejorada",1,0) -> 0 | Q9: =IF('C.Nivel de Servicio'!G10="Dentro de la vivienda",1,0) -> 0 | R9: =IF('C.Nivel de Servicio'!H10="Menos de 30 min.",1,0) -> 0 | S9: =IF('C.Nivel de Servicio'!I10="Todo el tiempo tenemos agua",1,0) -> 0 | T9: =IF('C.Nivel de Servicio'!N10="Todo el tiempo tenemos agua",1,0) -> 0 | U9: =IF('C.Nivel de Servicio'!O10="Negativo en E. coli",1,0) -> 0 | V9: =IF('C.Nivel de Servicio'!T10="SEGURA",1,IF('C.Nivel de Servicio'!T10="BÁSICO",0.5,0)) -> 0.5 | W9: ='D.RecuperacióndeCostes'!E9 -> 0 | X9: ='D.RecuperacióndeCostes'!H9 -> 0 | Y9: ='D.RecuperacióndeCostes'!H9 -> 0 | Z9: =IF('D.RecuperacióndeCostes'!I9="<5%",1,0) -> 0 | AA9: =0.25*W9+0.25*X9+0.25*Y9+0.25*Z9 -> 0 | AB9: ='E.OperaciónyMantenimiento'!E9 -> 0 | AC9: ='E.OperaciónyMantenimiento'!F9 -> 0 | AD9: =AB9*AC9 -> 0 | AE9: ='F.Gestión de riesgos hídricos'!E9 -> 0 | AF9: ='F.Gestión de riesgos hídricos'!F9 -> 0 | AG9: ='F.Gestión de riesgos hídricos'!G9 -> 0 | AH9: ='F.Gestión de riesgos hídricos'!H9 -> 0 | AI9: ='F.Gestión de riesgos hídricos'!I9 -> 0 | AJ9: ='F.Gestión de riesgos hídricos'!J9 -> 0 | AK9: ='F.Gestión de riesgos hídricos'!K9 -> 0 | AL9: ='F.Gestión de riesgos hídricos'!L9 -> 0 | ... AN9: ='F.Gestión de riesgos hídricos'!N9 -> 0 | AO9: =SUM(AE9:AN9)/10 -> 0 | AP9: ='G.Rendición de cuentas'!E9 -> 0 | AQ9: ='G.Rendición de cuentas'!F9 -> 0 | AR9: ='G.Rendición de cuentas'!G9 -> 0 | AS9: ='G.Rendición de cuentas'!H9 -> 0 | AT9: ='G.Rendición de cuentas'!I9 -> 0 | AU9: ='G.Rendición de cuentas'!J9 -> 0 | AV9: =(AP9*0.25)+(AQ9*0.25)+(AR9*0.125)+(AS9*0.125)+(AT9*0.125)+(AU9*0.125) -> 0 | AW9: ='H.2.Estado_Conserv.MAG'!AC9 -> 0 | AX9: ='H.1.Estado_Conserv MABE'!K9 -> 0 | AY9: =IF(AX9>=3,1,0) -> 0 | AZ9: ='H.1.Estado_Conserv MABE'!R9 -> 0 | BA9: =IF(AZ9>=4,1,0) -> 0 | BB9: ='H.1.Estado_Conserv MABE'!T9 -> 0 | BC9: ='H.1.Estado_Conserv MABE'!V9 -> 0 | BD9: =(AY9*0.25)+(BA9*0.25)+(BB9*0.25)+(BC9*0.25) -> 0 | BE9: ='H.3.Estado_Conserv.Pozos'!AB9 -> 0 | BF9: =+'I.Genero '!H11 -> 0 | BG9: =+'I.Genero '!K11 -> 0 | BH9: =+(BF9*0.5)+(BG9*0.5) -> 0 | BI9: =IF(+'J.AutoGestionCAPS'!G19>=0.5,1,0) -> 0 | BJ9: =IF(AND($G9=$BJ$4,$F9="MABE"),((O9*'Ind.Sostenib.'!$B$5)+(V9*'Ind.Sostenib.'!$C$5)+(AA9*'Ind.Sostenib.'!$D$5)+(AD9*'Ind.Sostenib.'!$E$5)+(AO9*'Ind.Sostenib.'!$F$5)+(AV9*'Ind.Sostenib.'!$G$5)+(BD9*'Ind.Sostenib.'!$H$5)+(BH9*'Ind.Sostenib.'!$I$5)+(BI9*'Ind.Sostenib.'!$J$5))*100,"") | BK9: =IF(AND($G9=$BK$4,$F9="MABE"),((O9*'Ind.Sostenib.'!$B$6)+(V9*'Ind.Sostenib.'!$C$5)+(AA9*'Ind.Sostenib.'!$D$5)+(AD9*'Ind.Sostenib.'!$E$5)+(AO9*'Ind.Sostenib.'!$F$5)+(AV9*'Ind.Sostenib.'!$G$5)+(BD9*'Ind.Sostenib.'!$H$5)+(BH9*'Ind.Sostenib.'!$I$5)+(BI9*'Ind.Sostenib.'!$J$5))*100,"") | BL9: =IF(AND(G9=$BL$4,F9="MABE"),((O9*'Ind.Sostenib.'!$B$7)+(V9*'Ind.Sostenib.'!$C$7)+(AA9*'Ind.Sostenib.'!$D$7)+(AD9*'Ind.Sostenib.'!$E$7)+(AO9*'Ind.Sostenib.'!$F$7)+(AV9*'Ind.Sostenib.'!$G$7)+(BD9*'Ind.Sostenib.'!$H$7)+(BH9*'Ind.Sostenib.'!$I$7)+(BI9*'Ind.Sostenib.'!$J$7))*100,"") | BM9: =IF(AND(G9=$BM$4,F9="MAG"),((O9*'Ind.Sostenib.'!$B$12)+(V9*'Ind.Sostenib.'!$C$12)+(AA9*'Ind.Sostenib.'!$D$12)+(AD9*'Ind.Sostenib.'!$E$12)+(AO9*'Ind.Sostenib.'!$F$12)+(AV9*'Ind.Sostenib.'!$G$12)+(AW9*'Ind.Sostenib.'!$H$12)+(BH9*'Ind.Sostenib.'!$I$12)+(BI9*'Ind.Sostenib.'!$J$12))*100,"") | BN9: =IF(AND(G9=$BN$4,F9="MAG"),((O9*'Ind.Sostenib.'!$B$13)+(V9*'Ind.Sostenib.'!$C$13)+(AA9*'Ind.Sostenib.'!$D$13)+(AD9*'Ind.Sostenib.'!$E$13)+(AO9*'Ind.Sostenib.'!$F$13)+(AV9*'Ind.Sostenib.'!$G$13)+(AW9*'Ind.Sostenib.'!$H$13)+(BH9*'Ind.Sostenib.'!$I$13)+(BI9*'Ind.Sostenib.'!$J$13))*100,"") | BO9: =IF(AND(G9=$BO$4,F9="MAG"),((O9*'Ind.Sostenib.'!$B$14)+(V9*'Ind.Sostenib.'!$C$14)+(AA9*'Ind.Sostenib.'!$D$14)+(AD9*'Ind.Sostenib.'!$E$14)+(AO9*'Ind.Sostenib.'!$F$14)+(AV9*'Ind.Sostenib.'!$G$14)+(AW9*'Ind.Sostenib.'!$H$14)+(BH9*'Ind.Sostenib.'!$I$14)+(BI9*'Ind.Sostenib.'!$J$14))*100,"") | BQ9: =IF(AND(G9=$BQ$4,F9<>"MAG",F9<>"MABE"),((O9*'Ind.Sostenib.'!$B$12)+(V9*'Ind.Sostenib.'!$C$12)+(AA9*'Ind.Sostenib.'!$D$12)+(AD9*'Ind.Sostenib.'!$E$12)+(AO9*'Ind.Sostenib.'!$F$12)+(AV9*'Ind.Sostenib.'!$G$12)+(BE9*'Ind.Sostenib.'!$H$12)+(BH9*'Ind.Sostenib.'!$I$12)+(BI9*'Ind.Sostenib.'!$J$12))*100,"") | BR9: =IF(AND(G9=$BR$4,F9<>"MABE",F9<>"MAG"),((O9*'Ind.Sostenib.'!$B$13)+(V9*'Ind.Sostenib.'!$C$13)+(AA9*'Ind.Sostenib.'!$D$13)+(AD9*'Ind.Sostenib.'!$E$13)+(AO9*'Ind.Sostenib.'!$F$13)+(AV9*'Ind.Sostenib.'!$G$13)+(BE9*'Ind.Sostenib.'!$H$13)+(BH9*'Ind.Sostenib.'!$I$13)+(BI9*'Ind.Sostenib.'!$J$13))*100,"") | BS9: =IF(AND(G9=$BS$4,F9<>"MAG",F9<>"MABE"),((O9*'Ind.Sostenib.'!$B$14)+(V9*'Ind.Sostenib.'!$C$14)+(AA9*'Ind.Sostenib.'!$D$14)+(AD9*'Ind.Sostenib.'!$E$14)+(AO9*'Ind.Sostenib.'!$F$14)+(AV9*'Ind.Sostenib.'!$G$14)+(BE9*'Ind.Sostenib.'!$H$14)+(BH9*'Ind.Sostenib.'!$I$14)+(BI9*'Ind.Sostenib.'!$J$14))*100,"")
A10: ='Listado CAPS'!A8 -> 0 | B10: ='Listado CAPS'!B8 -> 0 | C10: ='Listado CAPS'!C8 -> 0 | E10: ='Listado CAPS'!D8 -> F | F10: ='Listado CAPS'!E8 -> 0 | G10: ='Listado CAPS'!F8 -> 0 | H10: ='A.Org_CAPS'!AD86 -> 0 | I10: =IF(H10>=60%,1,IF(H10<4,0)) -> 0 | J10: =+' A.Legalización '!K11 -> 0 | K10: ='A.Org_CAPS'!AG86 -> 0 | L10: =IF(K10>=0.5,1,0) -> 0 | M10: ='A.Org_CAPS'!J86 -> 0 | N10: =IF(M10>=0.5,1,0) -> 0 | O10: =SUM(I10*0.25+J10*0.25+L10*0.25+N10*0.25) -> 0 | P10: =IF('C.Nivel de Servicio'!F11="Mejorada",1,0) -> 0 | Q10: =IF('C.Nivel de Servicio'!G11="Dentro de la vivienda",1,0) -> 0 | R10: =IF('C.Nivel de Servicio'!H11="Menos de 30 min.",1,0) -> 0 | S10: =IF('C.Nivel de Servicio'!I11="Todo el tiempo tenemos agua",1,0) -> 0 | T10: =IF('C.Nivel de Servicio'!N11="Todo el tiempo tenemos agua",1,0) -> 0 | U10: =IF('C.Nivel de Servicio'!O11="Negativo en E. coli",1,0) -> 0 | V10: =IF('C.Nivel de Servicio'!T11="SEGURA",1,IF('C.Nivel de Servicio'!T11="BÁSICO",0.5,0)) -> 0.5 | W10: ='D.RecuperacióndeCostes'!E10 -> 0 | X10: ='D.RecuperacióndeCostes'!H10 -> 0 | Y10: ='D.RecuperacióndeCostes'!H10 -> 0 | Z10: =IF('D.RecuperacióndeCostes'!I10="<5%",1,0) -> 0 | AA10: =0.25*W10+0.25*X10+0.25*Y10+0.25*Z10 -> 0 | AB10: ='E.OperaciónyMantenimiento'!E10 -> 0 | AC10: ='E.OperaciónyMantenimiento'!F10 -> 0 | AD10: =AB10*AC10 -> 0 | AE10: ='F.Gestión de riesgos hídricos'!E10 -> 0 | AF10: ='F.Gestión de riesgos hídricos'!F10 -> 0 | AG10: ='F.Gestión de riesgos hídricos'!G10 -> 0 | AH10: ='F.Gestión de riesgos hídricos'!H10 -> 0 | AI10: ='F.Gestión de riesgos hídricos'!I10 -> 0 | AJ10: ='F.Gestión de riesgos hídricos'!J10 -> 0 | AK10: ='F.Gestión de riesgos hídricos'!K10 -> 0 | AL10: ='F.Gestión de riesgos hídricos'!L10 -> 0 | ... AN10: ='F.Gestión de riesgos hídricos'!N10 -> 0 | AO10: =SUM(AE10:AN10)/10 -> 0 | AP10: ='G.Rendición de cuentas'!E10 -> 0 | AQ10: ='G.Rendición de cuentas'!F10 -> 0 | AR10: ='G.Rendición de cuentas'!G10 -> 0 | AS10: ='G.Rendición de cuentas'!H10 -> 0 | AT10: ='G.Rendición de cuentas'!I10 -> 0 | AU10: ='G.Rendición de cuentas'!J10 -> 0 | AV10: =(AP10*0.25)+(AQ10*0.25)+(AR10*0.125)+(AS10*0.125)+(AT10*0.125)+(AU10*0.125) -> 0 | AW10: ='H.2.Estado_Conserv.MAG'!AC10 -> 0 | AX10: ='H.1.Estado_Conserv MABE'!K10 -> 0 | AY10: =IF(AX10>=3,1,0) -> 0 | AZ10: ='H.1.Estado_Conserv MABE'!R10 -> 0 | BA10: =IF(AZ10>=4,1,0) -> 0 | BB10: ='H.1.Estado_Conserv MABE'!T10 -> 0 | BC10: ='H.1.Estado_Conserv MABE'!V10 -> 0 | BD10: =(AY10*0.25)+(BA10*0.25)+(BB10*0.25)+(BC10*0.25) -> 0 | BE10: ='H.3.Estado_Conserv.Pozos'!AB10 -> 0 | BF10: =+'I.Genero '!H12 -> 0 | BG10: =+'I.Genero '!K12 -> 0 | BH10: =+(BF10*0.5)+(BG10*0.5) -> 0 | BI10: =IF(+'J.AutoGestionCAPS'!G20>=0.5,1,0) -> 0 | BJ10: =IF(AND($G10=$BJ$4,$F10="MABE"),((O10*'Ind.Sostenib.'!$B$5)+(V10*'Ind.Sostenib.'!$C$5)+(AA10*'Ind.Sostenib.'!$D$5)+(AD10*'Ind.Sostenib.'!$E$5)+(AO10*'Ind.Sostenib.'!$F$5)+(AV10*'Ind.Sostenib.'!$G$5)+(BD10*'Ind.Sostenib.'!$H$5)+(BH10*'Ind.Sostenib.'!$I$5)+(BI10*'Ind.Sostenib.'!$J$5))*100,"") | BK10: =IF(AND($G10=$BK$4,$F10="MABE"),((O10*'Ind.Sostenib.'!$B$6)+(V10*'Ind.Sostenib.'!$C$5)+(AA10*'Ind.Sostenib.'!$D$5)+(AD10*'Ind.Sostenib.'!$E$5)+(AO10*'Ind.Sostenib.'!$F$5)+(AV10*'Ind.Sostenib.'!$G$5)+(BD10*'Ind.Sostenib.'!$H$5)+(BH10*'Ind.Sostenib.'!$I$5)+(BI10*'Ind.Sostenib.'!$J$5))*100,"") | BL10: =IF(AND(G10=$BL$4,F10="MABE"),((O10*'Ind.Sostenib.'!$B$7)+(V10*'Ind.Sostenib.'!$C$7)+(AA10*'Ind.Sostenib.'!$D$7)+(AD10*'Ind.Sostenib.'!$E$7)+(AO10*'Ind.Sostenib.'!$F$7)+(AV10*'Ind.Sostenib.'!$G$7)+(BD10*'Ind.Sostenib.'!$H$7)+(BH10*'Ind.Sostenib.'!$I$7)+(BI10*'Ind.Sostenib.'!$J$7))*100,"") | BM10: =IF(AND(G10=$BM$4,F10="MAG"),((O10*'Ind.Sostenib.'!$B$12)+(V10*'Ind.Sostenib.'!$C$12)+(AA10*'Ind.Sostenib.'!$D$12)+(AD10*'Ind.Sostenib.'!$E$12)+(AO10*'Ind.Sostenib.'!$F$12)+(AV10*'Ind.Sostenib.'!$G$12)+(AW10*'Ind.Sostenib.'!$H$12)+(BH10*'Ind.Sostenib.'!$I$12)+(BI10*'Ind.Sostenib.'!$J$12))*100,"") | BN10: =IF(AND(G10=$BN$4,F10="MAG"),((O10*'Ind.Sostenib.'!$B$13)+(V10*'Ind.Sostenib.'!$C$13)+(AA10*'Ind.Sostenib.'!$D$13)+(AD10*'Ind.Sostenib.'!$E$13)+(AO10*'Ind.Sostenib.'!$F$13)+(AV10*'Ind.Sostenib.'!$G$13)+(AW10*'Ind.Sostenib.'!$H$13)+(BH10*'Ind.Sostenib.'!$I$13)+(BI10*'Ind.Sostenib.'!$J$13))*100,"") | BO10: =IF(AND(G10=$BO$4,F10="MAG"),((O10*'Ind.Sostenib.'!$B$14)+(V10*'Ind.Sostenib.'!$C$14)+(AA10*'Ind.Sostenib.'!$D$14)+(AD10*'Ind.Sostenib.'!$E$14)+(AO10*'Ind.Sostenib.'!$F$14)+(AV10*'Ind.Sostenib.'!$G$14)+(AW10*'Ind.Sostenib.'!$H$14)+(BH10*'Ind.Sostenib.'!$I$14)+(BI10*'Ind.Sostenib.'!$J$14))*100,"") | BQ10: =IF(AND(G10=$BQ$4,F10<>"MAG",F10<>"MABE"),((O10*'Ind.Sostenib.'!$B$12)+(V10*'Ind.Sostenib.'!$C$12)+(AA10*'Ind.Sostenib.'!$D$12)+(AD10*'Ind.Sostenib.'!$E$12)+(AO10*'Ind.Sostenib.'!$F$12)+(AV10*'Ind.Sostenib.'!$G$12)+(BE10*'Ind.Sostenib.'!$H$12)+(BH10*'Ind.Sostenib.'!$I$12)+(BI10*'Ind.Sostenib.'!$J$12))*100,"") | BR10: =IF(AND(G10=$BR$4,F10<>"MABE",F10<>"MAG"),((O10*'Ind.Sostenib.'!$B$13)+(V10*'Ind.Sostenib.'!$C$13)+(AA10*'Ind.Sostenib.'!$D$13)+(AD10*'Ind.Sostenib.'!$E$13)+(AO10*'Ind.Sostenib.'!$F$13)+(AV10*'Ind.Sostenib.'!$G$13)+(BE10*'Ind.Sostenib.'!$H$13)+(BH10*'Ind.Sostenib.'!$I$13)+(BI10*'Ind.Sostenib.'!$J$13))*100,"") | BS10: =IF(AND(G10=$BS$4,F10<>"MAG",F10<>"MABE"),((O10*'Ind.Sostenib.'!$B$14)+(V10*'Ind.Sostenib.'!$C$14)+(AA10*'Ind.Sostenib.'!$D$14)+(AD10*'Ind.Sostenib.'!$E$14)+(AO10*'Ind.Sostenib.'!$F$14)+(AV10*'Ind.Sostenib.'!$G$14)+(BE10*'Ind.Sostenib.'!$H$14)+(BH10*'Ind.Sostenib.'!$I$14)+(BI10*'Ind.Sostenib.'!$J$14))*100,"")
